Workbook
Name area_vis_lv2: Constraint!$E$21
Name area_vis_lv21: Constraint!$F$21
Name area_vis_lv3: Constraint!$F$22
Name areavisend: [1]Constants!$F$20
Name areavisend: [1]Constants!$F$20
Name areavisend: [1]Constants!$F$20
Name areavisend: [1]Constants!$F$20
Name areavisend: [2]Constants!$F$20
Name areavislv2: [1]Constants!$F$19
Name areavislv2: [1]Constants!$F$19
Name areavislv2: [1]Constants!$F$19
Name areavislv2: [1]Constants!$F$19
Name areavislv2: Constraint!$F$21
Name areavislv3: [1]Constants!$F$21
Name areavislv3: [1]Constants!$F$21
Name areavislv3: [1]Constants!$F$21
Name areavislv3: [1]Constants!$F$21
Name areavislv3: [2]Constants!$F$21
Name distviscodeend: [1]Constants!$F$24
Name distviscodeend: [1]Constants!$F$24
Name distviscodeend: [1]Constants!$F$24
Name distviscodeend: [1]Constants!$F$24
Name distviscodeend: [2]Constants!$F$24
Name distviscodeendend: [1]Constants!$F$25
Name distviscodeendend: [1]Constants!$F$25
Name distviscodeendend: [1]Constants!$F$25
Name distviscodeendend: [1]Constants!$F$25
Name distviscodeendend: [2]Constants!$F$25
Name distviscodestart: [1]Constants!$F$23
Name distviscodestart: [1]Constants!$F$23
Name distviscodestart: [1]Constants!$F$23
Name distviscodestart: [1]Constants!$F$23
Name distviscodestart: [2]Constants!$F$23
Name distvisor: [1]Constants!$F$22
Name distvisor: [1]Constants!$F$22
Name distvisor: [1]Constants!$F$22
Name distvisor: [1]Constants!$F$22
Name distvisor: [2]Constants!$F$22
Name EndLV4: Constraint!$F$23
Name listend: [1]Constants!$F$6
Name listend: [1]Constants!$F$6
Name listend: [1]Constants!$F$6
Name listend: [1]Constants!$F$6
Name listend: Constraint!$F$6
Name listla: [1]Constants!$F$5
Name listla: [1]Constants!$F$5
Name listla: [1]Constants!$F$5
Name listla: [1]Constants!$F$5
Name listla: Constraint!$F$5
Name listlareport: [1]Constants!$F$4
Name listlareport: [1]Constants!$F$4
Name listlareport: [1]Constants!$F$4
Name listlareport: [1]Constants!$F$4
Name listlareport: Constraint!$F$4
Name listlat: Constraint!$F$5
Name liststart: [1]Constants!$F$3
Name liststart: [1]Constants!$F$3
Name liststart: [1]Constants!$F$3
Name liststart: [1]Constants!$F$3
Name liststart: Constraint!$F$3

Sheet Instructions
L2: Created
L3: Last Reviewed JTI
L4: Last Reviewed CSD
B6: 1. This is a working document stored in the cloud for JTI-NBE core questionnaire for the Trade Census
B7: 2. All latest changes, agreements will be captured and tracked in this central document
B8: 3. This will be the base for the programing of the core questionnaire
B10: The template is divided in sections that you will find back in the questionnaire. Color Coding Bellow.
B12: In every section there are columns for questions / comments / observation at then end (CSD/Dev Team) Cells highlighted in yellow require attention / answer
C14: System or instructions sections
C15: Survey Sections
C16: Tables of lists, SKU, market customizable sections
C17: System rules (Anomalies, Rejections, Field Back Checks…)
C18: Current Template Used for
C19: Qualitative follow-up questionnaire for Consummer & Custommer Insight & Distributor Deep Dive
B21: Overall Open Topics / Questions
B22: For specific questions on survey areas please use the specified column for this in the relevant section
B23: Question | F23: Status | G23: Response

Sheet Profile
I1: QUESTIONS
A2: ID | B2: Visibility rule | C2: QUESTION WORDING EN | D2: Reporting LABEL | E2: ANSWER TYPE | F2: ANSWER OPTIONS | G2: NOTES SYSTEM | H2: NOTES REPORTING | I2: CSD | J2: Dev-team | K2: Dev-team
A3: Section
A4: P-10 | C4: Surname | D4: =A4&" "&C4 -> P-10 Surname | E4: TEXT | F4: Automatic | G4: From the back office setup
A5: P-20 | C5: Name | D5: =A5&" "&C5 -> P-20 Name | E5: TEXT | F5: Automatic | H5: Use in Field Management Dashboard
A6: P-30 | C6: Enumerator Code | D6: =A6&" "&C6 -> P-30 Enumerator Code | E6: NUMERIC | F6: Automatic | H6: Use in Field Management Dashboard
A7: P-40 | C7: Supervisor Code | D7: =A7&" "&C7 -> P-40 Supervisor Code | E7: NUMERIC | F7: Automatic | H7: Use in Field Management Dashboard
A8: P-50 | C8: Date | D8: =A8&" "&C8 -> P-50 Date | E8: NUMERIC | G8: System - Automatic | H8: Use in Field Management Dashboard
A9: P-60 | C9: Telephone number | D9: =A9&" "&C9 -> P-60 Telephone number | E9: NUMERIC | F9: Automatic
A10: P-70 | C10: Time stamp START Interview | D10: P-70 Interview Start | E10: NUMERIC | F10: Automatic | G10: System - Automatic | H10: Important for measurement of quality of work

Sheet Obs
A1: ID | B1: Observation | C1: Included in JSON | D1: Needs to be modified in JSON
A2: Area
A3: A-10 | B3: Province is asked in the next section, this question should ask for the city | C3: YES | D3: NO
A4: A-20 | C4: YES | D4: NO
A5: A-30 | B5: Used to say Barangay, now Kecamatan, which is the administrative division name for Inodnesia | C5: YES | D5: YES
A6: Need to move quesiton O-30 to this section
A7: Outlet Details
A8: O-10 | C8: YES | D8: NO
A9: O-20 | C9: YES | D9: NO
A10: O-30 | B10: Falls in their scope of work | C10: NO | D10: YES
A11: O-40 | C11: YES | D11: NO
A12: O-50 | B12: Evaluate how important or if the enumerated area its valid in Indonesia | C12: YES | D12: MAYBE
A13: O-60 | B13: Falls in their scope of work | C13: NO | D13: YES
A14: O-70 | B14: Asks for the complete address of the Outlet, unnecessary, all the info required is asked question by question | C14: NO | D14: NO
A15: O-80 | B15: Included in their scope, but asked in the area part | C15: NO | D15: NO
A16: No ID yet | B16: RT/RW (Rukun Warga=Village, RT=Neighborhoods?) reffering to a more detailed description of the administrative areas of Indonesia, unnecessary | C16: NO | D16: NO
A17: No ID yet | B17: Number, reffers to phone number? not sure what they mean by that, unncessary | C17: NO | D17: NO
A18: No ID yet | B18: Postal Code not in scope, unnecessary | C18: NO | D18: NO
A19: O-90 | B19: Falls in their scope of work | C19: NO | D19: YES
A20: Additional comment | B20: "Insert outlet's phone number (1. Landline first before mobile)" Guess he reffers to ask for two phone numbers, not sure why?, unnecessary, maybe just ask for one or the other
A21: Interview Start
A22: I-10 | C22: YES | D22: YES
A23: I-20 | B23: Changed the order of questions? First giving the I-40 Should ask for the person who's being interviewed | C23: YES | D23: NO
A24: I-30 | B24: Changed the order of questions? Here should be the introduction | C24: YES | D24: NO
A25: I-31 | B25: Missing this part of the intro, check the part of the company's name | C25: YES | D25: YES
A26: I-40 | B26: Missing | C26: YES | D26: NO
A27: I-50 | B27: Hidden previously, might need to be change to "liquour" so it falls in scope | C27: NO | D27: YES
A28: I-60 | B28: Hidden previously, falls in scope | C28: NO | D28: YES
A29: I-70 | B29: Hidden previously, falls in scope | C29: NO | D29: YES
A30: I-80 | B30: Hidden previously, falls in scope | C30: NO | D30: YES
A31: I-90 | B31: Erased by user | C31: YES | D31: NO
A32: I-100 | B32: Falls in their scope of work, but need to verify the classification | C32: NO | D32: YES
A33: I-110 | B33: Hidden before, but might be unnecessary as already asked in Outlet details | C33: YES | D33: MAYBE
A34: I-120 | B34: Hidden before | C34: YES | D34: NO
... A41: I-139 | B41: Erased by user | C41: YES | D41: NO
A42: (Retail)Marketing
A43: M-1 | C43: YES | D43: NO
A44: M-101 | B44: Moved from one section to the next
A45: M-10 | C45: YES | D45: NO
A46: M-20 | B46: Falls into scope, needs to be added | C46: NO | D46: YES
A47: M-21 | B47: Need to be reviewed | C47: YES | D47: NO
A48: M-22 | B48: Falls into scope, but list of brands of FRIDGES needs to be established | C48: NO | D48: YES
A49: M-23 | B49: Not into scope, might be unnecessary | C49: NO | D49: YES
A50: M-30 | B50: Changed the wording… but same thing asked | C50: NO | D50: YES
A51: M-31 | B51: Falls into scope, but feels unnecessary | C51: NO | D51: YES
A52: M-40 | B52: Taken out for previous surveys | C52: NO | D52: YES
A53: M-50 | B53: Taken out for previous surveys | C53: NO | D53: YES
A54: M-60 | B54: Taken out for previous surveys | C54: NO | D54: YES
A55: M-71 | C55: YES | D55: NO
A56: M-72 | B56: Not in scope, not necessary | C56: NO | D56: NO
A57: M-80 | C57: YES | D57: NO
A58: M-90 | C58: YES | D58: NO
A59: M-100 | C59: YES | D59: YES
A60: Wholesaler page gone… wont be included?
A61: Volume & Price
A62: V-10 | B62: Used to say soft drinks (non-alcoholic in JSON), but carbonate its the wording used in their scope | C62: YES | D62: YES
A63: V-20 | B63: Used to say international spirits (spirits JSON), but changed to liquour as in scope | C63: YES | D63: YES
A64: V-21 | C64: YES | D64: NO
A65: V-50 | B65: Erased by user | C65: YES | D65: YES
A66: V-60 | C66: YES | D66: YES
A67: V-61 | C67: YES | D67: YES
A68: V-80 | C68: YES | D68: YES
A69: V-81 | C69: YES | D69: YES
A70: V-90 | C70: YES | D70: YES
A71: V-91 | B71: Erased by user | C71: YES | D71: YES
A72: Distribution
A73: D-5 | B73: Not included in the excel files, but appears on JSON, in scope | C73: YES | D73: YES
A74: D-6 | B74: Not included in the excel files, but appears on JSON, in scope | C74: YES | D74: YES
A75: D-10 | B75: Need to mention the brand of beer | C75: YES | D75: YES
A76: D-11 | B76: Erased by user | C76: YES | D76: YES
A77: D-12 | B77: Unnecessary, already asked | C77: NO | D77: NO
A78: D-13 | B78: Unnecessary, already asked | C78: NO | D78: NO
A79: D-20 to D-41 | B79: Missing, reffer to different brands of soft drinks, might | C79: YES | D79: YES
A80: D-50 | B80: Wording different to JSON, need to align | C80: YES | D80: YES
A81: D-55 | B81: Appears only in JSON, not in scope | C81: YES | D81: NO
A82: D-60 | B82: Falls in scope | C82: NO | D82: YES
A83: D-65 | B83: Only appears on JSON, not in scope | C83: YES | D83: YES
A84: D-70 | B84: Previously hidden, Not in scope or JSON, need to discuss its inclusion | C84: NO | D84: YES
... A87: D-90 | B87: Changed wording to place an order instead of delivered | C87: YES | D87: YES
A88: D-100 | C88: YES | D88: YES
A89: D-106 | B89: Unnecessary, already asked later by sales rep depending on company name | C89: NO | D89: NO
A90: D-107 onwards | B90: Questions fall in scope, but need to align name of distributors and amount of different names to be included | C90: YES | D90: YES
A91: End
A92: E-10 | C92: YES | D92: NO
A93: E-20 | C93: YES | D93: NO
A94: E-21 | C94: YES | D94: NO
A95: E-22 | C95: YES | D95: NO
A96: E-40 | C96: YES | D96: NO
A97: E-50 | C97: YES | D97: NO
A98: E-60 | C98: YES | D98: NO
A99: E-70 | C99: YES | D99: NO
A100: E-85 | B100: These questions were moved to the Interview start and outlet details | C100: YES | D100: YES
A101: E-90 | C101: YES | D101: YES
A102: E-110 | C102: YES | D102: YES

Sheet Area
A1: Question fields | G1: Answer fields | J1: Backoffice | M1: Comments
A2: ID | B2: Visibility rule | C2: QUESTION WORDING EN | D2: QUESTION WORDING FRENCH | E2: Wording change | F2: Question Priority 1 Keep 0 Discuss -1 remove ? | G2: Reporting LABEL | H2: ANSWER TYPE | I2: ANSWER OPTIONS | J2: Visible ENUMERATOR | K2: VISIBLE BC | L2: PREFILLED FOR BC | M2: ___ | N2: CSD | O2: Dev-team
A3: Section | D3: Dans quelle region se trouve le point de vente ? | F3: 1 | G3: A-10 Region | H3: SINGLE SELECTION
A4: A-10 | C4: What region are you located? | D4: Dans quelle region se trouve le point de vente ? | F4: 1 | G4: A-10 Region | H4: SINGLE SELECTION | I4: Region | J4: Yes | K4: Yes | L4: Yes
A5: A-20 | C5: What prefecture are you located? | D5: Dans quel département se trouve le point de vente ? | F5: 1 | G5: A-20 Prefecture | H5: SINGLE SELECTION | I5: Prefecture | J5: Yes | K5: Yes | L5: Yes
A6: A-30 | C6: What sub-prefecture/commune are you located? | D6: Dans quelle commune se trouve le point de vente ? | F6: 1 | G6: A-30 Sub-prefecture/Commune | H6: SINGLE SELECTION | I6: Sub-prefecture/Commune | J6: Yes | K6: Yes | L6: Yes
A7: A-40 | C7: What quartier are you located? | D7: Dans quel quartier se trouve le point de vente ? | F7: 1 | G7: A-40 Suburb | H7: SINGLE SELECTION | I7: Store Location Type | J7: Yes | K7: Yes | L7: Yes
A8: A-50 | C8: What is the block code? | F8: -1 | G8: A-50 Block | H8: SINGLE SELECTION | I8: Open text field | J8: Yes | K8: Yes | L8: Yes
A9: A-60 | C9: What is the sub-block code? | F9: -1 | G9: A-60 Subbolck | H9: SINGLE SELECTION | I9: Open text field | J9: Yes | K9: Yes | L9: Yes
A10: A-70 | C10: What is the Zip Code (Code postal)? | F10: 1 | G10: A-70 Zipcode | H10: SINGLE SELECTION | I10: Open text field | J10: Yes | K10: Yes | L10: Yes

Sheet Outlet details
A1: Question fields | G1: Answer fields | J1: Backoffice | M1: Comments
A2: ID | B2: Visibility rule | C2: QUESTION WORDING EN | D2: QUESTION WORDING FRENCH | E2: Wording change | F2: Question Priority 1 Keep 0 Discuss -1 remove ? | G2: Reporting LABEL | H2: ANSWER TYPE | I2: ANSWER OPTIONS | J2: Visible ENUMERATOR | K2: VISIBLE BC | L2: PREFILLED FOR BC | M2: ___ | N2: CSD | O2: Dev-team
A3: Section
A4: O-10 | C4: GPS location of outlet | D4: Coordonnées GPS du point de vente | F4: 1 | G4: O-10 GPS | H4: SYSTEM | I4: Device automatically captures | J4: Yes | K4: Yes | L4: Yes
A5: O-40 | C5: What is the address/landmark point that identifies the outlet? (e.g. NEAR THIS... NEXT TO... BEHIND THIS...) | D5: Quel est l'adresse / le point de repere du point de vente ? (A côté de …, après …, derrière ….) | F5: 1 | G5: O-40 Landmark | H5: TEXT | I5: Open verbatim field | J5: Yes | K5: Yes | L5: Yes
A6: O-41 | C6: What is the Street Name? | D6: Quel est le nom de la rue où se trouve le point de vente ? | F6: 1 | G6: O-41 Street | H6: TEXT | I6: Open verbatim field | J6: Yes | K6: Yes | L6: Yes
A7: O-42 | C7: What is the Building No? | D7: Quel est le numéro du batiment où se trouve le point de vente ? | F7: -1 | G7: O-42 Bldg no | H7: TEXT | I7: Open verbatim field | J7: Yes | K7: Yes | L7: Yes
A8: O-43 | C8: What is the Shop No? | D8: Quel est le numéro du point de vente ? | F8: -1 | G8: O-43 Shop no | H8: TEXT | I8: Open verbatim field | J8: Yes | K8: Yes | L8: Yes
A9: O-50 | C9: What is the Enumerated Area you are in? | F9: -1 | G9: O-50 EA | H9: TEXT | I9: Open verbatim field | J9: Yes | K9: Yes | L9: Yes
A10: O-60 | C10: What is the name of the outlet? | D10: Quel est le Nom du point de vente ? | F10: 1 | G10: O-60 Outlet Name | H10: TEXT | I10: Open verbatim field | J10: Yes | K10: Yes | L10: Yes
A11: O-61 | C11: What other name is this outlet known by? | D11: Quel autre Nom designe le point de vente ? | F11: 1 | G11: O-61 Addional Name | H11: TEXT | J11: Yes | K11: Yes | L11: Yes

Sheet Interview Start
A1: Question fields | G1: Answer fields | J1: Backoffice | M1: Comments
A2: ID | B2: Visibility rule | C2: QUESTION WORDING EN | D2: QUESTION WORDING FRENCH | E2: Wording change | F2: Question Priority 1 Keep 0 Discuss -1 remove ? | G2: Reporting LABEL | H2: ANSWER TYPE | I2: ANSWER OPTIONS | J2: Visible ENUMERATOR | K2: VISIBLE BC | L2: PREFILLED FOR BC | M2: ___ | N2: CSD | O2: Dev-team
A3: Section
A4: I-10 | C4: Find the most senior person available (Manager or Owner) | D4: Trouver la personne la plus expérimentée disponible (gérant ou propriétaire) | F4: 1 | G4: I-10 Note | H4: NOTE | J4: Yes | K4: Yes | L4: No
A5: I-20 | C5: Who are you speaking to? | D5: A qui parlez-vous ? | F5: 1 | G5: I-20 Interviewee Role | H5: SINGLE SELECTION | I5: Interviewee Roles | J5: Yes | K5: Yes | L5: Yes
A6: I-30 | C6: INTRODUCTION: My name is .… Our company is operating a Trade Census. The objective is to better understand the tobacco market to eventually improve service to you as point of sale. | D6: INTRODUCTION : Je m'appelle .… Notre société procède à un recensement commercial. L'objectif est de mieux comprendre le marché du tabac pour éventuellement améliorer le service qui vous est offert en tant que point de vente. | F6: 1 | G6: I-30 Note | H6: NOTE | J6: Yes | K6: Yes | L6: No
A7: I-31 | C7: A colleague of mine has recently visited you to conduct a Trade Census, and to insure we have quality information I am checking that we have correctly captured the information about your point of sale. I will be asking you a select number of questions for quality purposes. | D7: Un de mes collègues vous a récemment rendu visite pour effectuer un recensement commercial, et pour nous assurer que nous avons des informations de qualité, je vérifie que nous avons correctement saisi les informations sur votre point de vente. Je vais vous poser un certain nombre de questions à des fins de qualité. | F7: 1 | G7: I-31 Note | H7: NOTE | J7: No | K7: Yes | L7: No
A8: I-40 | C8: Would you have a few minutes available to answer some questions about your business? This should not take long. | D8: Auriez-vous quelques minutes à disposition pour répondre à quelques questions sur votre entreprise ? Cela ne devrait pas prendre longtemps. | F8: 1 | G8: I-40 Survey Compleness | H8: SINGLE SELECTION | I8: Continue Survey | J8: Yes | K8: Yes | L8: No
A9: NEW PAGE
A10: I-130 | C10: Are most (over 50%) of your sales to: | D10: Dans la plupart des cas (plus de 50 %) de vos ventes sont : | F10: 1 | G10: I-130 Segment | H10: SINGLE SELECTION | I10: Segment Options | J10: Yes | K10: Yes | L10: No
A11: I-134 | C11: Do you sell Cigarettes ? | F11: 1 | G11: I-134 Sell Cigarette | H11: SINGLE SELECTION | I11: Yes/No | J11: Yes | K11: Yes | L11: No | N11: If no, go to end section
A12: I-131 | B12: I-130 = "SEG1" | C12: Select the retailer channel | D12: Selectionnez le canal du détaillant | F12: 1 | G12: I-131 Retailer Channel | H12: SINGLE SELECTION | I12: Retailer Channels | J12: Yes | K12: Yes | L12: No
A13: I-132 | B13: I-130 = 2 (OFF TRADE) | C13: Select the Off-Trade channel | F13: -1 | G13: I-132 OFF Channel | H13: SINGLE SELECTION | I13: OFF Channels | J13: Yes | K13: Yes | L13: No
A14: I-133 | B14: I-130 = "SEG1" | C14: Select the wholesaler channel | D14: Selectionnez le type du grossiste | F14: 1 | G14: I-133 Wholesaler Channel | H14: SINGLE SELECTION | I14: Wholesaler Channels | J14: Yes | K14: Yes | L14: No
A15: I-1351 | B15: I-130 = "SEG1" | C15: Are you also distributing to other retailer ? | D15: Vendez-vous aux autres points de vente ? | F15: 1 | G15: I-1351 Outlet Retailer | H15: SINGLE SELECTION | I15: Yes/No | J15: Yes | K15: Yes
A16: I-1352 | B16: I-130 = "SEG1" | C16: Are you also distributing to consumers? | D16: Vendez-vous aux consommateurs ? | F16: 1 | G16: I-135 Outlet Consumer | H16: SINGLE SELECTION | I16: Yes/No | J16: Yes | K16: Yes
A17: I-136 | C17: Do you sell more in sticks, packs or bundle ? | D17: Vendez vous plus en tiges, en paquets ou en cartouches ? | F17: 1 | G17: I-136 Sell other Outlets | H17: SINGLE SELECTION | I17: PT | J17: Yes | K17: Yes
A20: I-401 | C20: Is the outlet part of a chain? | D20: هل المحل جزء من سلسلة؟ | F20: -1
A21: I-402 | C21: What chain does the outlet belong to? | D21: واش هي السلسلة الي تابع ليها المحل؟ | F21: -1
A22: I-403 | C22: What is the chain code? | D22: واش هو رمز السلسلة؟ | F22: -1
A23: I-404 | C23: What is the chain size (# of outlets belong to this chain)? | D23: واش هو حجم السلسلة (عدد المحلات اللي تابعة إلى هذه السلسلة)؟ | F23: -1
A24: I-405 | C24: Does the outlet belong to Group/Group Owenrship? | D24: هل ينتمي المحل إلى مجموعة / مجموعة شركاء؟ | F24: -1

Sheet Volume
A1: Question fields | F1: Answer fields | I1: Backoffice | L1: Visibility | O1: Comments
A2: ID | B2: Visibility rule | C2: QUESTION WORDING EN | D2: QUESTION WORDING ARABIC | E2: Question Priority 1 Keep 0 Discuss -1 remove ? | F2: Reporting LABEL | G2: ANSWER TYPE | H2: ANSWER OPTIONS | I2: Visible ENUMERATOR | J2: VISIBLE BC | K2: PREFILLED FOR BC | L2: VISIBLE IF ON-TRADE | M2: VISIBLE IF OFF-TRADE | N2: VISIBLE IF RTM | O2: ___ | P2: CSD | Q2: Dev-team
A3: Section | B3: I-40 = "CO-1"
A4: V-12 | C4: Do you sell Soft Drinks? | E4: -1 | G4: SINGLE SELECTION | H4: Yes/No | J4: Yes | K4: No | L4: YES | M4: YES | N4: YES
A5: V-13 | C5: Do you sell Beer? | E5: -1 | G5: SINGLE SELECTION | H5: Yes/No | J5: Yes | K5: No | L5: YES | M5: YES | N5: YES
A6: V-14 | C6: Do you sell Spirits or Wines? | E6: -1 | G6: SINGLE SELECTION | H6: Yes/No | J6: Yes | K6: No | L6: YES | M6: YES | N6: YES
A8: V-10 | C8: Do you sell shisha? | D8: Vendez-vous la shisha ? | E8: -1 | F8: V-10 Shisha | G8: SINGLE SELECTION | H8: Yes/No
A9: V-20 | C9: Do you sell evapes? | D9: Vendez-vous des vapoteurs ? | E9: 1 | F9: V-20 evapes | G9: SINGLE SELECTION | H9: Yes/No
A10: V-30 | C10: Do you sell electronic cigarettes? | D10: Vendez-vous des cigarettes electroniques ? | E10: -1 | F10: V-30 E-cigarettes | G10: SINGLE SELECTION | H10: Yes/No
A11: V-50 | C11: On an average week how much do you sell cigarettes (Tobacco) ? | D11: Pendant une semaine normale combien vendez-vous de cigarettes (en Paquets ou en Cartouches) ? | E11: 1 | F11: V-150 Category | G11: MULTIPLE NUMERICAL FIELDS | H11: Options: see Categories list | I11: Yes | J11: Yes | K11: No | L11: YES | M11: YES | N11: YES
A13: V-20 | B13: I-130 = 1 | C13: Price per pack/bundle | D13: Prix par pack/bundle | E13: 0 | F13: V-20 Note | G13: NOTE | I13: Yes | J13: Yes | K13: No
A14: V-21 | B14: I-130 = 2 | C14: Price per bundle/carton | D14: Prix par bundle/carton | E14: 0 | F14: V-21 Note | G14: NOTE | I14: Yes | J14: Yes | K14: No
A15: V-60 | C15: On a normal day, how much do you sell for each cigarette (in packs or cartons)? | D15: Pendant une journée normale, combien vendez vous chacune des cigarettes (En Paquets ou en Cartouches) ? | E15: 1 | F15: V-60 Volume SKU | G15: MULTIPLE NUMERICAL FIELDS | H15: See Categories SKUs lists | I15: Yes | J15: Yes | K15: No | L15: YES | M15: YES | N15: YES
A17: V-61 | C17: On an average week, how much do you sell in sticks ? | D17: Pendant une semaine normale combien de sticks vendez vous ? | E17: -1 | F17: V-61 Sticks Sold | G17: SINGLE SELECTION | H17: PT
A18: V-62 | C18: On an average week, how much do you sell in packs ? | D18: Pendant une semaine normale combien de paquets vendez vous ? | E18: -1 | F18: V-62 Packs Sold | G18: SINGLE SELECTION
A20: V-70 | C20: On an average week how much do you sell of the following Shishas? | D20: Pendant une semaine normale, combien vendez vous chacune des shisha ? | E20: -1 | F20: V-70 Shishas | G20: MULTIPLE NUMERICAL FIELDS | I20: Yes | J20: Yes | K20: No | L20: YES | M20: YES | N20: YES
C21: How much stock of cigarette do you have ? | E21: -1 | G21: MULTIPLE NUMERICAL FIELDS | H21: See Categories SKUs lists
C22: On an average day how much do you sell of the following Cigarettes ( in pack)? | E22: -1

Sheet Wholesaler
A1: Question fields | F1: Answer fields | I1: Backoffice | L1: Comments
A2: ID | B2: Visibility rule | C2: QUESTION WORDING EN | D2: QUESTION WORDING FRENCH | E2: Question Priority 1 Keep 0 Discuss -1 remove ? | F2: Reporting LABEL | G2: ANSWER TYPE | H2: ANSWER OPTIONS | I2: Visible ENUMERATOR | J2: VISIBLE BC | K2: PREFILLED FOR BC | L2: ___ | M2: CSD | N2: Dev-team | O2: CSD | P2: CSD
A3: Section | B3: I-40 = "CO-1" and I-130 = "SEG-2"
A4: W-10 | C4: Who are your customers? | D4: Qui sont vos clients ? | E4: 1 | F4: W-10 WHS Customers | G4: MULTIPLE SELECTION | H4: Whosailer Customer | I4: Yes | J4: Yes | K4: No
A5: W-20 | B5: W-10 e-or ["WCU-1", "WCU-2", "WCU-3", "WCU-4", "WCU-5"] | C5: How many retailers do you service? | D5: Combien de points de vente/détaillants servez-vous ? | E5: 1 | F5: W-20 Num Retailers | G5: NUMERIC | H5: Open numeric field | I5: Yes | J5: No | K5: No
A6: W-30 | B6: W-10 e ["WCU-6"] | C6: How many sub wholesalers do you service? | D6: Combien de semi-grossiste servez-vous ? | E6: 1 | F6: W-30 Num SubWHS | G6: NUMERIC | H6: Open numeric field | I6: Yes | J6: Yes | K6: No
A7: W-40 | B7: W-10 = 3 | C7: How many other type of clients do you service? | E7: 0 | F7: W-10 WHS Customers | G7: NUMERIC | H7: Open numeric field | I7: Yes | J7: Yes | K7: No
A8: W-41 | C8: Do you have an updated overview/list of your customers and their accounts? | E8: 0 | F8: W-41 Consumer List | G8: SINGLE SELECTION | H8: Yes/No | I8: Yes | J8: Yes | K8: Yes
A10: W-50 | C10: What are the top retailer types / channels you service? Choose from a maximum of 3. | E10: -1 | F10: W-50 Top Retailers | G10: MULTIPLE SELECTION (max 3) | H10: Customers Wholesalers | I10: Yes | J10: No | K10: No
A12: W-60 | C12: Do you help with any supplier activations/ promotions? | E12: -1 | G12: SINGLE SELECTION | H12: Yes/No | J12: No | K12: No
A13: W-70 | C13: Do you have a sales/delivery team? | D13: Avez-vous une équipe de vente / livraison ? | E13: 1 | F13: W-70 Sales Team | G13: SINGLE SELECTION | H13: Yes/No | I13: Yes | J13: No | K13: No
A14: W-80 | C14: Does your sales team work with a routing/journey plan? | E14: -1 | F14: W-80 Route Plan | G14: SINGLE SELECTION | H14: Yes/No | I14: Yes | J14: No | K14: No
A15: W-90 | C15: What are the responsibilities of the sales team? | E15: -1 | F15: W-90 ST Responsibility | G15: MULTIPLE SELECTION (min 1, max 3) | H15: See Sales Team Responsibility List | I15: Yes | J15: No | K15: No
A16: W-100 | C16: Do you incentivise your sales reps? | E16: -1 | F16: W-100 SR Incentives | G16: SINGLE SELECTION | H16: Yes/No | I16: Yes | J16: No | K16: No
A18: W-110 | C18: How many people work for your business? | D18: Combien de personnes travaillent pour votre entreprise ? | E18: 1 | F18: W-110 Num Employees | G18: NUMERIC | H18: Open numeric field | I18: Yes | J18: Yes | K18: No
A19: W-120 | B19: W-110 is > 0 | C19: How many people accross the departments? | E19: -1 | G19: MULTIPLE NUMERICAL FIELDS | H19: See Departments List | J19: Yes | K19: No
A21: W-130 | C21: Do you offer credit terms? | E21: -1 | F21: W-130 Credit Terms | G21: SINGLE SELECTION | H21: Yes/No | I21: Yes | J21: No | K21: No
A22: W-131 | B22: W-130 = Yes | C22: What type of credit do you offer? | E22: -1 | F22: W-131 Type of Credit | G22: MULTIPLE SELECTION | H22: See Type of Credit List | I22: Yes | J22: No | K22: No
A23: W-132 | B23: W-131 = 2 | C23: How long is the credit in weeks? | E23: 0 | F23: W-132 Credit Length | G23: NUMERIC | H23: Open numeric field | I23: Yes | J23: No | K23: No
A24: W-133 | B24: W-131 = 1 | C24: What's the minimum value of invoices open for credit? | E24: 0 | F24: W-133 Num Invoices | G24: NUMERIC | H24: Open numeric field | I24: Yes | J24: No | K24: No
A25: W-140 | C25: How do you take the majority of your orders? Choose a maximum of 2. | E25: -1 | F25: W-140 Order Methods | G25: MULTIPLE SELECTION (min 1, max 2) | H25: See Order Methods List | I25: Yes | J25: No | K25: No
A26: W-141 | B26: I-133 = 1 | C26: How much of your sales are for consumer at retail price or for retailers at wholesale price? | E26: -1 | F26: W-141 Selling Mode | G26: SINGLE SELECTION | H26: Selling Mode | I26: Yes | J26: No | K26: No
A27: W-142 | C27: Do you deliver to your clients? | E27: -1 | F27: W-142 Client Delivery | G27: SINGLE SELECTION | H27: Yes/No | I27: Yes | J27: No | K27: No
A28: W-143 | B28: W-142 = Yes | C28: How are your cigarettes delivered to your customers? | E28: -1 | F28: W-143 Delivery Methods | G28: SINGLE SELECTION | H28: Delivery Mode | I28: Yes | J28: No | K28: No
A30: W-150 | C30: Do you have a forecast in place for your sales? | E30: -1 | G30: SINGLE SELECTION | H30: Yes/No | J30: No | K30: No
A31: W-160 | C31: How often do you buy per week (inbound stock)? Enter a number between 0 and 7 | D31: À quelle fréquence achetez-vous par semaine (stock entrant) ? Entrez un nombre entre 0 et 7. | E31: 1 | F31: W-160 Purchase Frequency | G31: NUMERIC | H31: Numeric field 0 to 7 | I31: Yes | J31: No | K31: No
A32: W-170 | C32: Do you measure and register your stock? | E32: -1 | F32: W-170 Stock Measurement | G32: SINGLE SELECTION | H32: Yes/No | I32: Yes | J32: No | K32: No
A34: W-180 | C34: How many trucks do you have? | E34: -1 | G34: NUMERIC | H34: Open numeric field | J34: No | K34: No
A35: W-190 | C35: How many vehicles do you have? | D35: Combien de véhicules de livraison avez-vous (Tricycle, moto, vehicules, ...)? | E35: 1 | F35: W-190 Num Vehicles | G35: NUMERIC | H35: Open numeric field | I35: Yes | J35: No | K35: No
A36: W-200 | C36: Do you use a computer for your business? | E36: -1 | F36: W-200 Computers | G36: SINGLE SELECTION | H36: Yes/No | I36: Yes | J36: No | K36: No
A37: W-205 | C37: Do you use a smartphone for your business? | D37: Utilisez-vous un smartphone pour gérer votre point de vente ? | E37: 1 | F37: W-205 smartphone | G37: SINGLE SELECTION | H37: Yes/No | I37: Yes | J37: No | K37: No
A38: W-210 | C38: Do you have internet? | E38: -1 | F38: W-210 Internet | G38: SINGLE SELECTION | H38: Yes/No | I38: Yes | J38: No | K38: No
A39: W-220 | C39: Do you have all-day power? | E39: -1 | F39: W-220 Power | G39: SINGLE SELECTION | H39: Yes/No | I39: Yes | J39: No | K39: No
A41: W-250 | C41: What's the most important thing your supplier should provide you? | D41: Quelle est la chose la plus importante que votre fournisseur devrait vous fournir ? (Maximum 3) | E41: 1 | F41: W-250 Supplier Support | G41: SINGLE SELECTION | H41: Supplier Support | I41: Yes | J41: No | K41: No
A42: W-260 | C42: Which brands of fridges are present in the outlet | E42: -1 | F42: W-260 W Cooler Available | G42: MULITPLE SELECTION (allow to insert numbers) | H42: See Visibility Brands List | J42: No | K42: No
A44: W-280 | C44: Do you provide credit to your clients? | E44: -1 | G44: SINGLE SELECTION | H44: Yes/No | J44: No | K44: No
A45: W-290 | C45: How many retail clients buy at least once a month from you? | E45: -1 | G45: NUMERIC | H45: Open numeric field | J45: No | K45: No
A46: W-300 | C46: Which beer brand has the most visible branding outside of the outlet with signage ? | E46: -1 | F46: M-30 Most Visible Brand Outside | G46: SINGLE SELECTION | H46: See Visibility Brands List | J46: No | K46: No

Sheet Marketing
A1: Question fields | G1: Answer fields | J1: Backoffice | M1: Comments
A2: ID | B2: Visibility rule | C2: QUESTION WORDING EN | D2: QUESTION WORDING FRENCH | E2: Wording change | F2: Question Priority 1 Keep 0 Discuss -1 remove ? | G2: Reporting LABEL | H2: ANSWER TYPE | I2: ANSWER OPTIONS | J2: Visible ENUMERATOR | K2: VISIBLE BC | L2: PREFILLED FOR BC | M2: ___ | N2: CSD | O2: Dev-team
A3: M-10 | C3: Does the outlet have a checkout? | F3: -1 | H3: SINGLE SELECTION | I3: Yes/No | K3: No | L3: No
A4: M-20 | B4: M-10=Yes | C4: How many of the following type of checkout do you have? | F4: -1 | H4: MULTIPLE NUMERICAL FIELDS | I4: Type Of Fridges | K4: No | L4: No
A5: Section | B5: I-40 = "CO-1" and I-130 ! "SEG-2"
A6: M-24 | C6: On average, how many customers buy cigarettes from your outlet in a day? | D6: En moyenne, combien de clients achètent les cigarettes chez vous par jour ? | F6: 1 | G6: M-24 Customers | H6: NUMERICAL | I6: Open Numeric Field | J6: Yes | K6: No | L6: No
A7: M-30 | C7: Which brand is the MOST visible in the outlet (outside/ inside) ? | D7: Quelle marque de cigarette est la PLUS visible dans le point de vente (extérieur/ intérieur) ? | F7: 1 | G7: M-30 Most Visible Brand | H7: SINGLE SELECTION | I7: Visibility Brands | J7: Yes | K7: No | L7: No
A8: M-31 | C8: Which brand has the MOST visible from inside the outlet? | F8: -1 | G8: M-30 Most Visible Brand Inside | H8: SINGLE SELECTION | I8: Visibility Brands | K8: No | L8: No
A9: M-40 | C9: Does the outlet owner accept visibility items? | F9: -1 | G9: M-50 Display Sign Accepted | H9: SINGLE SELECTION | I9: Yes/No | K9: No | L9: No
A10: M-42 | C10: Is there already a display sign present? Select the type of sign present | F10: -1 | H10: MULTIPLE SELECTION | I10: Dealer Sign | K10: No | L10: No
A11: M-43 | C11: Are pack being displayed ? | D11: Les packs de cigarettes sont-ils visibles ? | F11: 1 | G11: M-43 Pack Displayed | H11: SINGLE SELECTION | I11: Yes/No | J11: Yes | K11: No | L11: No
A12: M-44 | C12: Select the brands that have a wall unit display present | D12: Sélectionnez les marques visibles sur le présentoir à cigarettes encastré dans le mur | F12: 1 | G12: M-44 Wall Display | H12: MULTIPLE NUMERICAL FIELDS | I12: Visibility Brands | K12: No | L12: No
A13: M-45 | C13: Select the brands that have an overhead dispaly present | D13: Sélectionnez les marques visibles sur le présentoir à cigarettes suspendu | F13: 1 | G13: M-45 Overhead Display | H13: MULTIPLE NUMERICAL FIELDS | I13: Visibility Brands | K13: No | L13: No
A14: M-46 | C14: Select the brands that have an standing display present | D14: Sélectionnez les marques visibles sur le présentoir à cigarettes sur pied | F14: 1 | G14: M-46 Standingl Display | H14: MULTIPLE NUMERICAL FIELDS | I14: Visibility Brands | K14: No | L14: No
A15: M-48 | B15: M-42=5 | C15: Select the brands that have a wall painting present | F15: 1 | G15: M-43 Pack Displayed | H15: MULTIPLE NUMERICAL FIELDS | I15: Visibility Brands | K15: No | L15: No
A16: M-49 | B16: M-42=6 | C16: Select the brands that have a free standing display sign present | F16: 1 | G16: M-43 Pack Displayed | H16: MULTIPLE NUMERICAL FIELDS | I16: Visibility Brands | K16: No | L16: No
A17: M-60 | C17: Which of the following brands are present (listed) in the outlet? | F17: 1 | G17: M-43 Pack Displayed | H17: MULTIPLE NUMERICAL FIELDS | I17: Visibility Brands | K17: No | L17: No
A18: M-71 | C18: What are your busiest times of day? (Maximum 2 responses) | F18: 1 | G18: M-43 Pack Displayed | H18: MULTIPLE SELECTION | I18: Time Of The Day | K18: No | L18: No
A19: M-80 | C19: Main gender of consumers | F19: 1 | G19: M-43 Pack Displayed | H19: SINGLE SELECTION | I19: Consumer Gender | K19: No | L19: No
A20: M-90 | C20: Main age of consumers | F20: 1 | G20: M-43 Pack Displayed | H20: SINGLE SELECTION | I20: Consumer Age | K20: No | L20: No
A21: M-100 | C21: Check if following items are present in the outlet (premium indicators) | F21: 1 | G21: M-43 Pack Displayed | H21: MULTIPLE SELECTION | I21: Premium Indicators | K21: No | L21: No
A22: M-116 | C22: What 2 brands from the following list are the most important to you and your consumers? | F22: 1 | G22: M-43 Pack Displayed | H22: MULTIPLE SELECTION (min 2, max 2) | I22: Visibility Brands | K22: No | L22: No
A23: M-117 | C23: What is the year of this outlet's establishment? | F23: 1 | G23: M-43 Pack Displayed
A24: M-118 | C24: What is the number of full time employees? | D24: Combien d'employés à temps plein avez-vous dans votre point de vente ? | F24: 1
A25: M-119 | C25: Is there a storage room available? | D25: Avez-vous un endroit de stockage de la cigarette ? | F25: 1 | G25: M-119 Storage Room | H25: SINGLE SELECTION | I25: Yes/No
A26: M-120 | C26: What is the size of the storage room (in m2)? | D26: Quelle est la superficie de la pièce de stockage (en m2) ? | F26: 1 | G26: M-120 Storage Size | H26: NUMERICAL | I26: Open Numeric Field
A27: M-121 | C27: How many days do you work per week? | D27: Combien de jours travaillez - vous par semaine ? | F27: 1 | G27: M-121 Number Work Days | H27: NUMERICAL | I27: Open Numeric Field | J27: Yes | K27: No | L27: No

Sheet Distribution
A1: Question fields | G1: Answer fields | J1: Backoffice | M1: Comments
A2: ID | B2: Visibility rule | C2: QUESTION WORDING EN | D2: QUESTION WORDING FRENCH | E2: Wording change | F2: Question Priority 1 Keep 0 Discuss -1 remove ? | G2: Reporting LABEL | H2: ANSWER TYPE | I2: ANSWER OPTIONS | J2: Visible ENUMERATOR | K2: VISIBLE BC | L2: PREFILLED FOR BC | M2: ___ | N2: CSD | O2: Dev-team | P2: Min | Q2: Max | R2: Dev-team | S2: The following set of questions will be asked for a minimum of two breweries/companies and a maximum of 9 breweries/companies, please identify the breweries/companies for which you would like to ask the distribution section of the questionnaire, the first brewery is set as an example, we recommend to choose a mix of 5 breweries and 5 soft drink producers
A3: Section | B3: I-40 = "CO-1"
A4: D-10 | C4: ="Where do you mainly source your "&R5&" cigarettes from?" -> Where do you mainly source your cigarettes from? | D4: Où vous approvisionnez-vous principalement en cigarettes JTI? | F4: 1 | G4: D-10 BAT Sourcing | H4: SINGLE SELECTION | I4: cigarettes Sources | J4: Yes | K4: No | L4: No
A5: D-11 | B5: D-10 ! ["SOUR-1"] | C5: How do you make the majority of your orders? | D5: Comment faites-vous HABITUELLEMENT votre commande ? | F5: 1 | G5: D-11 Order Methods | H5: SINGLE SELECTION | I5: Orders Methods | J5: Yes | K5: No | L5: No | S5: 1
A6: D-12 | B6: D-10 ! ["SOUR-1"] | C6: How often do you buy, get delivered per week? | D6: A quelle fréquence achetez-vous/vous faites-vous livrer par semaine ? | F6: 1 | G6: D-12 Purchase Frequency | H6: NUMERIC | I6: Numeric field 0 to 7 | J6: Yes | K6: No | L6: No | P6: 0 | Q6: 7 | S6: 2
A7: D-13 | B7: =A4&"=3,5 or 6" -> D-10=3,5 or 6 | C7: Are you happy with the order quantity and/or frequency? | F7: 0 | H7: SINGLE SELECTION | I7: Yes/No | K7: No | L7: No | S7: 3
A8: D-14 | B8: =A4&"=3,5 or 6" -> D-10=3,5 or 6 | C8: What is the minimum quantity to order to get delivered by a supplier/wholesaler or distributor? | F8: 0 | H8: NUMERIC | I8: Open Numeric Field | K8: No | L8: No | S8: 4
A9: D-15 | B9: =A4&" is not 1" -> D-10 is not 1 | C9: What are your payment conditions? | F9: 0 | H9: SINGLE SELECTION | I9: Payment Condition | K9: No | L9: No | S9: 5
A10: D-16 | B10: =A9&" is not 1" -> D-15 is not 1 | C10: What type of credit do you get? | F10: 0 | H10: MULTIPLE SELECTION | I10: Type of Credit | K10: No | L10: No | S10: 6
A11: D-17 | B11: =A10&" =1" -> D-16 =1 | C11: What is the maximum number of open invoices allowed? | F11: 0 | H11: NUMERIC | I11: Open Numeric Field | K11: No | L11: No | S11: 7
A12: D-18 | B12: =A10&" =2" -> D-16 =2 | C12: How long is the credit in weeks? | F12: 0 | H12: NUMERIC | I12: Numeric field 0 to 52 | K12: No | L12: No | S12: 8
A13: D-19 | B13: D-10 =-or ["SOUR-4", "SOUR-5"] | C13: What is the name of your official Wholesaler/Distributor? | D13: Quel est le nom de votre principal fournisseur pour les produits ? | F13: 1 | G13: D-19 BAT WHS | H13: SINGLE SELECTION | I13: Text box | J13: Yes | K13: No | L13: No | S13: 3
A14: NEW PAGE | S14: 4
A15: D-20 | C15: ="Where do you mainly source your "&R6&" cigarettes from?" -> Where do you mainly source your cigarettes from? | D15: Où vous approvisionnez-vous principalement en cigarettes BAT? | F15: 1 | G15: D-10 PMI Sourcing | H15: SINGLE SELECTION | I15: cigarettes Sources | J15: Yes | K15: No | L15: No | S15: 5
A16: D-21 | B16: D-20 ! ["SOUR-1"] | C16: =C5 -> How do you make the majority of your orders? | D16: Comment faites-vous HABITUELLEMENT votre commande ? | F16: 1 | G16: D-11 Order Methods | H16: SINGLE SELECTION | I16: Orders Methods | J16: Yes | K16: No | L16: No | S16: 6
A17: D-22 | B17: D-20 ! ["SOUR-1"] | C17: =C6 -> How often do you buy, get delivered per week? | D17: A quelle fréquence achetez-vous/vous faites-vous livrer par semaine ? | F17: 1 | G17: D-12 Purchase Frequency | H17: NUMERIC | I17: Numeric field 0 to 7 | J17: Yes | K17: No | L17: No | P17: 0 | Q17: 7 | S17: 7
A18: D-23 | B18: =A15&"=3,5 or 6" -> D-20=3,5 or 6 | C18: =C7 -> Are you happy with the order quantity and/or frequency? | F18: 1 | H18: SINGLE SELECTION | I18: Yes/No | K18: No | L18: No | S18: 8
A19: D-24 | B19: =A15&"=3,5 or 6" -> D-20=3,5 or 6 | C19: =C8 -> What is the minimum quantity to order to get delivered by a supplier/wholesaler or distributor? | F19: 1 | H19: NUMERIC | I19: Open Numeric Field | K19: No | L19: No | S19: 9
A20: D-25 | B20: =A15&" is not 1" -> D-20 is not 1 | C20: =C9 -> What are your payment conditions? | F20: 0 | H20: SINGLE SELECTION | I20: Payment Condition | K20: No | L20: No | S20: 10
A21: D-26 | B21: =A20&" is not 1" -> D-25 is not 1 | C21: =C10 -> What type of credit do you get? | F21: 0 | H21: MULTIPLE SELECTION | I21: Type of Credit | K21: No | L21: No | S21: 11
A22: D-27 | B22: =A21&" =1" -> D-26 =1 | C22: =C11 -> What is the maximum number of open invoices allowed? | F22: 0 | H22: NUMERIC | I22: Open Numeric Field | K22: No | L22: No | S22: 12
A23: D-28 | B23: =A21&" =2" -> D-26 =2 | C23: =C12 -> How long is the credit in weeks? | F23: 0 | H23: NUMERIC | I23: Numeric field 0 to 52 | K23: No | L23: No | S23: 13
A24: D-29 | B24: D-20 =-or ["SOUR-4", "SOUR-5"] | C24: =C13 -> What is the name of your official Wholesaler/Distributor? | D24: Quel est le nom de votre principal fournisseur pour les produits ? | F24: 1 | G24: D-19 PMI WHS | H24: SINGLE SELECTION | I24: Wholesalers/Distributors | J24: Yes | K24: No | L24: No
A25: NEW PAGE
A26: D-30 | C26: ="Where do you mainly source your "&R13&" cigarettes from?" -> Where do you mainly source your cigarettes from? | D26: Où vous approvisionnez-vous principalement en cigarettes PMI ? | F26: 1 | G26: D-10 JTI Sourcing | H26: SINGLE SELECTION | I26: cigarettes Sources | J26: Yes | K26: No | L26: No
A27: D-31 | B27: D-30 ! ["SOUR-1"] | C27: =C16 -> How do you make the majority of your orders? | D27: Comment faites-vous HABITUELLEMENT votre commande ? | F27: 1 | G27: D-11 Order Methods | H27: SINGLE SELECTION | I27: Orders Methods | J27: Yes | K27: No | L27: No
A28: D-32 | B28: D-30 ! ["SOUR-1"] | C28: =C17 -> How often do you buy, get delivered per week? | D28: A quelle fréquence achetez-vous/vous faites-vous livrer par semaine ? | F28: 1 | G28: D-12 Purchase Frequency | H28: NUMERIC | I28: Numeric field 0 to 7 | J28: Yes | K28: No | L28: No | P28: 0 | Q28: 7
A29: D-33 | B29: =A26&"=3,5 or 6" -> D-30=3,5 or 6 | C29: =C18 -> Are you happy with the order quantity and/or frequency? | F29: 0 | H29: SINGLE SELECTION | I29: Yes/No | K29: No | L29: No
A30: D-34 | B30: =A26&"=3,5 or 6" -> D-30=3,5 or 6 | C30: =C19 -> What is the minimum quantity to order to get delivered by a supplier/wholesaler or distributor? | F30: 0 | H30: NUMERIC | I30: Open Numeric Field | K30: No | L30: No
A31: D-35 | B31: =A26&" is not 1" -> D-30 is not 1 | C31: =C20 -> What are your payment conditions? | F31: 0 | H31: SINGLE SELECTION | I31: Payment Condition | K31: No | L31: No
A32: D-36 | B32: =A31&" is not 1" -> D-35 is not 1 | C32: =C21 -> What type of credit do you get? | F32: 0 | H32: MULTIPLE SELECTION | I32: Type of Credit | K32: No | L32: No
A33: D-37 | B33: =A32&" =1" -> D-36 =1 | C33: =C22 -> What is the maximum number of open invoices allowed? | F33: 0 | H33: NUMERIC | I33: Open Numeric Field | K33: No | L33: No
A34: D-38 | B34: =A32&" =2" -> D-36 =2 | C34: =C23 -> How long is the credit in weeks? | F34: 0 | H34: NUMERIC | I34: Numeric field 0 to 52 | K34: No | L34: No
A35: D-39 | B35: D-30 =-or ["SOUR-4", "SOUR-5"] | C35: =C24 -> What is the name of your official Wholesaler/Distributor? | D35: Quel est le nom de votre principal fournisseur pour les produits ? | F35: 1 | G35: D-19 JTI WHS | H35: SINGLE SELECTION | I35: Wholesalers/Distributors | J35: Yes | K35: No | L35: No
A36: NEW PAGE
A37: D-40 | C37: ="Where do you mainly source your "&R14&" cigarettes from?" -> Where do you mainly source your cigarettes from? | D37: Où vous approvisionnez-vous principalement en cigarettes Oriental ? | F37: 1 | G37: D-10 ITG Sourcing | H37: SINGLE SELECTION | I37: cigarettes Sources | J37: Yes | K37: No | L37: No
A38: D-41 | B38: D-40 ! ["SOUR-1"] | C38: =C27 -> How do you make the majority of your orders? | D38: Comment faites-vous HABITUELLEMENT votre commande ? | F38: 1 | G38: D-11 Order Methods | H38: SINGLE SELECTION | I38: Orders Methods | J38: Yes | K38: No | L38: No
A39: D-42 | B39: D-40 ! ["SOUR-1"] | C39: =C28 -> How often do you buy, get delivered per week? | D39: A quelle fréquence achetez-vous/vous faites-vous livrer par semaine ? | F39: 1 | G39: D-12 Purchase Frequency | H39: NUMERIC | I39: Numeric field 0 to 7 | J39: Yes | K39: No | L39: No | P39: 0 | Q39: 7
A40: D-43 | B40: =A37&"=3,5 or 6" -> D-40=3,5 or 6 | C40: =C29 -> Are you happy with the order quantity and/or frequency? | F40: 0 | H40: SINGLE SELECTION | I40: Yes/No | K40: No | L40: No
A41: D-44 | B41: =A37&"=3,5 or 6" -> D-40=3,5 or 6 | C41: =C30 -> What is the minimum quantity to order to get delivered by a supplier/wholesaler or distributor? | F41: 0 | H41: NUMERIC | I41: Open Numeric Field | K41: No | L41: No
A42: D-45 | B42: =A37&" is not 1" -> D-40 is not 1 | C42: =C31 -> What are your payment conditions? | F42: 0 | H42: SINGLE SELECTION | I42: Payment Condition | K42: No | L42: No
A43: D-46 | B43: =A42&" is not 1" -> D-45 is not 1 | C43: =C32 -> What type of credit do you get? | F43: 0 | H43: MULTIPLE SELECTION | I43: Type of Credit | K43: No | L43: No
A44: D-47 | B44: =A43&" =1" -> D-46 =1 | C44: =C33 -> What is the maximum number of open invoices allowed? | F44: 0 | H44: NUMERIC | I44: Open Numeric Field | K44: No | L44: No
A45: D-48 | B45: =A43&" =2" -> D-46 =2 | C45: =C34 -> How long is the credit in weeks? | F45: 0 | H45: NUMERIC | I45: Numeric field 0 to 52 | K45: No | L45: No
A46: D-49 | B46: D-40 =-or ["SOUR-4", "SOUR-5"] | C46: =C35 -> What is the name of your official Wholesaler/Distributor? | D46: Quel est le nom de votre principal fournisseur pour les produits ? | F46: 1 | G46: D-19 ITG WHS | H46: SINGLE SELECTION | I46: Wholesalers/Distributors | J46: Yes | K46: No | L46: No
A47: NEW PAGE
A48: D-50 | C48: ="Where do you mainly source your "&R15&" cigarettes from?(UTC new name)" -> Where do you mainly source your cigarettes from?(UTC new name) | D48: Où vous approvisionnez-vous principalement en cigarettes KT& G? | F48: 1 | G48: D-10 SNTA Sourcing | H48: SINGLE SELECTION | I48: cigarettes Sources | J48: Yes | K48: No | L48: No
A49: D-51 | B49: D-50 ! ["SOUR-1"] | C49: =C38 -> How do you make the majority of your orders? | D49: Comment faites-vous HABITUELLEMENT votre commande ? | F49: 1 | G49: D-11 Order Methods | H49: SINGLE SELECTION | I49: Orders Methods | J49: Yes | K49: No | L49: No
A50: D-52 | B50: D-50 ! ["SOUR-1"] | C50: =C39 -> How often do you buy, get delivered per week? | D50: A quelle fréquence achetez-vous/vous faites-vous livrer par semaine ? | F50: 1 | G50: D-12 Purchase Frequency | H50: NUMERIC | I50: Numeric field 0 to 7 | J50: Yes | K50: No | L50: No | P50: 0 | Q50: 7
A51: D-53 | B51: =A48&"=3,5 or 6" -> D-50=3,5 or 6 | C51: =C40 -> Are you happy with the order quantity and/or frequency? | F51: 0 | H51: SINGLE SELECTION | I51: Yes/No | K51: No | L51: No
A52: D-54 | B52: =A48&"=3,5 or 6" -> D-50=3,5 or 6 | C52: =C41 -> What is the minimum quantity to order to get delivered by a supplier/wholesaler or distributor? | F52: 0 | H52: NUMERIC | I52: Open Numeric Field | K52: No | L52: No
A53: D-55 | B53: =A48&" is not 1" -> D-50 is not 1 | C53: =C42 -> What are your payment conditions? | F53: 0 | H53: SINGLE SELECTION | I53: Payment Condition | K53: No | L53: No
A54: D-56 | B54: =A53&" is not 1" -> D-55 is not 1 | C54: =C43 -> What type of credit do you get? | F54: 0 | H54: MULTIPLE SELECTION | I54: Type of Credit | K54: No | L54: No
A55: D-57 | B55: =A54&" =1" -> D-56 =1 | C55: =C44 -> What is the maximum number of open invoices allowed? | F55: 0 | H55: NUMERIC | I55: Open Numeric Field | K55: No | L55: No
A56: D-58 | B56: =A54&" =2" -> D-56 =2 | C56: =C45 -> How long is the credit in weeks? | F56: 0 | H56: NUMERIC | I56: Numeric field 0 to 52 | K56: No | L56: No
A57: D-59 | B57: D-50 =-or ["SOUR-4", "SOUR-5"] | C57: =C46 -> What is the name of your official Wholesaler/Distributor? | D57: Quel est le nom de votre principal fournisseur pour les produits ? | F57: 1 | G57: D-19 SNTA WHS | H57: SINGLE SELECTION | I57: Wholesalers/Distributors | J57: Yes | K57: No | L57: No
A58: NEW PAGE
A59: D-60 | C59: ="Where do you mainly source your "&R10&" cigarettes from?" -> Where do you mainly source your cigarettes from? | F59: -1 | H59: SINGLE SELECTION | I59: cigarettes Sources | K59: No | L59: No
A60: D-61 | B60: =A59&" is not 1" -> D-60 is not 1 | C60: =C49 -> How do you make the majority of your orders? | F60: -1 | H60: SINGLE SELECTION | I60: Orders Methods | K60: No | L60: No
A61: D-62 | B61: =A59&" is not 1" -> D-60 is not 1 | C61: =C50 -> How often do you buy, get delivered per week? | F61: 0 | H61: NUMERIC | I61: Numeric field 0 to 7 | K61: No | L61: No
A62: D-63 | B62: =A59&"=3,5 or 6" -> D-60=3,5 or 6 | C62: =C51 -> Are you happy with the order quantity and/or frequency? | F62: 0 | H62: SINGLE SELECTION | I62: Yes/No | K62: No | L62: No
A63: D-64 | B63: =A59&"=3,5 or 6" -> D-60=3,5 or 6 | C63: =C52 -> What is the minimum quantity to order to get delivered by a supplier/wholesaler or distributor? | F63: 0 | H63: NUMERIC | I63: Open Numeric Field | K63: No | L63: No
A64: D-65 | B64: =A59&" is not 1" -> D-60 is not 1 | C64: =C53 -> What are your payment conditions? | F64: 0 | H64: SINGLE SELECTION | I64: Payment Condition | K64: No | L64: No
A65: D-66 | B65: =A64&" is not 1" -> D-65 is not 1 | C65: =C54 -> What type of credit do you get? | F65: 0 | H65: MULTIPLE SELECTION | I65: Type of Credit | K65: No | L65: No
A66: D-67 | B66: =A65&" =1" -> D-66 =1 | C66: =C55 -> What is the maximum number of open invoices allowed? | F66: 0 | H66: NUMERIC | I66: Open Numeric Field | K66: No | L66: No
A67: D-68 | B67: =A65&" =2" -> D-66 =2 | C67: =C56 -> How long is the credit in weeks? | F67: 0 | H67: NUMERIC | I67: Numeric field 0 to 52 | K67: No | L67: No
A68: D-69 | B68: =A59&"=4 or 5" -> D-60=4 or 5 | C68: =C57 -> What is the name of your official Wholesaler/Distributor? | F68: -1 | H68: SINGLE SELECTION | I68: Wholesalers/Distributors | K68: No | L68: No
A69: NEW PAGE
A70: D-70 | C70: ="Where do you mainly source your "&R11&" cigarettes from?" -> Where do you mainly source your cigarettes from? | F70: 1 | H70: SINGLE SELECTION | I70: cigarettes Sources | K70: No | L70: No
A71: D-71 | B71: =A70&" is not 1" -> D-70 is not 1 | C71: =C49 -> How do you make the majority of your orders? | F71: 1 | H71: SINGLE SELECTION | I71: Orders Methods | K71: No | L71: No
A72: D-72 | B72: =A70&" is not 1" -> D-70 is not 1 | C72: =C50 -> How often do you buy, get delivered per week? | F72: 1 | H72: NUMERIC | I72: Numeric field 0 to 7 | K72: No | L72: No
A73: D-73 | B73: =A70&"=3,5 or 6" -> D-70=3,5 or 6 | C73: =C51 -> Are you happy with the order quantity and/or frequency? | F73: 1 | H73: SINGLE SELECTION | I73: Yes/No | K73: No | L73: No
A74: D-74 | B74: =A70&"=3,5 or 6" -> D-70=3,5 or 6 | C74: =C52 -> What is the minimum quantity to order to get delivered by a supplier/wholesaler or distributor? | F74: 1 | H74: NUMERIC | I74: Open Numeric Field | K74: No | L74: No
A75: D-75 | B75: =A70&" is not 1" -> D-70 is not 1 | C75: =C53 -> What are your payment conditions? | F75: 1 | H75: SINGLE SELECTION | I75: Payment Condition | K75: No | L75: No
A76: D-76 | B76: =A75&" is not 1" -> D-75 is not 1 | C76: =C54 -> What type of credit do you get? | F76: 1 | H76: MULTIPLE SELECTION | I76: Type of Credit | K76: No | L76: No
A77: D-77 | B77: =A76&" =1" -> D-76 =1 | C77: =C55 -> What is the maximum number of open invoices allowed? | F77: 1 | H77: NUMERIC | I77: Open Numeric Field | K77: No | L77: No
A78: D-78 | B78: =A76&" =2" -> D-76 =2 | C78: =C56 -> How long is the credit in weeks? | F78: 1 | H78: NUMERIC | I78: Numeric field 0 to 52 | K78: No | L78: No
A79: D-79 | B79: =A70&"=4 or 5" -> D-70=4 or 5 | C79: =C57 -> What is the name of your official Wholesaler/Distributor? | F79: 1 | H79: SINGLE SELECTION | I79: Wholesalers/Distributors | K79: No | L79: No
A80: NEW PAGE
A81: D-80 | C81: ="Where do you mainly source your "&R12&" cigarettes from?" -> Where do you mainly source your cigarettes from? | F81: 1 | H81: SINGLE SELECTION | I81: cigarettes Sources | K81: No | L81: No
A82: D-81 | B82: =A81&" is not 1" -> D-80 is not 1 | C82: =C60 -> How do you make the majority of your orders? | F82: 1 | H82: SINGLE SELECTION | I82: Orders Methods | K82: No | L82: No
A83: D-82 | B83: =A81&" is not 1" -> D-80 is not 1 | C83: =C61 -> How often do you buy, get delivered per week? | F83: 1 | H83: NUMERIC | I83: Numeric field 0 to 7 | K83: No | L83: No
A84: D-83 | B84: =A81&"=3,5 or 6" -> D-80=3,5 or 6 | C84: =C62 -> Are you happy with the order quantity and/or frequency? | F84: 1 | G84: JTI | H84: SINGLE SELECTION | I84: Yes/No | K84: No | L84: No
A85: D-84 | B85: =A81&"=3,5 or 6" -> D-80=3,5 or 6 | C85: =C63 -> What is the minimum quantity to order to get delivered by a supplier/wholesaler or distributor? | F85: 1 | G85: BAT | H85: NUMERIC | I85: Open Numeric Field | K85: No | L85: No
A86: D-85 | B86: =A81&" is not 1" -> D-80 is not 1 | C86: =C64 -> What are your payment conditions? | F86: 1 | G86: PMI | H86: SINGLE SELECTION | I86: Payment Condition | K86: No | L86: No
A87: D-86 | B87: =A86&" is not 1" -> D-85 is not 1 | C87: =C65 -> What type of credit do you get? | F87: 1 | G87: Oriental | H87: MULTIPLE SELECTION | I87: Type of Credit | K87: No | L87: No
A88: D-87 | B88: =A87&" =1" -> D-86 =1 | C88: =C66 -> What is the maximum number of open invoices allowed? | F88: 1 | G88: KT&G | H88: NUMERIC | I88: Open Numeric Field | K88: No | L88: No
A89: D-88 | B89: =A87&" =2" -> D-86 =2 | C89: =C67 -> How long is the credit in weeks? | F89: 1 | G89: Other | H89: NUMERIC | I89: Numeric field 0 to 52 | K89: No | L89: No
A90: D-89 | B90: =A81&"=4 or 5" -> D-80=4 or 5 | C90: =C68 -> What is the name of your official Wholesaler/Distributor? | F90: 1 | H90: SINGLE SELECTION | I90: Wholesalers/Distributors | K90: No | L90: No
A91: NEW PAGE
A92: D-90 | C92: ="Where do you mainly source your "&R13&" cigarettes from?" -> Where do you mainly source your cigarettes from? | F92: 1 | H92: SINGLE SELECTION | I92: cigarettes Sources | K92: No | L92: No
A93: D-91 | B93: =A92&" is not 1" -> D-90 is not 1 | C93: =C71 -> How do you make the majority of your orders? | F93: 1 | H93: SINGLE SELECTION | I93: Orders Methods | K93: No | L93: No
A94: D-92 | B94: =A92&" is not 1" -> D-90 is not 1 | C94: =C72 -> How often do you buy, get delivered per week? | F94: 1 | H94: NUMERIC | I94: Numeric field 0 to 7 | K94: No | L94: No
A95: D-93 | B95: =A92&"=3,5 or 6" -> D-90=3,5 or 6 | C95: =C73 -> Are you happy with the order quantity and/or frequency? | F95: 1 | H95: SINGLE SELECTION | I95: Yes/No | K95: No | L95: No
A96: D-94 | B96: =A92&"=3,5 or 6" -> D-90=3,5 or 6 | C96: =C74 -> What is the minimum quantity to order to get delivered by a supplier/wholesaler or distributor? | F96: 1 | H96: NUMERIC | I96: Open Numeric Field | K96: No | L96: No
A97: D-95 | B97: =A92&" is not 1" -> D-90 is not 1 | C97: =C75 -> What are your payment conditions? | F97: 1 | H97: SINGLE SELECTION | I97: Payment Condition | K97: No | L97: No
A98: D-96 | B98: =A97&" is not 1" -> D-95 is not 1 | C98: =C76 -> What type of credit do you get? | F98: 1 | H98: MULTIPLE SELECTION | I98: Type of Credit | K98: No | L98: No
A99: D-97 | B99: =A98&" =1" -> D-96 =1 | C99: =C77 -> What is the maximum number of open invoices allowed? | F99: 1 | H99: NUMERIC | I99: Open Numeric Field | K99: No | L99: No
A100: D-98 | B100: =A98&" =2" -> D-96 =2 | C100: =C78 -> How long is the credit in weeks? | F100: 1 | H100: NUMERIC | I100: Numeric field 0 to 52 | K100: No | L100: No
...

Sheet End
A1: Question fields | G1: Answer fields | J1: Backoffice | M1: Comments
A2: ID | B2: Visibility rule | C2: QUESTION WORDING EN | D2: QUESTION WORDING ARABIC | E2: Wording change | F2: Question Priority 1 Keep 0 Discuss -1 remove ? | G2: Reporting LABEL | H2: ANSWER TYPE | I2: ANSWER OPTIONS | J2: Visible ENUMERATOR | K2: VISIBLE BC | L2: PREFILLED FOR BC | M2: ___ | N2: CSD | O2: Dev-team
A3: Section
A4: E-10 | B4: I-40 = "Yes" | C4: Note - INTERVIEWER READ THE FOLLOWING TO OWNER/MANAGER: Thank you for participating in our survey. In the coming days, you may be contacted by my supervisor to assess the quality of my work and to answer any questions you may have with respect to this interview. | D4: Note - ENUMERATEUR LIRE CE QUI SUIT AU PROPRIÉTAIRE/GÉRANT : Merci pour votre participation à notre sondage. Dans les prochains jours, vous serez peut-être contacté par mon superviseur afin d'évaluer la qualité de mon travail, de répondre à toutes vos questions concernant cet entretien et vérifier que j'ai correctement saisi les informations sur votre point de vente. | F4: 1 | H4: NOTE | I4: 1. NEXT | K4: YES | L4: Yes
A5: E-20 | C5: May I take a picture of the outside and inside of your outlet? | D5: Puis-je prendre une photo de l'intérieur et de l'extérieur de votre point de vente ? | F5: 1 | H5: NOTE | J5: Yes | K5: No | L5: No
A6: E-21 | C6: Take a picture of the inside | D6: Prendre une photo de l'intérieur | F6: 1 | H6: PHOTOGRAPH | J6: Yes | K6: No | L6: No
A7: E-22 | C7: Take a picture of the outside | D7: Prendre une photo de l'extérieur | F7: 1 | H7: PHOTOGRAPH | J7: Yes | K7: No | L7: No
A8: E-23 | C8: Take a picture of the menu | F8: 1 | H8: PHOTOGRAPH | K8: No | L8: No
A9: E-24 | C9: Take a picture of POSM | F9: 1 | H9: PHOTOGRAPH | K9: No | L9: No
A10: E-25 | C10: Take a picture of draught beer | F10: 1 | H10: PHOTOGRAPH | K10: No | L10: No
A11: E-26 | C11: Take a picture of chiller | F11: 1 | H11: PHOTOGRAPH | K11: No | L11: No
A12: E-27 | C12: Take a picture of the serial number on fridge 1 | F12: 1 | H12: PHOTOGRAPH
A13: E-28 | C13: Take a picture of the serial number on fridge 2 | F13: 1 | H13: PHOTOGRAPH
A14: E-29 | C14: Take a picture of the serial number on fridge 3 | F14: 1 | H14: PHOTOGRAPH
A15: E-30 | C15: What would you say is the outlet quality? | F15: 0 | H15: SINGLE SELECTION
A16: NEW PAGE
A17: E-40 | B17: I-40 = "Yes" | C17: I hereby certify that this interview has been carried out by me according to the instructions I received. | D17: Je certifie par la présente que cet entretien a été réalisé par mes soins conformément aux instructions que j'ai reçues. | F17: 1 | H17: NOTE | J17: Yes | K17: No | L17: No
A18: E-50 | B18: 0-10 = 0 | C18: GPS Location of Outlet | D18: Coordonnées GPS du point de vente | F18: 1 | H18: SYSTEM | I18: Device captures automatically. | J18: Yes | K18: No | L18: No
A19: E-110 | B19: I-40 = "Yes" | C19: May I confirm your telephone number? This way my managers may contact you to check that I have correctly captured the information about your business. | D19: Puis-je confirmer votre numéro de téléphone ? De cette façon, mes responsables peuvent vous contacter pour vérifier que j'ai correctement saisi les informations sur votre entreprise. | F19: 1 | H19: NUMERIC | I19: Open Numeric Field | J19: Yes | K19: Yes | L19: Yes
A20: E-111 | C20: Do you have an additional telephone number just in case? (DON'T INSERT COUNTRYCODE) | D20: Avez-vous un numéro de téléphone supplémentaire au cas où ? (NE PAS INSÉRER LE CODE DE PAYS) | F20: 1 | H20: NUMERIC | I20: Open Numeric Field | J20: Yes | K20: Yes | L20: Yes
A21: E-112 | C21: May I confirm your name and surname? | D21: Puis-je confirmer votre nom et prénom? | F21: 1 | G21: E-112 Interviewee Name | H21: TEXT | J21: Yes | K21: Yes | L21: Yes
A22: E-113 | C22: What is the manager/owner's name? | D22: Quel est le nom du gerant/propriétaire ? | F22: 1 | G22: E-113 Manager Name | H22: TEXT
A23: E-60 | C23: General Comments | D23: Commentaires | F23: 1 | H23: TEXT | I23: Open Verbatim Field | J23: Yes | K23: Yes | L23: Yes
A24: E-70 | C24: Time stamp END Interview | D24: Horodatage de fin d'entretien | F24: 1 | H24: DATE & TIME | I24: Device captures automatically. | J24: Yes | K24: Yes | L24: No

Sheet AREA Level 1
A2: SEQ ID | B2: ID | C2: Name -Reporting | D2: Name - App
A3: 1 | B3: CAM1 | C3: Adamaoua | D3: Adamaoua
A4: 2 | B4: CAM2 | C4: Centre | D4: Centre
A5: 3 | B5: CAM3 | C5: Est | D5: Est
A6: 4 | B6: CAM4 | C6: Extrême-Nord | D6: Extrême-Nord
A7: 5 | B7: CAM5 | C7: Littoral | D7: Littoral
A8: 6 | B8: CAM6 | C8: Nord | D8: Nord
A9: 7 | B9: CAM7 | C9: Nord-Ouest | D9: Nord-Ouest
A10: 8 | B10: CAM8 | C10: Ouest | D10: Ouest
A11: 9 | B11: CAM9 | C11: Sud | D11: Sud
A12: 10 | B12: CAM10 | C12: Sud-Ouest | D12: Sud-Ouest

Sheet Province List
A2: A-10 & A-20 & A-30 | B2: Regions | C2: Regions French | D2: Department / Sub regions | E2: Departement French | F2: Communes | G2: Commune French
A3: =+_xlfn.XLOOKUP(B3,'AREA Level 1'!C:C,'AREA Level 1'!B:B) -> CAM1 | B3: Adamaoua | D3: Mayo-Banyo | F3: Bankim
A4: =+_xlfn.XLOOKUP(B4,'AREA Level 1'!C:C,'AREA Level 1'!B:B) -> CAM1 | B4: Adamaoua | D4: Mayo-Banyo | F4: Banyo
A5: =+_xlfn.XLOOKUP(B5,'AREA Level 1'!C:C,'AREA Level 1'!B:B) -> CAM1 | B5: Adamaoua | D5: Vina | F5: Belel
A6: =+_xlfn.XLOOKUP(B6,'AREA Level 1'!C:C,'AREA Level 1'!B:B) -> CAM1 | B6: Adamaoua | D6: Mbéré | F6: Dir
A7: =+_xlfn.XLOOKUP(B7,'AREA Level 1'!C:C,'AREA Level 1'!B:B) -> CAM1 | B7: Adamaoua | D7: Mbéré | F7: Djohong
A8: =+_xlfn.XLOOKUP(B8,'AREA Level 1'!C:C,'AREA Level 1'!B:B) -> CAM1 | B8: Adamaoua | D8: Faro-et-Déo | F8: Galim-Tignere
A9: =+_xlfn.XLOOKUP(B9,'AREA Level 1'!C:C,'AREA Level 1'!B:B) -> CAM1 | B9: Adamaoua | D9: Faro-et-Déo | F9: Kontcha
A10: =+_xlfn.XLOOKUP(B10,'AREA Level 1'!C:C,'AREA Level 1'!B:B) -> CAM1 | B10: Adamaoua | D10: Vina | F10: Martap
A11: =+_xlfn.XLOOKUP(B11,'AREA Level 1'!C:C,'AREA Level 1'!B:B) -> CAM1 | B11: Adamaoua | D11: Faro-et-Déo | F11: Mayo-Baleo
A12: =+_xlfn.XLOOKUP(B12,'AREA Level 1'!C:C,'AREA Level 1'!B:B) -> CAM1 | B12: Adamaoua | D12: Mayo-Banyo | F12: Mayo-Darle
A13: =+_xlfn.XLOOKUP(B13,'AREA Level 1'!C:C,'AREA Level 1'!B:B) -> CAM1 | B13: Adamaoua | D13: Vina | F13: Mbe
A14: =+_xlfn.XLOOKUP(B14,'AREA Level 1'!C:C,'AREA Level 1'!B:B) -> CAM1 | B14: Adamaoua | D14: Mbéré | F14: Meiganga
... A365: =+_xlfn.XLOOKUP(B365,'AREA Level 1'!C:C,'AREA Level 1'!B:B) -> CAM10 | B365: Sud-Ouest | D365: Fako | F365: West-Coast
A366: =+_xlfn.XLOOKUP(B366,'AREA Level 1'!C:C,'AREA Level 1'!B:B) -> 0
A367: =+_xlfn.XLOOKUP(B367,'AREA Level 1'!C:C,'AREA Level 1'!B:B) -> 0

Sheet Sheet4
A2: A-10 & A-20 & A-30 | B2: Regions | C2: Regions French | D2: Department / Sub regions | E2: Departement French | F2: Communes | G2: Commune French
A3: CAM1 | B3: Adamaoua | D3: Mayo-Banyo | F3: Bankim | G3: =+_xlfn.XLOOKUP(D3,'AREA Level 2'!C:C,'AREA Level 2'!B:B) -> CAM_LV2_1
A4: CAM1 | B4: Adamaoua | D4: Mayo-Banyo | F4: Banyo | G4: =+_xlfn.XLOOKUP(D4,'AREA Level 2'!C:C,'AREA Level 2'!B:B) -> CAM_LV2_1
A5: CAM1 | B5: Adamaoua | D5: Vina | F5: Belel | G5: =+_xlfn.XLOOKUP(D5,'AREA Level 2'!C:C,'AREA Level 2'!B:B) -> CAM_LV2_2
A6: CAM1 | B6: Adamaoua | D6: Mbéré | F6: Dir | G6: =+_xlfn.XLOOKUP(D6,'AREA Level 2'!C:C,'AREA Level 2'!B:B) -> CAM_LV2_3
A7: CAM1 | B7: Adamaoua | D7: Mbéré | F7: Djohong | G7: =+_xlfn.XLOOKUP(D7,'AREA Level 2'!C:C,'AREA Level 2'!B:B) -> CAM_LV2_3
A8: CAM1 | B8: Adamaoua | D8: Faro-et-Déo | F8: Galim-Tignere | G8: =+_xlfn.XLOOKUP(D8,'AREA Level 2'!C:C,'AREA Level 2'!B:B) -> CAM_LV2_4
A9: CAM1 | B9: Adamaoua | D9: Faro-et-Déo | F9: Kontcha | G9: =+_xlfn.XLOOKUP(D9,'AREA Level 2'!C:C,'AREA Level 2'!B:B) -> CAM_LV2_4
A10: CAM1 | B10: Adamaoua | D10: Vina | F10: Martap | G10: =+_xlfn.XLOOKUP(D10,'AREA Level 2'!C:C,'AREA Level 2'!B:B) -> CAM_LV2_2
A11: CAM1 | B11: Adamaoua | D11: Faro-et-Déo | F11: Mayo-Baleo | G11: =+_xlfn.XLOOKUP(D11,'AREA Level 2'!C:C,'AREA Level 2'!B:B) -> CAM_LV2_4
A12: CAM1 | B12: Adamaoua | D12: Mayo-Banyo | F12: Mayo-Darle | G12: =+_xlfn.XLOOKUP(D12,'AREA Level 2'!C:C,'AREA Level 2'!B:B) -> CAM_LV2_1
A13: CAM1 | B13: Adamaoua | D13: Vina | F13: Mbe | G13: =+_xlfn.XLOOKUP(D13,'AREA Level 2'!C:C,'AREA Level 2'!B:B) -> CAM_LV2_2
A14: CAM1 | B14: Adamaoua | D14: Mbéré | F14: Meiganga | G14: =+_xlfn.XLOOKUP(D14,'AREA Level 2'!C:C,'AREA Level 2'!B:B) -> CAM_LV2_3
... A365: CAM10 | B365: Sud-Ouest | D365: Fako | F365: West-Coast | G365: =+_xlfn.XLOOKUP(D365,'AREA Level 2'!C:C,'AREA Level 2'!B:B) -> CAM_LV2_57
A366: 0 | G366: =+_xlfn.XLOOKUP(D366,'AREA Level 2'!C:C,'AREA Level 2'!B:B) -> 0
A367: 0 | G367: =+_xlfn.XLOOKUP(D367,'AREA Level 2'!C:C,'AREA Level 2'!B:B) -> 0

Sheet AREA Level 2
A2: SEQ ID | B2: ID | C2: Name -Reporting | D2: Name - App | E2: Level 1 ID
A3: 1 | B3: =_xlfn.CONCAT("CAM_LV2_",A3) -> CAM_LV2_1 | C3: Mayo-Banyo | D3: Mayo-Banyo | E3: =+_xlfn.XLOOKUP(D3,Sheet4!D:D,Sheet4!A:A) -> CAM1
A4: 2 | B4: =_xlfn.CONCAT("CAM_LV2_",A4) -> CAM_LV2_2 | C4: Vina | D4: Vina | E4: =+_xlfn.XLOOKUP(D4,Sheet4!D:D,Sheet4!A:A) -> CAM1
A5: 3 | B5: =_xlfn.CONCAT("CAM_LV2_",A5) -> CAM_LV2_3 | C5: Mbéré | D5: Mbéré | E5: =+_xlfn.XLOOKUP(D5,Sheet4!D:D,Sheet4!A:A) -> CAM1
A6: 4 | B6: =_xlfn.CONCAT("CAM_LV2_",A6) -> CAM_LV2_4 | C6: Faro-et-Déo | D6: Faro-et-Déo | E6: =+_xlfn.XLOOKUP(D6,Sheet4!D:D,Sheet4!A:A) -> CAM1
A7: 5 | B7: =_xlfn.CONCAT("CAM_LV2_",A7) -> CAM_LV2_5 | C7: Djérem | D7: Djérem | E7: =+_xlfn.XLOOKUP(D7,Sheet4!D:D,Sheet4!A:A) -> CAM1
A8: 6 | B8: =_xlfn.CONCAT("CAM_LV2_",A8) -> CAM_LV2_6 | C8: Mefou-et-Afamba | D8: Mefou-et-Afamba | E8: =+_xlfn.XLOOKUP(D8,Sheet4!D:D,Sheet4!A:A) -> CAM2
A9: 7 | B9: =_xlfn.CONCAT("CAM_LV2_",A9) -> CAM_LV2_7 | C9: Nyong-et-So'o | D9: Nyong-et-So'o | E9: =+_xlfn.XLOOKUP(D9,Sheet4!D:D,Sheet4!A:A) -> CAM2
A10: 8 | B10: =_xlfn.CONCAT("CAM_LV2_",A10) -> CAM_LV2_8 | C10: Mefou-et-Akono | D10: Mefou-et-Akono | E10: =+_xlfn.XLOOKUP(D10,Sheet4!D:D,Sheet4!A:A) -> CAM2
A11: 9 | B11: =_xlfn.CONCAT("CAM_LV2_",A11) -> CAM_LV2_9 | C11: Nyong-et-Mfoumou | D11: Nyong-et-Mfoumou | E11: =+_xlfn.XLOOKUP(D11,Sheet4!D:D,Sheet4!A:A) -> CAM2
A12: 10 | B12: =_xlfn.CONCAT("CAM_LV2_",A12) -> CAM_LV2_10 | C12: Mbam-et-Inoubou | D12: Mbam-et-Inoubou | E12: =+_xlfn.XLOOKUP(D12,Sheet4!D:D,Sheet4!A:A) -> CAM2
A13: 11 | B13: =_xlfn.CONCAT("CAM_LV2_",A13) -> CAM_LV2_11 | C13: Lekié | D13: Lekié | E13: =+_xlfn.XLOOKUP(D13,Sheet4!D:D,Sheet4!A:A) -> CAM2
A14: 12 | B14: =_xlfn.CONCAT("CAM_LV2_",A14) -> CAM_LV2_12 | C14: Haute-Sanaga | D14: Haute-Sanaga | E14: =+_xlfn.XLOOKUP(D14,Sheet4!D:D,Sheet4!A:A) -> CAM2
... A60: 58 | B60: =_xlfn.CONCAT("CAM_LV2_",A60) -> CAM_LV2_58 | C60: Meme | D60: Meme | E60: =+_xlfn.XLOOKUP(D60,Sheet4!D:D,Sheet4!A:A) -> CAM10
A61: 59
A62: 60
A63: 61
A64: 62
A65: 63
A66: 64
A67: 65

Sheet I&M Lists
B1: Question | C1: Code | D1: List name | E1: Question Wording ENGLISH | G1: Question Wording Arabic
B2: I-20 | C2: IR | D2: LST-INTERVIEWEE-ROLE | E2: Interviewee Roles
B3: 1 | C3: =CONCATENATE($C$2,"-",B3) -> IR-1 | E3: Manager | G3: Gérant
B4: 2 | C4: =CONCATENATE($C$2,"-",B4) -> IR-2 | E4: Owner | G4: Propriétaire
B5: 3 | C5: =CONCATENATE($C$2,"-",B5) -> IR-3 | E5: Other | G5: Autre
B8: I-40 | C8: CO | D8: LST-CONTINUE | E8: Continue Survey
B9: 1 | C9: =CONCATENATE($C$8,"-",B9) -> CO-1 | E9: YES - Continue with the survey | G9: Oui - Poursuivre l'entretien
B10: 2 | C10: =CONCATENATE($C$8,"-",B10) -> CO-2 | E10: NO - Appointment | G10: Non - Prise de rendez-vous
B11: 3 | C11: =CONCATENATE($C$8,"-",B11) -> CO-3 | E11: NO - Refused | G11: Non - Refus
B12: 4 | C12: =CONCATENATE($C$8,"-",B12) -> CO-4 | E12: NO - Closed | G12: Non - Fermé
B15: I-130 | C15: SEG | D15: LST-SEGMENT | E15: Segment Options | G15: Segment Options
B16: 1 | C16: =CONCATENATE($C$15,"-",B16) -> SEG-1 | E16: To consumers | G16: Aux consommateurs
B17: 2 | C17: =CONCATENATE($C$15,"-",B17) -> SEG-2 | E17: To other retailers | G17: Aux autres points de vente
B20: PT | C20: DIS | D20: LST-PER-DISTRIBUTION | E20: % Distributor
B21: 1 | C21: =CONCATENATE($C$20,"-",B21) -> DIS-1 | E21: Less than 10% | G21: Moins de 10%
B22: 2 | C22: =CONCATENATE($C$20,"-",B22) -> DIS-2 | E22: Between 10 - 20% | G22: Entre 10 - 20%
B23: 3 | C23: =CONCATENATE($C$20,"-",B23) -> DIS-3 | E23: Between 20 - 30% | G23: Entre 20 - 30%
B24: 4 | C24: =CONCATENATE($C$20,"-",B24) -> DIS-4 | E24: Between 30 - 40% | G24: Entre 30 - 40%
B25: 5 | C25: =CONCATENATE($C$20,"-",B25) -> DIS-5 | E25: Between 40 - 50% | G25: Entre 40 - 50%
B27: W-250 | C27: SUS | D27: LST-SUPPLIER-SUPPORT | E27: Supplier Support
B28: 1 | C28: =CONCATENATE($C$27,"-",B28) -> SUS-1 | E28: Price | G28: Prix
B29: 2 | C29: =CONCATENATE($C$27,"-",B29) -> SUS-2 | E29: Promotion | G29: Promotion
B30: 3 | C30: =CONCATENATE($C$27,"-",B30) -> SUS-3 | E30: Relationship | G30: Relationnel
B31: 4 | C31: =CONCATENATE($C$27,"-",B31) -> SUS-4 | E31: Fast & effective delivery | G31: Livraison rapide & efficace
B32: 5 | C32: =CONCATENATE($C$27,"-",B32) -> SUS-5 | E32: Availability | G32: Disponibilité
B33: 6 | C33: =CONCATENATE($C$27,"-",B33) -> SUS-6 | E33: Activation (activities,materials and equipment) | G33: Activation (activités,materiels et équipements)
B34: 7 | C34: =CONCATENATE($C$27,"-",B34) -> SUS-7 | E34: Merchandising | G34: Merchandising
B35: 8 | C35: =CONCATENATE($C$27,"-",B35) -> SUS-8 | E35: Proximity | G35: Proximité
B36: 9 | C36: =CONCATENATE($C$27,"-",B36) -> SUS-9 | E36: Assortment | G36: Assortiment
B37: 10 | C37: =CONCATENATE($C$27,"-",B37) -> SUS-10 | E37: Quality | G37: Qualité
B39: Multiple | C39: SUP | D39: LST-VISIBLEBRAND | E39: Visibility Brands
B40: 2 | C40: =CONCATENATE($C$39,"-",B40) -> SUP-2 | E40: JTI | G40: JTI
B41: 3 | C41: =CONCATENATE($C$39,"-",B41) -> SUP-3 | E41: BAT | G41: BAT
B42: 4 | C42: =CONCATENATE($C$39,"-",B42) -> SUP-4 | E42: PMI | G42: PMI
B43: 5 | C43: =CONCATENATE($C$39,"-",B43) -> SUP-5 | E43: Oriental | G43: ITG
B44: 6 | C44: =CONCATENATE($C$39,"-",B44) -> SUP-6 | E44: KT&G | G44: SNTA
B45: 7 | C45: =CONCATENATE($C$39,"-",B45) -> SUP-7 | E45: Other | G45: Other Branded
B46: 8 | C46: =CONCATENATE($C$39,"-",B46) -> SUP-8
B47: 9 | C47: =CONCATENATE($C$39,"-",B47) -> SUP-9
B48: 10 | C48: =CONCATENATE($C$39,"-",B48) -> SUP-10
B51: M-125 | E51: Digital Apps
B52: 1
B53: 2
B54: 3
B55: 4
B56: 5
B57: 6
B60: D-10 ... D-50 | C60: SOUR | D60: LST-SOURCE | E60: Cigarette Sources (update)
B61: 1 | C61: =CONCATENATE($C$60,"-",B61) -> SOUR-1 | E61: Never in my assortment | G61: Produit non disponible dans mon assortiment
B62: 2 | C62: =CONCATENATE($C$60,"-",B62) -> SOUR-2 | E62: Wholesaler Delivery | G62: Livraison du grossiste
B63: 3 | C63: =CONCATENATE($C$60,"-",B63) -> SOUR-3 | E63: Wholelsaler Pick-up | G63: Collecte chez le grossiste
B64: 4 | C64: =CONCATENATE($C$60,"-",B64) -> SOUR-4 | E64: Semi-Wholesaler Delivery | G64: Livraison du semi-grossiste
B65: 5 | C65: =CONCATENATE($C$60,"-",B65) -> SOUR-5 | E65: Semi-Wholesaler Pick-up | G65: Collecte chez le semi-grossiste
B66: 6 | C66: =CONCATENATE($C$60,"-",B66) -> SOUR-6 | E66: Retailer (supermarket, ect) pick-up | G66: Achat chez les detaillants (Boutique, Supermarché, ....)
B67: 7 | C67: =CONCATENATE($C$60,"-",B67) -> SOUR-7 | E67: Trade and Marketing rep top up sales | G67: Vente directe des délégues commerciaux
B68: 8 | C68: =CONCATENATE($C$60,"-",B68) -> SOUR-8 | E68: multi-brand saler | G68: Vendeur multicarde
B69: 9 | C69: =CONCATENATE($C$60,"-",B69) -> SOUR-9 | E69: Distributor / Sub Distributor | G69: Distributeur / Sous distributeur
B71: D-11….D-51 | C71: TYPE | D71: LST-ORDER-METHODE | E71: Orders Methods
B72: 1 | C72: =CONCATENATE($C$71,"-",B61) -> TYPE-1 | E72: Phone In | G72: Appel téléphonique
B73: 2 | C73: =CONCATENATE($C$71,"-",B62) -> TYPE-2 | E73: Collection | G73: Collecte
B74: 3 | C74: =CONCATENATE($C$71,"-",B63) -> TYPE-3 | E74: While Visiting | G74: Pendant la visite
B75: 4 | C75: =CONCATENATE($C$71,"-",B64) -> TYPE-4 | E75: Pre-Order | G75: Pre-commande
B77: D-19 | E77: Wholesalers/Distributors
B78: 1 | E78: Alotau Enterprises
B79: 2 | E79: Andersons Foodland - Kpo
B80: 3 | E80: Andersons Foodland Lae
B81: 4 | E81: Auskoa Limited
B83: D-100 | C83: SR | D83: LST-SALES-REPS-DYN | E83: Sales Rep
B84: 1 | C84: =CONCATENATE($C$83,"-",B84) -> SR-1 | E84: JTI (Aspen, Winston) | G84: JTI (Aspen, Winston)
B85: 2 | C85: =CONCATENATE($C$83,"-",B85) -> SR-2 | E85: BAT (B&H, L&B, Rothmans, Diplomat) | G85: BAT (B&H, L&B, Rothmans, Diplomat)
B86: 3 | C86: =CONCATENATE($C$83,"-",B86) -> SR-3 | E86: PMI (Marlboro)? | G86: PMI (Marlboro)?
B87: 4 | C87: =CONCATENATE($C$83,"-",B87) -> SR-4 | E87: Oriental (Gold Seal, Oris, D&J) | G87: Oriental (Gold Seal, Oris, D&J)
B88: 5 | C88: =CONCATENATE($C$83,"-",B88) -> SR-5 | E88: KT&G (Esse, Time) | G88: KT&G (Esse, Time)
B89: 6 | C89: =CONCATENATE($C$83,"-",B89) -> SR-6 | E89: Other | G89: Other
B90: 7
B91: 8
B92: 9
B93: 10
B96: D-101 … D-109 | C96: VF | D96: LST-VISIT-FREQUENCY | E96: Visit Frequency
B97: 1 | C97: =CONCATENATE($C$96,"-",B97) -> VF-1 | E97: Less than once per month | G97: Moins d'une fois par mois
B98: 2 | C98: =CONCATENATE($C$96,"-",B98) -> VF-2 | E98: Once a month | G98: Une fois par mois
B99: 3 | C99: =CONCATENATE($C$96,"-",B99) -> VF-3 | E99: Once every 2 weeks | G99: Une fois toute les 2 semaines
B100: 4 | C100: =CONCATENATE($C$96,"-",B100) -> VF-4 | E100: Once a week or more | G100: Une fois ou plus par semaine
B103: M-103 | D103: LST-TRADE-LICENSE | E103: Trading License
B104: 1 | C104: =CONCATENATE($C$110,"-",B104) -> REG-1 | E104: Provincial License | G104: Licence Provinciale
B105: 2 | C105: =CONCATENATE($C$110,"-",B105) -> REG-2 | E105: National License | G105: Licence Nationale
B106: 3 | C106: =CONCATENATE($C$110,"-",B106) -> REG-3 | E106: No License | G106: Pas de Licence
B110: M-103 | C110: REG | D110: LST-REGION-DYN | E110: Region
B111: 1 | C111: =CONCATENATE($C$110,"-",B111) -> REG-1 | E111: Center | G111: Centre
B112: 2 | C112: =CONCATENATE($C$110,"-",B112) -> REG-2 | E112: Est | G112: Est
B113: 3 | C113: =CONCATENATE($C$110,"-",B113) -> REG-3 | E113: Ouest | G113: Ouest
B117: M-103 | C117: CAT | D117: LST-PRODUCT-CATEGORIES | E117: CATEGORIES
B118: 1 | C118: =CONCATENATE($C$117,"-",B118) -> CAT-1 | E118: Tobacco (in Packs) | G118: Tabac (Packs)
B119: 2 | C119: =CONCATENATE($C$117,"-",B119) -> CAT-2 | E119: Tobacco (in Bundle) | G119: Tabac (Bundle)
B120: 3 | C120: =CONCATENATE($C$117,"-",B120) -> CAT-3 | E120: Tobacco WHOLESALER (in Master Case) | G120: Grossiste de Tabac ()
B121: 4 | C121: =CONCATENATE($C$117,"-",B121) -> CAT-4 | E121: Shisa (in Kg) | G121: Shisha (Kg)
B122: 5 | C122: =CONCATENATE($C$117,"-",B122) -> CAT-5 | E122: Evapes | G122: Vapoteurs
B123: 6 | C123: =CONCATENATE($C$117,"-",B123) -> CAT-6 | E123: Electronic cigarettes | G123: Cigarettes Electronique
B126: M-103 | C126: CAT | D126: LBL-PRODUCT-CAT-UNITS | E126: CAT-UNITS
B127: 1 | C127: =CONCATENATE($C$117,"-",B127) -> CAT-1 | E127: Packs | G127: Paquet
...

Sheet Constants
A1: Answer Options
A2: TEXT
A3: SYSTEM
A4: NOTE
A5: DATE & TIME
A6: PHOTOGRAPH
A7: SINGLE SELECTION
A8: MULTIPLE SELECTION
A9: MULTIPLE SELECTION (min 1, max 2)
A10: MULTIPLE SELECTION (min 1, max 3)
A11: MULTIPLE SELECTION (min 2, max 2)
A12: MULTIPLE SELECTION (max 3)
... A16: GPS

Sheet C&C Lists
A1: IFUQ-10 | B1: Channel Type
A2: 1 | B2: On-Trade
A3: 2 | B3: Off-Trade
A4: 3 | B4: Distributor
A6: IFUQ-20 | B6: Interviewee Role
A7: 1 | B7: Manager
A8: 2 | B8: Owner
A9: 3 | B9: Bartender
A10: 4 | B10: Consumer
A12: IFUQ-40 | B12: Continue Survey
A13: 1 | B13: YES - Continue with the survey
A14: 2 | B14: NO - Appointment
A15: 3 | B15: NO - Refused
A18: VFUQ-10 | B18: Gender
A19: 1 | B19: Male
A20: 2 | B20: Female
A22: VFUQ-20 | B22: Age Group
A23: 1 | B23: 18-24
A24: 2 | B24: 25-34
A25: 3 | B25: 35-44
A26: 4 | B26: 45+
A28: VFUQ-30 | B28: Professional Group
A29: 1 | B29: Employees or Students
A30: 2 | B30: Business People
A31: 3 | B31: Government
A32: 4 | B32: Expat
A33: 5 | B33: All of the above
A35: VFUQ-50 | B35: Educational Level
A36: 1 | B36: No diploma
A37: 2 | B37: High School
A38: 3 | B38: Higher
A40: VFUQ-60 | B40: Purchasing Power
A41: 1 | B41: Low
A42: 2 | B42: Medium
A43: 3 | B43: High
A45: VFUQ-90 | B45: Busiest Hours
A46: 1 | B46: 9am-11am
A47: 2 | B47: 11am-5pm
A48: 3 | B48: 5pm-9pm
A49: 4 | B49: 9pm-1am
A50: 5 | B50: 1am-5am
A52: VFUQ-100 VFUQ-150 | B52: Days of week
A53: 1 | B53: Monday
A54: 2 | B54: Tuesday
A55: 3 | B55: Wednesday
A56: 4 | B56: Thursday
A57: 5 | B57: Friday
A58: 6 | B58: Saturday
A59: 7 | B59: Sunday
A61: VFUQ-110 | B61: Months
A62: 1 | B62: January
A63: 2 | B63: February
A64: 3 | B64: March
A65: 4 | B65: April
A66: 5 | B66: May
A67: 6 | B67: June
A68: 7 | B68: July
A69: 8 | B69: August
A70: 9 | B70: September
A71: 10 | B71: October
A72: 11 | B72: November
A73: 12 | B73: December
A75: VFUQ-130 | B75: Outlet Age
A76: 1 | B76: Less than 1 month
A77: 2 | B77: 1 to 6 months
A78: 3 | B78: 6 months to 1 Year
A79: 4 | B79: 1 to 3 years
A80: 5 | B80: 3 to 10 years
A81: 6 | B81: Over 10 years
A83: VFUQ-140 | B83: Visit Time
A84: 1 | B84: First time
A85: 2 | B85: First month
A86: 3 | B86: Between 1-12 months
A87: 4 | B87: More than a year
A89: VFUQ-160 | B89: Visit Frequency
A90: 1 | B90: Daily
A91: 2 | B91: Multiple times per week
A92: 3 | B92: Weekly
A93: 4 | B93: Once every 2 weeks
A94: 5 | B94: Monthly
A95: 6 | B95: Occassionally
A97: VFUQ-170 | B97: Visit Company
A98: 1 | B98: Alone
A99: 2 | B99: Friends
A100: 3 | B100: Colleagues
A101: 4 | B101: Family
A103: VFUQ-180 | B103: Hobbies
A104: 1 | B104: Politics
A105: 2 | B105: Sports
A106: 3 | B106: Music
A107: 4 | B107: Culture
A108: 5 | B108: Travel
A110: VFUQ-190 | B110: Household Build Up
A111: 1 | B111: Alone
A112: 2 | B112: Partner
A113: 3 | B113: Children
A114: 4 | B114: Friends
A116: VFUQ-240 | B116: Visit Reasons
A117: 1 | B117: Atmosphere
A118: 2 | B118: Proximity
...

Sheet C&C Driver Start
A1: Question fields | G1: Answer fields | J1: Backoffice | M1: Comments
A2: ID | B2: Visibility rule | C2: QUESTION WORDING EN | D2: QUESTION WORDING __ | E2: Wording change | F2: Question Priority 1 Keep 0 Discuss -1 remove ? | G2: Reporting LABEL | H2: ANSWER TYPE | I2: ANSWER OPTIONS | J2: Visible ENUMERATOR | K2: VISIBLE BC | L2: PREFILLED FOR BC | M2: ___ | N2: CSD | O2: Dev-team
A3: IFUQ-1 | C3: GPS | H3: GPS | I3: Auto Filled | K3: No
A4: IFUQ-10 | C4: Confirm the channel that you are in | H4: SINGLE SELECTION | I4: Channel Type | K4: No
A5: IFUQ-20 | B5: If IFQ | C5: Who are you speaking to? | H5: SINGLE SELECTION | I5: Interviewee Role | K5: No
A6: IFUQ-30 | B6: I-10=ON or I-10=OFF | C6: INTRODUCTION: My name is .… A colleague of mine has recently visited you to collect information regarding a Trade Census. I would like to have follow-up qualititative survey withyourself and a small number of your consumers. The objective is to assist the company to better understand the market and eventually improve service to you and your consumers | H6: NOTE | I6: 1. NEXT | K6: No
A7: IFUQ-31 | B7: i-10=RTM | C7: INTRODUCTION: My name is ... A colleague of mine has recently visited you to collect information regarding a Trade Census. I would like to have follow-up qualitative survey with yourself. The objective is to assist the company to better understand the distribution landscape, your needs and eventually improve service to you. | H7: NOTE | I7: 1. NEXT | K7: No
A8: IFUQ-32 | B8: I-10=ON or I-10=OFF and IFUQ-20=C | C8: INTRODUCTION: My name is .… Our company is operating a market research analysis. The objective is to assist the company to better understand the market and the consummers. We would like to ask you a few questions as a consumer within this outlet, we will only take a few minutes of your time. | K8: No
A9: IFUQ-40 | C9: Would you have a few minutes available to answer some questions about your business? This should not take long. | H9: SINGLE SELECTION | I9: Continue Survey | K9: No

Sheet C&C Driver
I1: Comments
A2: ID | B2: Visibility rule | C2: QUESTION WORDING EN | D2: QUESTION WORDING __ | E2: REPORTING LABEL | F2: ANSWER TYPE | G2: ANSWER OPTIONS | H2: NOTES | I2: ___ | J2: CSD | K2: Dev-team
A3: Section Situation (header on multiple pages)
A4: VFUQ-10 | B4: (IFUQ-10=1 or2) and (IFUQ-20=C) | C4: Which gender is mostly represented in this outlet? | F4: SINGLE SELECTION | G4: Gender | H4: Observational
A5: VFUQ-20 | B5: (IFUQ-10=1 or2) and (IFUQ-20=C) | C5: Which age group is mostly represented in this outlet? | F5: SINGLE SELECTION | G5: Age Group | H5: Observational
A6: NEW PAGE
A7: VFUQ-30 | B7: (IFUQ-10=1 or2) and (IFUQ-20=C) | C7: Which professional group is mostly represented in this outlet? | F7: SINGLE SELECTION | G7: Professional Group | H7: Observational
A8: VFUQ-40 | B8: (IFUQ-10=1 or2) and (IFUQ-20=C) | C8: What nationality is mostly present in this outlet? | F8: SINGLE SELECTION | H8: Observational
A9: VFUQ-50 | B9: (IFUQ-10=1 or2) and (IFUQ-20=C) | C9: Which educational level is mostly represented in this outlet? | F9: SINGLE SELECTION | G9: Educational Level | H9: Observational
A10: NEW PAGE
A11: VFUQ-60 | B11: (IFUQ-10=1 or2) and (IFUQ-20 != C) | C11: What is the purchasing power of the consumer | F11: SINGLE SELECTION | G11: Purchasing Power | H11: Observational
A12: VFUQ-70 | B12: (IFUQ-10=1 or2) and (IFUQ-20 != C) | C12: Gender of the manager? | F12: SINGLE SELECTION | G12: Gender | H12: Observational
A13: VFUQ-80 | B13: (IFUQ-10=1 or2) and (IFUQ-20 != C) | C13: Age group of the manager? | F13: SINGLE SELECTION | G13: Age Group | H13: Observational
A14: NEW PAGE
A15: VFUQ-90 | B15: (IFUQ-10=1 or2) and (IFUQ-20 != C) | C15: What are the busiest hours of operation for you? | F15: SINGLE SELECTION | G15: Busiest Hours | H15: Asked
A16: VFUQ-100 | B16: (IFUQ-10=1 or2) and (IFUQ-20 != C) | C16: What are the busiest days of the week? | F16: MULTIPLE SELECTION (min 1, max 3) | G16: Days of the Week | H16: Asked
A17: NEW PAGE
A18: VFUQ-110 | B18: (IFUQ-10=1 or2) and (IFUQ-20 != C) | C18: What are the busiest months of the year? | F18: MULTIPLE SELECTION (min 1, max 3) | G18: Months | H18: Asked
A19: NEW PAGE
A20: VFUQ-120 | B20: (IFUQ-10=1 or2) and (IFUQ-20 != C) | C20: How many staff do you have working for your business? | F20: NUMERICAL | H20: Asked
A21: VFUQ-130 | B21: (IFUQ-10=1 or2) and (IFUQ-20 != C) | C21: How old is this outlet? | F21: SINGLE SELECTION | G21: Outlet Age | H21: Asked
A22: NEW PAGE
A23: VFUQ-140 | B23: (IFUQ-10=1 or2) and (IFUQ-20=C) | C23: How long have you been visiting this outlet? | F23: SINGLE SELECTION | G23: Visit Time | H23: Asked
A24: VFUQ-150 | B24: (IFUQ-10=1 or2) and (IFUQ-20=C) | C24: Which day(s) do you visit this type of outlet normally? | F24: MULTIPLE SELECTION (min 1, max 3) | G24: See Days of the Week | H24: Asked
A25: NEW PAGE
A26: VFUQ-160 | B26: (IFUQ-10=1 or2) and (IFUQ-20=C) | C26: How frequent do you visit this outlet normally? | F26: SINGLE SELECTION | G26: Visit Frequency | H26: Asked
A27: VFUQ-170 | B27: (IFUQ-10=1 or2) and (IFUQ-20=C) | C27: In what company do you visit this outlet normally? | F27: SINGLE SELECTION | G27: Visit Company | H27: Asked
A28: NEW PAGE
A29: VFUQ-180 | B29: (IFUQ-10=1 or2) and (IFUQ-20=C) | C29: What are your main interests/ hobbies | F29: MULTIPLE SELECTION (min 1, max 3) | G29: Hobbies | H29: Asked
A30: VFUQ-190 | B30: (IFUQ-10=1 or2) and (IFUQ-20=C) | C30: What is the build up of your household? | F30: SINGLE SELECTION | G30: Household Build Up | H30: Asked
A31: NEW PAGE
A32: VFUQ-200 | B32: (IFUQ-10=1 or2) and (IFUQ-20 != C) | C32: Is there an exterior area? | F32: SINGLE SELECTION | G32: Yes/No | H32: Observational
A33: VFUQ-210 | B33: (IFUQ-10=1 or2) and (IFUQ-20 != C) and VFUQ-200 = Y | C33: Is it bigger than the interior area? | F33: SINGLE SELECTION | G33: Yes/No | H33: Observational
A34: VFUQ-220 | B34: (IFUQ-10=1 or2) and (IFUQ-20 != C) | C34: How many fridges are there here in the outlet? | F34: NUMERICAL | H34: Observational
A35: VFUQ-230 | B35: (IFUQ-10=1 or2) and (IFUQ-20 != C) | C35: How many are used to stock beer? | F35: NUMERICAL | H35: Observational
A36: NEW PAGE
A37: Section Motivation (header on multiple pages)
A38: VFUQ-240 | B38: (IFUQ-10=1) and (IFUQ-20 = C) | C38: For which main reasons do you visit this outlet? | F38: MULTIPLE SELECTION (min 1, max 3) | G38: Visit Reasons | H38: Asked
A39: NEW PAGE
A40: VFUQ-250 | B40: (IFUQ-10=2) and (IFUQ-20 = C) | C40: What type of shopping are you doing? | F40: SINGLE SELECTION | G40: Shopping Type | H40: Asked
A41: VFUQ-260 | B41: (IFUQ-10=1 or2) and (IFUQ-20 = C) | C41: Do you drink beer? | F41: SINGLE SELECTION | G41: Yes/No | H41: Asked
A42: VFUQ-270 | B42: (IFUQ-10=1 or2) and (IFUQ-20 = C) and (VFUQ-260=Y) | C42: Why do you drink beer? | F42: SINGLE SELECTION | G42: Beer Reasons | H42: Asked
A43: VFUQ-280 | B43: (IFUQ-10=1 or2) and (IFUQ-20 = C) and (VFUQ-260=N) | C43: Why do you NOT drink beer? | F43: SINGLE SELECTION | G43: Beer NOT Reasons | H43: Asked
A44: NEW PAGE
A45: VFUQ-290 | B45: (IFUQ-10=2) and (IFUQ-20=C) | C45: Who do you buy beer for? | F45: MULTIPLE SELECTION (min 1, max 3) | G45: Beer WHO | H45: Asked
A46: NEW PAGE
A47: VFUQ-300 | B47: (IFUQ-10=1 or2) and (IFUQ-20 = C) and (VFUQ-260=Y) | C47: What beer is most important to you? | F47: SINGLE SELECTION | G47: Beer WHAT | H47: Asked
A48: VFUQ-310 | B48: (IFUQ-10=1 or2) and (IFUQ-20 = C) and (VFUQ-260=Y) | C48: What is the main reason for you to drink beer? | F48: SINGLE SELECTION | G48: Beer WHY | H48: Asked
A49: VFUQ-320 | B49: (IFUQ-10=1 or2) and (IFUQ-20 = C) and (VFUQ-260=Y) | C49: Will you drink other beers? | F49: SINGLE SELECTION | G49: Yes/No | H49: Asked
A50: NEW PAGE
A51: VFUQ-330 | B51: (IFUQ-10=1 or2) and (IFUQ-20 = C) | C51: Is the price of beer important to you? | F51: SINGLE SELECTION | G51: Yes/No | H51: Asked
A52: VFUQ-340 | B52: (IFUQ-10=1 or2) and (IFUQ-20 = C) | C52: Is alcohol content in beer important to you? If yes what is you ideal % content ? | F52: SINGLE SELECTION | G52: Alcohol Content | H52: Asked
A53: NEW PAGE
A54: VFUQ-350 | B54: (IFUQ-10=1 or2) and (IFUQ-20 = C) | C54: Do you check the price of beer before ordering/ buying? | F54: SINGLE SELECTION | G54: Yes/No | H54: Asked
A55: VFUQ-360 | B55: (IFUQ-10=1 or2) and (IFUQ-20 = C) | C55: If you do not see your favorite beer, will you…? | F55: SINGLE SELECTION | G55: Beer NEXT | H55: Asked
A56: NEW PAGE
A57: VFUQ-370 | B57: (IFUQ-10=1 or2) and (IFUQ-20 = C) | C57: Can the personel influence you order / purchase? | F57: SINGLE SELECTION | G57: Yes/No | H57: Asked
A58: VFUQ-380 | B58: (IFUQ-10=1 or2) and (IFUQ-20 = C) | C58: Do you like promotions? | F58: SINGLE SELECTION | G58: Yes/No | H58: Asked
A59: VFUQ-390 | B59: (IFUQ-10=1) and (IFUQ-20 = C) | C59: What type of promotions would influence you to buy a brand? (ON) | F59: SINGLE SELECTION | G59: Promotions | H59: Asked
A60: VFUQ-400 | B60: (IFUQ-10=2) and (IFUQ-20 = C) | C60: What type of promotions would influence you to buy a brand? (OFF) | F60: SINGLE SELECTION | G60: Promotions | H60: Asked
A61: NEW PAGE
A62: VFUQ-410 | B62: (IFUQ-10=1 or2) and (IFUQ-20=!C) | C62: What are some of the challenges of your job? | F62: TEXT | H62: Asked
A63: VFUQ-420 | B63: (IFUQ-10=1 or2) and (IFUQ-20=!C) | C63: Are you searching for an assortment of beer brands? | F63: SINGLE SELECTION | G63: Yes/No | H63: Asked
A64: VFUQ-430 | B64: (IFUQ-10=1 or2) and (IFUQ-20=!C) | C64: Which beer brands is most important to you? | F64: SINGLE SELECTION | G64: Beer WHAT | H64: Asked
A65: NEW PAGE
A66: VFUQ-440 | B66: (IFUQ-10=1 or2) and (IFUQ-20=!C) | C66: Which services from your beer suppliers are most important to you? | F66: SINGLE SELECTION | G66: Beer Services | H66: Asked
A67: VFUQ-450 | B67: (IFUQ-10=1 or2) and (IFUQ-20=!C) | C67: Which services are most important but are not being provided satisfactorily? | F67: SINGLE SELECTION | G67: Beer Services | H67: Asked
A68: NEW PAGE
A69: VFUQ-460 | B69: (IFUQ-10=1 or2) and (IFUQ-20=!C) | C69: What would you say helps your outlet to sell beer brands fastest? | F69: SINGLE SELECTION | G69: Beer Sales Help | H69: Asked
A70: VFUQ-470 | B70: (IFUQ-10=1 or2) and (IFUQ-20=!C) | C70: What activations have the biggest impact on your sales? | F70: SINGLE SELECTION | G70: Activations | H70: Asked
A71: VFUQ-480 | B71: (IFUQ-10=1 or2) and (IFUQ-20=!C) | C71: What is the most important thing in the relationship with your beer supplier? | F71: SINGLE SELECTION | G71: Supplier Relationship | H71: Asked
A72: NEW PAGE
A73: Section Perception (header on multiple pages)
A74: VFUQ-490 | B74: (IFUQ-10=1) and (IFUQ-20=C) | C74: What do you expect from an outlet like this? | F74: MULTIPLE SELECTION (min 1, max 3) | G74: Visit Reasons | H74: Asked
A75: NEW PAGE
A76: VFUQ-500 | B76: (IFUQ-10=1) and (IFUQ-20=C) | C76: What do you drink if you don't drink beer? | F76: SINGLE SELECTION | G76: Beer ALTERNATIVES | H76: Asked
A77: VFUQ-510 | B77: (IFUQ-10=1) and (IFUQ-20=C) | C77: Do you generally order the same beer brand? | F77: SINGLE SELECTION | G77: Yes/No | H77: Asked
A78: NEW PAGE
A79: VFUQ-520 | B79: (IFUQ-10=1) and (IFUQ-20=C) | C79: Do you prefer bottles or cans? | F79: SINGLE SELECTION | G79: Packaging | H79: Asked
A80: VFUQ-530 | B80: (IFUQ-10=1 or2) and (IFUQ-20=C) | C80: What size do you prefer? | F80: SINGLE SELECTION | G80: Size | H80: Asked
A81: VFUQ-540 | B81: (IFUQ-10=1 or2) and (IFUQ-20=C) | C81: Do you prefer to drink beer warm or cold? | F81: SINGLE SELECTION | G81: Temperature | H81: Asked
A82: NEW PAGE
A83: VFUQ-550 | B83: (IFUQ-10=1 or2) and (IFUQ-20=!C) | C83: For which main reasons do customers visit your outlet? | F83: SINGLE SELECTION | G83: Visit Reasons | H83: Asked
A84: NEW PAGE
A85: VFUQ-560 | B85: (IFUQ-10=1 or2) and (IFUQ-20=!C) | C85: How important are each of these beer brands in your outlet? | F85: Scale for each brand - Low/Medium/High | G85: Beer WHAT | H85: Asked
A86: VFUQ-620 | B86: (IFUQ-10=1 or2) and (IFUQ-20=!C) | C86: What are the most consumed beers? | F86: MULTIPLE SELECTION | G86: Beer WHAT | H86: Asked
A87: NEW PAGE
A88: Section Behaviour (header on multiple pages)
A89: VFUQ-630 | B89: (IFUQ-10=1) and (IFUQ-20=C) | C89: How many bottles/cans do you drink when coming to this outlet? | F89: NUMERICAL | G89: Open Numeric Field | H89: Asked
A90: VFUQ-640 | B90: (IFUQ-10=1) and (IFUQ-20=C) | C90: How long do you normally stay? | F90: SINGLE SELECTION | G90: Length of Stay | H90: Asked
A91: VFUQ-650 | B91: (IFUQ-10=1 or 2) and (IFUQ-20=C) | C91: Where were you before you came here? | F91: SINGLE SELECTION | G91: Locations Before/After | H91: Asked
A92: VFUQ-660 | B92: (IFUQ-10=1) and (IFUQ-20=C) | C92: Where do you go afterwards? | F92: SINGLE SELECTION | G92: Locations Before/After | H92: Asked
A93: NEW PAGE
A94: VFUQ-670 | B94: (IFUQ-10=1) and (IFUQ-20 != C) | C94: What main activities do people come to do in this outlet ? | F94: MULTIPLE SELECTION (min 1, max 3) | G94: Outlet Activities | H94: Observational
A95: VFUQ-680 | B95: (IFUQ-10=1) and (IFUQ-20 != C) | C95: Are they mostly sitting or standing? | F95: SINGLE SELECTION | G95: Sit/Stand | H95: Observational
A96: NEW PAGE
A97: VFUQ-690 | B97: (IFUQ-10=1) and (IFUQ-20 != C) | C97: How do they order? | F97: SINGLE SELECTION | G97: Order Method | H97: Observational
A98: VFUQ-700 | B98: (IFUQ-10=1) and (IFUQ-20 != C) | C98: What is the most purchased drink? | F98: SINGLE SELECTION | G98: Most Purchased Drink | H98: Observational
A99: NEW PAGE
A100: VFUQ-710 | B100: (IFUQ-10=1 or2) and (IFUQ-20!=C) | C100: What type of SKU is mostly displayed? (Bottles and Cans) | F100: SINGLE SELECTION | G100: SKU Type | H100: Observational
...

Sheet Follow-up quality Distributor Q
A2: ID | B2: Visibility rule | C2: QUESTION WORDING EN | D2: QUESTION WORDING __ | E2: REPORTING LABEL | F2: ANSWER TYPE | G2: ANSWER OPTIONS | H2: NOTES | I2: ___ | J2: CSD | K2: Dev-team
A3: DFUQ-10 | B3: IFUQ-10=RTM | C3: Who are your customers? | F3: MULTIPLE SELECTION | G3: Merged List I-131 & I-132 & I-133
A4: NEW PAGE
A5: DFUQ-20 | B5: IFUQ-10=RTM | C5: Do you help with any supplier activations/promotions? | F5: SINGLE SELECTION | G5: Yes/No
A6: DFUQ-30 | B6: IFUQ-10=RTM | C6: Do you have a sales/ delivery team? | F6: SINGLE SELECTION | G6: Yes/No
A7: DFUQ-40 | B7: IFUQ-10=RTM; DFUQ-30=Y | C7: Does your sales team work with a routing/journey plan? | F7: SINGLE SELECTION | G7: Yes/No
A8: DFUQ-50 | B8: IFUQ-10=RTM; DFUQ-30=Y | C8: What are their responsibilities? | F8: MULTIPLE SELECTION | G8: Responsibility
A9: NEW PAGE
A10: DFUQ-60 | B10: IFUQ-10=RTM | C10: How many people work for your business? | F10: NUMERICAL | G10: Open Numeric Field
A11: DFUQ-70 | B11: IFUQ-10=RTM | C11: Do you offer credit terms? | F11: SINGLE SELECTION | G11: Yes/No
A12: DFUQ-80 | B12: IFUQ-10=RTM | C12: How are your orders made? | F12: MULTIPLE SELECTION | G12: Order Methods
A13: NEW PAGE
A14: DFUQ-90 | B14: IFUQ-10=RTM | C14: Do you do sales forecasting? | F14: SINGLE SELECTION | G14: Yes/No
A15: DFUQ-100 | B15: IFUQ-10=RTM | C15: How often do you buy per week(inbound stock)? | F15: NUMERICAL | G15: 0 to 7
A16: DFUQ-110 | B16: IFUQ-10=RTM | C16: Do you measure your stock? | F16: SINGLE SELECTION | G16: Yes/No
A17: DFUQ-130 | B17: IFUQ-10=RTM | C17: How many trucks do you have? | F17: NUMERICAL | G17: Open Numeric Field
A18: DFUQ-140 | B18: IFUQ-10=RTM | C18: How many tricycles do you have? | F18: NUMERICAL | G18: Open Numeric Field
A19: NEW PAGE
A20: DFUQ-160 | B20: IFUQ-10=RTM | C20: Do you use a computer for your business? | F20: SINGLE SELECTION | G20: Yes/No
A21: DFUQ-170 | B21: IFUQ-10=RTM | C21: Do you have internet? | F21: SINGLE SELECTION | G21: Yes/No
A22: DFUQ-190 | B22: IFUQ-10=RTM | C22: Do you incentivise your sales reps? | F22: SINGLE SELECTION | G22: Yes/No
A23: DFUQ-200 | B23: IFUQ-10=RTM | C23: Do you have an overview of your customers and their accounts? | F23: SINGLE SELECTION | G23: Yes/No
A24: DFUQ-210 | B24: IFUQ-10=RTM | C24: Do you have all-day power? | F24: SINGLE SELECTION | G24: Yes/No
A25: NEW PAGE
A26: DFUQ-220 | B26: IFUQ-10=RTM | C26: What are the most important? | F26: TEXT | G26: Open Verbatim Field
A27: DFUQ-230 | B27: IFUQ-10=RTM | C27: How important are they? | F27: TEXT | G27: Open Verbatim Field
A28: NEW PAGE
A29: EndFUQ-1 | C29: Do you wish to interview another consumer in this location? | F29: SINGLE SELECTION | G29: Yes/No
A30: EFUQ-10 | C30: Time stamp END Interview? | F30: DATE & TIME | G30: System - Automatic
A31: EFUQ-20 | C31: I hereby certify that this interview has been carried out by me according to the instructions I received. | F31: NOTE
A32: EFUQ-30 | B32: IFUQ-1 is not captured. | C32: GPS location. | F32: GPS | G32: System - Automatic
A33: EFUQ-40 | C33: General Comments: | F33: TEXT | G33: Open Verbatim Field

Sheet Level2 Builder
B2: ID | C2: Name -Reporting | D2: Name - App | E2: Level 1 ID
B3: =+_xlfn.XLOOKUP(C3,'AREA Level 2'!C:C,'AREA Level 2'!B:B) -> CAM_LV2_1 | C3: Mayo-Banyo | D3: Mayo-Banyo | E3: =+_xlfn.XLOOKUP(D3,Sheet4!D:D,Sheet4!A:A) -> CAM1 | F3: =_xlfn.CONCAT(liststart,B3,listlareport,C3,listlat,D3,areavislv2,E3,areavisend) -> { "v": "CAM_LV2_1", "n" : { "SYS": "Mayo-Banyo", "EN": "Mayo-Banyo" }, "vi" : [ { "r": "A-10", "o": "=", "t": "v", "v": "CAM1" } ] },
B4: =+_xlfn.XLOOKUP(C4,'AREA Level 2'!C:C,'AREA Level 2'!B:B) -> CAM_LV2_2 | C4: Vina | D4: Vina | E4: =+_xlfn.XLOOKUP(D4,Sheet4!D:D,Sheet4!A:A) -> CAM1 | F4: =_xlfn.CONCAT(liststart,B4,listlareport,C4,listlat,D4,areavislv2,E4,areavisend) -> { "v": "CAM_LV2_2", "n" : { "SYS": "Vina", "EN": "Vina" }, "vi" : [ { "r": "A-10", "o": "=", "t": "v", "v": "CAM1" } ] },
B5: =+_xlfn.XLOOKUP(C5,'AREA Level 2'!C:C,'AREA Level 2'!B:B) -> CAM_LV2_3 | C5: Mbéré | D5: Mbéré | E5: =+_xlfn.XLOOKUP(D5,Sheet4!D:D,Sheet4!A:A) -> CAM1 | F5: =_xlfn.CONCAT(liststart,B5,listlareport,C5,listlat,D5,areavislv2,E5,areavisend) -> { "v": "CAM_LV2_3", "n" : { "SYS": "Mbéré", "EN": "Mbéré" }, "vi" : [ { "r": "A-10", "o": "=", "t": "v", "v": "CAM1" } ] },
B6: =+_xlfn.XLOOKUP(C6,'AREA Level 2'!C:C,'AREA Level 2'!B:B) -> CAM_LV2_4 | C6: Faro-et-Déo | D6: Faro-et-Déo | E6: =+_xlfn.XLOOKUP(D6,Sheet4!D:D,Sheet4!A:A) -> CAM1 | F6: =_xlfn.CONCAT(liststart,B6,listlareport,C6,listlat,D6,areavislv2,E6,areavisend) -> { "v": "CAM_LV2_4", "n" : { "SYS": "Faro-et-Déo", "EN": "Faro-et-Déo" }, "vi" : [ { "r": "A-10", "o": "=", "t": "v", "v": "CAM1" } ] },
B7: =+_xlfn.XLOOKUP(C7,'AREA Level 2'!C:C,'AREA Level 2'!B:B) -> CAM_LV2_5 | C7: Djérem | D7: Djérem | E7: =+_xlfn.XLOOKUP(D7,Sheet4!D:D,Sheet4!A:A) -> CAM1 | F7: =_xlfn.CONCAT(liststart,B7,listlareport,C7,listlat,D7,areavislv2,E7,areavisend) -> { "v": "CAM_LV2_5", "n" : { "SYS": "Djérem", "EN": "Djérem" }, "vi" : [ { "r": "A-10", "o": "=", "t": "v", "v": "CAM1" } ] },
B8: =+_xlfn.XLOOKUP(C8,'AREA Level 2'!C:C,'AREA Level 2'!B:B) -> CAM_LV2_6 | C8: Mefou-et-Afamba | D8: Mefou-et-Afamba | E8: =+_xlfn.XLOOKUP(D8,Sheet4!D:D,Sheet4!A:A) -> CAM2 | F8: =_xlfn.CONCAT(liststart,B8,listlareport,C8,listlat,D8,areavislv2,E8,areavisend) -> { "v": "CAM_LV2_6", "n" : { "SYS": "Mefou-et-Afamba", "EN": "Mefou-et-Afamba" }, "vi" : [ { "r": "A-10", "o": "=", "t": "v", "v": "CAM2" } ] },
B9: =+_xlfn.XLOOKUP(C9,'AREA Level 2'!C:C,'AREA Level 2'!B:B) -> CAM_LV2_7 | C9: Nyong-et-So'o | D9: Nyong-et-So'o | E9: =+_xlfn.XLOOKUP(D9,Sheet4!D:D,Sheet4!A:A) -> CAM2 | F9: =_xlfn.CONCAT(liststart,B9,listlareport,C9,listlat,D9,areavislv2,E9,areavisend) -> { "v": "CAM_LV2_7", "n" : { "SYS": "Nyong-et-So'o", "EN": "Nyong-et-So'o" }, "vi" : [ { "r": "A-10", "o": "=", "t": "v", "v": "CAM2" } ] },
B10: =+_xlfn.XLOOKUP(C10,'AREA Level 2'!C:C,'AREA Level 2'!B:B) -> CAM_LV2_8 | C10: Mefou-et-Akono | D10: Mefou-et-Akono | E10: =+_xlfn.XLOOKUP(D10,Sheet4!D:D,Sheet4!A:A) -> CAM2 | F10: =_xlfn.CONCAT(liststart,B10,listlareport,C10,listlat,D10,areavislv2,E10,areavisend) -> { "v": "CAM_LV2_8", "n" : { "SYS": "Mefou-et-Akono", "EN": "Mefou-et-Akono" }, "vi" : [ { "r": "A-10", "o": "=", "t": "v", "v": "CAM2" } ] },
B11: =+_xlfn.XLOOKUP(C11,'AREA Level 2'!C:C,'AREA Level 2'!B:B) -> CAM_LV2_9 | C11: Nyong-et-Mfoumou | D11: Nyong-et-Mfoumou | E11: =+_xlfn.XLOOKUP(D11,Sheet4!D:D,Sheet4!A:A) -> CAM2 | F11: =_xlfn.CONCAT(liststart,B11,listlareport,C11,listlat,D11,areavislv2,E11,areavisend) -> { "v": "CAM_LV2_9", "n" : { "SYS": "Nyong-et-Mfoumou", "EN": "Nyong-et-Mfoumou" }, "vi" : [ { "r": "A-10", "o": "=", "t": "v", "v": "CAM2" } ] },
B12: =+_xlfn.XLOOKUP(C12,'AREA Level 2'!C:C,'AREA Level 2'!B:B) -> CAM_LV2_10 | C12: Mbam-et-Inoubou | D12: Mbam-et-Inoubou | E12: =+_xlfn.XLOOKUP(D12,Sheet4!D:D,Sheet4!A:A) -> CAM2 | F12: =_xlfn.CONCAT(liststart,B12,listlareport,C12,listlat,D12,areavislv2,E12,areavisend) -> { "v": "CAM_LV2_10", "n" : { "SYS": "Mbam-et-Inoubou", "EN": "Mbam-et-Inoubou" }, "vi" : [ { "r": "A-10", "o": "=", "t": "v", "v": "CAM2" } ] },
B13: =+_xlfn.XLOOKUP(C13,'AREA Level 2'!C:C,'AREA Level 2'!B:B) -> CAM_LV2_11 | C13: Lekié | D13: Lekié | E13: =+_xlfn.XLOOKUP(D13,Sheet4!D:D,Sheet4!A:A) -> CAM2 | F13: =_xlfn.CONCAT(liststart,B13,listlareport,C13,listlat,D13,areavislv2,E13,areavisend) -> { "v": "CAM_LV2_11", "n" : { "SYS": "Lekié", "EN": "Lekié" }, "vi" : [ { "r": "A-10", "o": "=", "t": "v", "v": "CAM2" } ] },
B14: =+_xlfn.XLOOKUP(C14,'AREA Level 2'!C:C,'AREA Level 2'!B:B) -> CAM_LV2_12 | C14: Haute-Sanaga | D14: Haute-Sanaga | E14: =+_xlfn.XLOOKUP(D14,Sheet4!D:D,Sheet4!A:A) -> CAM2 | F14: =_xlfn.CONCAT(liststart,B14,listlareport,C14,listlat,D14,areavislv2,E14,areavisend) -> { "v": "CAM_LV2_12", "n" : { "SYS": "Haute-Sanaga", "EN": "Haute-Sanaga" }, "vi" : [ { "r": "A-10", "o": "=", "t": "v", "v": "CAM2" } ] },
... B60: =+_xlfn.XLOOKUP(C60,'AREA Level 2'!C:C,'AREA Level 2'!B:B) -> CAM_LV2_58 | C60: Meme | D60: Meme | E60: =+_xlfn.XLOOKUP(D60,Sheet4!D:D,Sheet4!A:A) -> CAM10 | F60: =_xlfn.CONCAT(liststart,B60,listlareport,C60,listlat,D60,areavislv2,E60,areavisend) -> { "v": "CAM_LV2_58", "n" : { "SYS": "Meme", "EN": "Meme" }, "vi" : [ { "r": "A-10", "o": "=", "t": "v", "v": "CAM10" } ] },

Sheet Volume & Price List
A2: V-50 | B2: Product Categories | C2: Arabic Wording for Product Categories | D2: On an average week how much do you sell of the following Categories | E2: Unit | F2: Arabic Wording for Units | G2: Validation | H2: Conversion Average Litre per case or bottle | I2: Category
A3: 1 | B3: Tobacco (in packs/carton) | E3: Packs/Cartons | G3: Max = 10,000
A4: 2 | B4: Shisa (in Kg) | E4: Kg
A5: 3 | B5: Evapes
A6: 4 | B6: electronic cigarettes
A9: V-60 | B9: Tobacco | D9: Unit | E9: Unit | G9: Company | H9: Category | I9: Conversion Pack | J9: Conversion Bundle | K9: Conversion Carton
A10: V60SKU1 | B10: Aspen | C10: JTI | G10: JTI | I10: 10 | J10: 1
A11: V60SKU2 | B11: Winston | C11: JTI | G11: JTI | I11: 10 | J11: 1
A12: V60SKU3 | B12: Marlboro | C12: PMI | G12: PMI | I12: 10 | J12: 1
A13: V60SKU4 | B13: B&H | C13: BAT | G13: BAT | I13: 10 | J13: 1
A14: V60SKU5 | B14: L&B | C14: BAT | G14: BAT | I14: 10 | J14: 1
A15: V60SKU6 | B15: Rothmans | C15: BAT | G15: BAT | I15: 10 | J15: 1
A16: V60SKU7 | B16: Diplomat | C16: BAT | G16: BAT | I16: 10 | J16: 1
A17: V60SKU8 | B17: Gold Seal | C17: Oriental | G17: Oriental | I17: 10 | J17: 1
A18: V60SKU9 | B18: Gold Pin | C18: Oriental | G18: Oriental | I18: 10
A19: V60SKU10 | B19: Oris | C19: Oriental | G19: Oriental | I19: 10 | J19: 1
A20: V60SKU11 | B20: D&J | C20: Oriental | G20: Oriental | I20: 10 | J20: 1
A21: V60SKU12 | B21: Esse | C21: KT&G | G21: KT&G | I21: 10 | J21: 1
A22: V60SKU13 | B22: Time | C22: KT&G | G22: KT&G | I22: 10 | J22: 1
A23: V60SKU14 | B23: Vega | C23: Others | G23: Others | I23: 10 | J23: 1
I24: 10 | J24: 1
A34: 27
A35: 28
A36: 29
A37: 30
A38: 31
A39: 32
A40: 33
A41: 34
A42: 35
A43: 36
A44: 37
A45: 38
... A55: 48
A57: V-70 | B57: Shisa | D57: Unit | E57: Unit | G57: Company | H57: Category | I57: Conversion Pack | J57: Conversion Bundle | K57: Conversion Carton
A58: 1
A59: 2
A60: 3
A61: 4
A62: 5
A63: 6
A64: 7
A65: 8
A66: 9
A67: 10
A68: 11
A69: 12
... A105: 48

Sheet Level1 Builder 
B2: ID | C2: Name -Reporting | D2: Name - App
B3: CAM1 | C3: Adamaoua | D3: Adamaoua | E3: =_xlfn.CONCAT(liststart,B3,listlareport,C3,listlat,D3,listend) -> { "v": "CAM1", "n" : { "SYS": "Adamaoua", "EN": "Adamaoua"} },
B4: CAM2 | C4: Centre | D4: Centre | E4: =_xlfn.CONCAT(liststart,B4,listlareport,C4,listlat,D4,listend) -> { "v": "CAM2", "n" : { "SYS": "Centre", "EN": "Centre"} },
B5: CAM3 | C5: Est | D5: Est | E5: =_xlfn.CONCAT(liststart,B5,listlareport,C5,listlat,D5,listend) -> { "v": "CAM3", "n" : { "SYS": "Est", "EN": "Est"} },
B6: CAM4 | C6: Extrême-Nord | D6: Extrême-Nord | E6: =_xlfn.CONCAT(liststart,B6,listlareport,C6,listlat,D6,listend) -> { "v": "CAM4", "n" : { "SYS": "Extrême-Nord", "EN": "Extrême-Nord"} },
B7: CAM5 | C7: Littoral | D7: Littoral | E7: =_xlfn.CONCAT(liststart,B7,listlareport,C7,listlat,D7,listend) -> { "v": "CAM5", "n" : { "SYS": "Littoral", "EN": "Littoral"} },
B8: CAM6 | C8: Nord | D8: Nord | E8: =_xlfn.CONCAT(liststart,B8,listlareport,C8,listlat,D8,listend) -> { "v": "CAM6", "n" : { "SYS": "Nord", "EN": "Nord"} },
B9: CAM7 | C9: Nord-Ouest | D9: Nord-Ouest | E9: =_xlfn.CONCAT(liststart,B9,listlareport,C9,listlat,D9,listend) -> { "v": "CAM7", "n" : { "SYS": "Nord-Ouest", "EN": "Nord-Ouest"} },
B10: CAM8 | C10: Ouest | D10: Ouest | E10: =_xlfn.CONCAT(liststart,B10,listlareport,C10,listlat,D10,listend) -> { "v": "CAM8", "n" : { "SYS": "Ouest", "EN": "Ouest"} },
B11: CAM9 | C11: Sud | D11: Sud | E11: =_xlfn.CONCAT(liststart,B11,listlareport,C11,listlat,D11,listend) -> { "v": "CAM9", "n" : { "SYS": "Sud", "EN": "Sud"} },
B12: CAM10 | C12: Sud-Ouest | D12: Sud-Ouest | E12: =_xlfn.CONCAT(liststart,B12,listlareport,C12,listlat,D12,listend) -> { "v": "CAM10", "n" : { "SYS": "Sud-Ouest", "EN": "Sud-Ouest"} },

Sheet Level3 Builder
B2: ID | C2: Name -Reporting | D2: Name - App | E2: Level 2 ID
B3: CAM_LV3_1 | C3: Bankim | D3: Bankim | E3: CAM_LV2_1 | F3: =_xlfn.CONCAT(liststart,B3,listlareport,C3,listlat,D3,area_vis_lv21,E3,areavisend) -> { "v": "CAM_LV3_1", "n" : { "SYS": "Bankim", "EN": "Bankim" }, "vi" : [ { "r": "A-20", "o": "=", "t": "v", "v": "CAM_LV2_1" } ] },
B4: CAM_LV3_2 | C4: Banyo | D4: Banyo | E4: CAM_LV2_1 | F4: =_xlfn.CONCAT(liststart,B4,listlareport,C4,listlat,D4,area_vis_lv21,E4,areavisend) -> { "v": "CAM_LV3_2", "n" : { "SYS": "Banyo", "EN": "Banyo" }, "vi" : [ { "r": "A-20", "o": "=", "t": "v", "v": "CAM_LV2_1" } ] },
B5: CAM_LV3_3 | C5: Belel | D5: Belel | E5: CAM_LV2_2 | F5: =_xlfn.CONCAT(liststart,B5,listlareport,C5,listlat,D5,area_vis_lv21,E5,areavisend) -> { "v": "CAM_LV3_3", "n" : { "SYS": "Belel", "EN": "Belel" }, "vi" : [ { "r": "A-20", "o": "=", "t": "v", "v": "CAM_LV2_2" } ] },
B6: CAM_LV3_4 | C6: Dir | D6: Dir | E6: CAM_LV2_3 | F6: =_xlfn.CONCAT(liststart,B6,listlareport,C6,listlat,D6,area_vis_lv21,E6,areavisend) -> { "v": "CAM_LV3_4", "n" : { "SYS": "Dir", "EN": "Dir" }, "vi" : [ { "r": "A-20", "o": "=", "t": "v", "v": "CAM_LV2_3" } ] },
B7: CAM_LV3_5 | C7: Djohong | D7: Djohong | E7: CAM_LV2_3 | F7: =_xlfn.CONCAT(liststart,B7,listlareport,C7,listlat,D7,area_vis_lv21,E7,areavisend) -> { "v": "CAM_LV3_5", "n" : { "SYS": "Djohong", "EN": "Djohong" }, "vi" : [ { "r": "A-20", "o": "=", "t": "v", "v": "CAM_LV2_3" } ] },
B8: CAM_LV3_6 | C8: Galim-Tignere | D8: Galim-Tignere | E8: CAM_LV2_4 | F8: =_xlfn.CONCAT(liststart,B8,listlareport,C8,listlat,D8,area_vis_lv21,E8,areavisend) -> { "v": "CAM_LV3_6", "n" : { "SYS": "Galim-Tignere", "EN": "Galim-Tignere" }, "vi" : [ { "r": "A-20", "o": "=", "t": "v", "v": "CAM_LV2_4" } ] },
B9: CAM_LV3_7 | C9: Kontcha | D9: Kontcha | E9: CAM_LV2_4 | F9: =_xlfn.CONCAT(liststart,B9,listlareport,C9,listlat,D9,area_vis_lv21,E9,areavisend) -> { "v": "CAM_LV3_7", "n" : { "SYS": "Kontcha", "EN": "Kontcha" }, "vi" : [ { "r": "A-20", "o": "=", "t": "v", "v": "CAM_LV2_4" } ] },
B10: CAM_LV3_8 | C10: Martap | D10: Martap | E10: CAM_LV2_2 | F10: =_xlfn.CONCAT(liststart,B10,listlareport,C10,listlat,D10,area_vis_lv21,E10,areavisend) -> { "v": "CAM_LV3_8", "n" : { "SYS": "Martap", "EN": "Martap" }, "vi" : [ { "r": "A-20", "o": "=", "t": "v", "v": "CAM_LV2_2" } ] },
B11: CAM_LV3_9 | C11: Mayo-Baleo | D11: Mayo-Baleo | E11: CAM_LV2_4 | F11: =_xlfn.CONCAT(liststart,B11,listlareport,C11,listlat,D11,area_vis_lv21,E11,areavisend) -> { "v": "CAM_LV3_9", "n" : { "SYS": "Mayo-Baleo", "EN": "Mayo-Baleo" }, "vi" : [ { "r": "A-20", "o": "=", "t": "v", "v": "CAM_LV2_4" } ] },
B12: CAM_LV3_10 | C12: Mayo-Darle | D12: Mayo-Darle | E12: CAM_LV2_1 | F12: =_xlfn.CONCAT(liststart,B12,listlareport,C12,listlat,D12,area_vis_lv21,E12,areavisend) -> { "v": "CAM_LV3_10", "n" : { "SYS": "Mayo-Darle", "EN": "Mayo-Darle" }, "vi" : [ { "r": "A-20", "o": "=", "t": "v", "v": "CAM_LV2_1" } ] },
B13: CAM_LV3_11 | C13: Mbe | D13: Mbe | E13: CAM_LV2_2 | F13: =_xlfn.CONCAT(liststart,B13,listlareport,C13,listlat,D13,area_vis_lv21,E13,areavisend) -> { "v": "CAM_LV3_11", "n" : { "SYS": "Mbe", "EN": "Mbe" }, "vi" : [ { "r": "A-20", "o": "=", "t": "v", "v": "CAM_LV2_2" } ] },
B14: CAM_LV3_12 | C14: Meiganga | D14: Meiganga | E14: CAM_LV2_3 | F14: =_xlfn.CONCAT(liststart,B14,listlareport,C14,listlat,D14,area_vis_lv21,E14,areavisend) -> { "v": "CAM_LV3_12", "n" : { "SYS": "Meiganga", "EN": "Meiganga" }, "vi" : [ { "r": "A-20", "o": "=", "t": "v", "v": "CAM_LV2_3" } ] },
... B365: CAM_LV3_363 | C365: West-Coast | D365: West-Coast | E365: CAM_LV2_57 | F365: =_xlfn.CONCAT(liststart,B365,listlareport,C365,listlat,D365,area_vis_lv21,E365,areavisend) -> { "v": "CAM_LV3_363", "n" : { "SYS": "West-Coast", "EN": "West-Coast" }, "vi" : [ { "r": "A-20", "o": "=", "t": "v", "v": "CAM_LV2_57" } ] },

Sheet Level4 Builder
B2: ID | C2: Name -Reporting | D2: Name - App | E2: Level 3 ID
A3: Douala 1er | B3: CAM_LV4_1 | C3: BONAMOUDOUROU | D3: BONAMOUDOUROU | E3: CAM_LV3_179 | F3: =_xlfn.CONCAT(liststart,B3,listlareport,C3,listlat,D3,area_vis_lv3,E3,areavisend) -> { "v": "CAM_LV4_1", "n" : { "SYS": "BONAMOUDOUROU", "EN": "BONAMOUDOUROU" }, "vi" : [ { "r": "A-30", "o": "=", "t": "v", "v": "CAM_LV3_179" } ] },
A4: Douala 1er | B4: CAM_LV4_2 | C4: BONAMOUTI DEIDO | D4: BONAMOUTI DEIDO | E4: CAM_LV3_179 | F4: =_xlfn.CONCAT(liststart,B4,listlareport,C4,listlat,D4,area_vis_lv3,E4,areavisend) -> { "v": "CAM_LV4_2", "n" : { "SYS": "BONAMOUTI DEIDO", "EN": "BONAMOUTI DEIDO" }, "vi" : [ { "r": "A-30", "o": "=", "t": "v", "v": "CAM_LV3_179" } ] },
A5: Douala 1er | B5: CAM_LV4_3 | C5: BONATENE | D5: BONATENE | E5: CAM_LV3_179 | F5: =_xlfn.CONCAT(liststart,B5,listlareport,C5,listlat,D5,area_vis_lv3,E5,areavisend) -> { "v": "CAM_LV4_3", "n" : { "SYS": "BONATENE", "EN": "BONATENE" }, "vi" : [ { "r": "A-30", "o": "=", "t": "v", "v": "CAM_LV3_179" } ] },
A6: Douala 1er | B6: CAM_LV4_4 | C6: BONATEKI | D6: BONATEKI | E6: CAM_LV3_179 | F6: =_xlfn.CONCAT(liststart,B6,listlareport,C6,listlat,D6,area_vis_lv3,E6,areavisend) -> { "v": "CAM_LV4_4", "n" : { "SYS": "BONATEKI", "EN": "BONATEKI" }, "vi" : [ { "r": "A-30", "o": "=", "t": "v", "v": "CAM_LV3_179" } ] },
A7: Douala 1er | B7: CAM_LV4_5 | C7: BONANJO | D7: BONANJO | E7: CAM_LV3_179 | F7: =_xlfn.CONCAT(liststart,B7,listlareport,C7,listlat,D7,area_vis_lv3,E7,areavisend) -> { "v": "CAM_LV4_5", "n" : { "SYS": "BONANJO", "EN": "BONANJO" }, "vi" : [ { "r": "A-30", "o": "=", "t": "v", "v": "CAM_LV3_179" } ] },
A8: Douala 1er | B8: CAM_LV4_6 | C8: BALI | D8: BALI | E8: CAM_LV3_179 | F8: =_xlfn.CONCAT(liststart,B8,listlareport,C8,listlat,D8,area_vis_lv3,E8,areavisend) -> { "v": "CAM_LV4_6", "n" : { "SYS": "BALI", "EN": "BALI" }, "vi" : [ { "r": "A-30", "o": "=", "t": "v", "v": "CAM_LV3_179" } ] },
A9: Douala 1er | B9: CAM_LV4_7 | C9: BONAPRISO | D9: BONAPRISO | E9: CAM_LV3_179 | F9: =_xlfn.CONCAT(liststart,B9,listlareport,C9,listlat,D9,area_vis_lv3,E9,areavisend) -> { "v": "CAM_LV4_7", "n" : { "SYS": "BONAPRISO", "EN": "BONAPRISO" }, "vi" : [ { "r": "A-30", "o": "=", "t": "v", "v": "CAM_LV3_179" } ] },
A10: Douala 1er | B10: CAM_LV4_8 | C10: NKONGMONDO | D10: NKONGMONDO | E10: CAM_LV3_179 | F10: =_xlfn.CONCAT(liststart,B10,listlareport,C10,listlat,D10,area_vis_lv3,E10,areavisend) -> { "v": "CAM_LV4_8", "n" : { "SYS": "NKONGMONDO", "EN": "NKONGMONDO" }, "vi" : [ { "r": "A-30", "o": "=", "t": "v", "v": "CAM_LV3_179" } ] },
A11: Douala 1er | B11: CAM_LV4_9 | C11: BESSENGUE | D11: BESSENGUE | E11: CAM_LV3_179 | F11: =_xlfn.CONCAT(liststart,B11,listlareport,C11,listlat,D11,area_vis_lv3,E11,areavisend) -> { "v": "CAM_LV4_9", "n" : { "SYS": "BESSENGUE", "EN": "BESSENGUE" }, "vi" : [ { "r": "A-30", "o": "=", "t": "v", "v": "CAM_LV3_179" } ] },
A12: Douala 1er | B12: CAM_LV4_10 | C12: NEW DEIDO | D12: NEW DEIDO | E12: CAM_LV3_179 | F12: =_xlfn.CONCAT(liststart,B12,listlareport,C12,listlat,D12,area_vis_lv3,E12,areavisend) -> { "v": "CAM_LV4_10", "n" : { "SYS": "NEW DEIDO", "EN": "NEW DEIDO" }, "vi" : [ { "r": "A-30", "o": "=", "t": "v", "v": "CAM_LV3_179" } ] },
A13: Douala 1er | B13: CAM_LV4_11 | C13: GRAND MOULIN | D13: GRAND MOULIN | E13: CAM_LV3_179 | F13: =_xlfn.CONCAT(liststart,B13,listlareport,C13,listlat,D13,area_vis_lv3,E13,areavisend) -> { "v": "CAM_LV4_11", "n" : { "SYS": "GRAND MOULIN", "EN": "GRAND MOULIN" }, "vi" : [ { "r": "A-30", "o": "=", "t": "v", "v": "CAM_LV3_179" } ] },
A14: Douala 1er | B14: CAM_LV4_12 | C14: NKONDO | D14: NKONDO | E14: CAM_LV3_179 | F14: =_xlfn.CONCAT(liststart,B14,listlareport,C14,listlat,D14,area_vis_lv3,E14,areavisend) -> { "v": "CAM_LV4_12", "n" : { "SYS": "NKONDO", "EN": "NKONDO" }, "vi" : [ { "r": "A-30", "o": "=", "t": "v", "v": "CAM_LV3_179" } ] },
... A262: Yaounde 7e | B262: CAM_LV4_260 | C262: NKOLAFEME | D262: NKOLAFEME | E262: CAM_LV3_90 | F262: =_xlfn.CONCAT(liststart,B262,listlareport,C262,listlat,D262,area_vis_lv3,E262,areavisend) -> { "v": "CAM_LV4_260", "n" : { "SYS": "NKOLAFEME", "EN": "NKOLAFEME" }, "vi" : [ { "r": "A-30", "o": "=", "t": "v", "v": "CAM_LV3_90" } ] },
B263: CAM_LV4_261 | C263: Other | D263: Autre | F263: =_xlfn.CONCAT(liststart,B263,listlareport,C263,listlat,D263,EndLV4) -> { "v": "CAM_LV4_261", "n" : { "SYS": "Other", "EN": "Autre" }
A264: Bafoussam 1er | B264: CAM_LV4_262 | C264: BENENGO,B | D264: BENENGO,B | E264: CAM_LV3_266 | F264: =_xlfn.CONCAT(liststart,B264,listlareport,C264,listlat,D264,area_vis_lv3,E264,areavisend) -> { "v": "CAM_LV4_262", "n" : { "SYS": "BENENGO,B", "EN": "BENENGO,B" }, "vi" : [ { "r": "A-30", "o": "=", "t": "v", "v": "CAM_LV3_266" } ] },
A265: Bafoussam 1er | B265: CAM_LV4_263 | C265: BADIENGSO | D265: BADIENGSO | E265: CAM_LV3_266 | F265: =_xlfn.CONCAT(liststart,B265,listlareport,C265,listlat,D265,area_vis_lv3,E265,areavisend) -> { "v": "CAM_LV4_263", "n" : { "SYS": "BADIENGSO", "EN": "BADIENGSO" }, "vi" : [ { "r": "A-30", "o": "=", "t": "v", "v": "CAM_LV3_266" } ] },
A266: Bafoussam 1er | B266: CAM_LV4_264 | C266: ZONE,INDUSTRIELLE | D266: ZONE,INDUSTRIELLE | E266: CAM_LV3_266 | F266: =_xlfn.CONCAT(liststart,B266,listlareport,C266,listlat,D266,area_vis_lv3,E266,areavisend) -> { "v": "CAM_LV4_264", "n" : { "SYS": "ZONE,INDUSTRIELLE", "EN": "ZONE,INDUSTRIELLE" }, "vi" : [ { "r": "A-30", "o": "=", "t": "v", "v": "CAM_LV3_266" } ] },
A267: Bafoussam 1er | B267: CAM_LV4_265 | C267: FAMLA | D267: FAMLA | E267: CAM_LV3_266 | F267: =_xlfn.CONCAT(liststart,B267,listlareport,C267,listlat,D267,area_vis_lv3,E267,areavisend) -> { "v": "CAM_LV4_265", "n" : { "SYS": "FAMLA", "EN": "FAMLA" }, "vi" : [ { "r": "A-30", "o": "=", "t": "v", "v": "CAM_LV3_266" } ] },
A268: Bafoussam 1er | B268: CAM_LV4_266 | C268: DJELENG 5 | D268: DJELENG 5 | E268: CAM_LV3_266 | F268: =_xlfn.CONCAT(liststart,B268,listlareport,C268,listlat,D268,area_vis_lv3,E268,areavisend) -> { "v": "CAM_LV4_266", "n" : { "SYS": "DJELENG 5", "EN": "DJELENG 5" }, "vi" : [ { "r": "A-30", "o": "=", "t": "v", "v": "CAM_LV3_266" } ] },
A269: Bafoussam 1er | B269: CAM_LV4_267 | C269: DJEMOUN | D269: DJEMOUN | E269: CAM_LV3_266 | F269: =_xlfn.CONCAT(liststart,B269,listlareport,C269,listlat,D269,area_vis_lv3,E269,areavisend) -> { "v": "CAM_LV4_267", "n" : { "SYS": "DJEMOUN", "EN": "DJEMOUN" }, "vi" : [ { "r": "A-30", "o": "=", "t": "v", "v": "CAM_LV3_266" } ] },
A270: Bafoussam 1er | B270: CAM_LV4_268 | C270: QUARTIER,ADMINISTRATIF | D270: QUARTIER,ADMINISTRATIF | E270: CAM_LV3_266 | F270: =_xlfn.CONCAT(liststart,B270,listlareport,C270,listlat,D270,area_vis_lv3,E270,areavisend) -> { "v": "CAM_LV4_268", "n" : { "SYS": "QUARTIER,ADMINISTRATIF", "EN": "QUARTIER,ADMINISTRATIF" }, "vi" : [ { "r": "A-30", "o": "=", "t": "v", "v": "CAM_LV3_266" } ] },
A271: Bafoussam 1er | B271: CAM_LV4_269 | C271: BAMENZI | D271: BAMENZI | E271: CAM_LV3_266 | F271: =_xlfn.CONCAT(liststart,B271,listlareport,C271,listlat,D271,area_vis_lv3,E271,areavisend) -> { "v": "CAM_LV4_269", "n" : { "SYS": "BAMENZI", "EN": "BAMENZI" }, "vi" : [ { "r": "A-30", "o": "=", "t": "v", "v": "CAM_LV3_266" } ] },
A272: Bafoussam 1er | B272: CAM_LV4_270 | C272: KING,PLACE | D272: KING,PLACE | E272: CAM_LV3_266 | F272: =_xlfn.CONCAT(liststart,B272,listlareport,C272,listlat,D272,area_vis_lv3,E272,areavisend) -> { "v": "CAM_LV4_270", "n" : { "SYS": "KING,PLACE", "EN": "KING,PLACE" }, "vi" : [ { "r": "A-30", "o": "=", "t": "v", "v": "CAM_LV3_266" } ] },
A273: Bafoussam 1er | B273: CAM_LV4_271 | C273: CHEFFERIE | D273: CHEFFERIE | E273: CAM_LV3_266 | F273: =_xlfn.CONCAT(liststart,B273,listlareport,C273,listlat,D273,area_vis_lv3,E273,areavisend) -> { "v": "CAM_LV4_271", "n" : { "SYS": "CHEFFERIE", "EN": "CHEFFERIE" }, "vi" : [ { "r": "A-30", "o": "=", "t": "v", "v": "CAM_LV3_266" } ] },
A274: Bafoussam 1er | B274: CAM_LV4_272 | C274: BENENGO,A | D274: BENENGO,A | E274: CAM_LV3_266 | F274: =_xlfn.CONCAT(liststart,B274,listlareport,C274,listlat,D274,area_vis_lv3,E274,areavisend) -> { "v": "CAM_LV4_272", "n" : { "SYS": "BENENGO,A", "EN": "BENENGO,A" }, "vi" : [ { "r": "A-30", "o": "=", "t": "v", "v": "CAM_LV3_266" } ] },
A275: Bafoussam 1er | B275: CAM_LV4_273 | C275: TAMJA | D275: TAMJA | E275: CAM_LV3_266 | F275: =_xlfn.CONCAT(liststart,B275,listlareport,C275,listlat,D275,area_vis_lv3,E275,areavisend) -> { "v": "CAM_LV4_273", "n" : { "SYS": "TAMJA", "EN": "TAMJA" }, "vi" : [ { "r": "A-30", "o": "=", "t": "v", "v": "CAM_LV3_266" } ] },
... A297: Bafoussam 3e | B297: CAM_LV4_295 | C297: NDZE | D297: NDZE | E297: CAM_LV3_268 | F297: =_xlfn.CONCAT(liststart,B297,listlareport,C297,listlat,D297,area_vis_lv3,E297,areavisend) -> { "v": "CAM_LV4_295", "n" : { "SYS": "NDZE", "EN": "NDZE" }, "vi" : [ { "r": "A-30", "o": "=", "t": "v", "v": "CAM_LV3_268" } ] },

Sheet AREA Level 4
A2: SEQ ID | B2: ID | C2: Name -Reporting | D2: Name - App | E2: Level 2 ID | H2: commune | I2: quartier
A3: 1 | B3: =_xlfn.CONCAT("CAM_LV3_",A3) -> CAM_LV3_1 | C3: BONAMOUDOUROU | D3: Bankim | E3: =+_xlfn.XLOOKUP(C3,Sheet4!F:F,Sheet4!G:G) -> #N/A | H3: DOUALA 1 | I3: BONAMOUDOUROU
A4: 2 | B4: =_xlfn.CONCAT("CAM_LV3_",A4) -> CAM_LV3_2 | C4: BONAMOUTI DEIDO | D4: Banyo | E4: =+_xlfn.XLOOKUP(C4,Sheet4!F:F,Sheet4!G:G) -> #N/A | H4: DOUALA 1 | I4: BONAMOUTI DEIDO
A5: 3 | B5: =_xlfn.CONCAT("CAM_LV3_",A5) -> CAM_LV3_3 | C5: BONATENE | D5: Belel | E5: =+_xlfn.XLOOKUP(C5,Sheet4!F:F,Sheet4!G:G) -> #N/A | H5: DOUALA 1 | I5: BONATENE
A6: 4 | B6: =_xlfn.CONCAT("CAM_LV3_",A6) -> CAM_LV3_4 | C6: BONATEKI | D6: Dir | E6: =+_xlfn.XLOOKUP(C6,Sheet4!F:F,Sheet4!G:G) -> #N/A | H6: DOUALA 1 | I6: BONATEKI
A7: 5 | B7: =_xlfn.CONCAT("CAM_LV3_",A7) -> CAM_LV3_5 | C7: BONANJO | D7: Djohong | E7: =+_xlfn.XLOOKUP(C7,Sheet4!F:F,Sheet4!G:G) -> #N/A | H7: DOUALA 1 | I7: BONANJO
A8: 6 | B8: =_xlfn.CONCAT("CAM_LV3_",A8) -> CAM_LV3_6 | C8: BALI | D8: Galim-Tignere | E8: =+_xlfn.XLOOKUP(C8,Sheet4!F:F,Sheet4!G:G) -> CAM_LV2_37 | H8: DOUALA 1 | I8: BALI
A9: 7 | B9: =_xlfn.CONCAT("CAM_LV3_",A9) -> CAM_LV3_7 | C9: BONAPRISO | D9: Kontcha | E9: =+_xlfn.XLOOKUP(C9,Sheet4!F:F,Sheet4!G:G) -> #N/A | H9: DOUALA 1 | I9: BONAPRISO
A10: 8 | B10: =_xlfn.CONCAT("CAM_LV3_",A10) -> CAM_LV3_8 | C10: NKONGMONDO | D10: Martap | E10: =+_xlfn.XLOOKUP(C10,Sheet4!F:F,Sheet4!G:G) -> #N/A | H10: DOUALA 1 | I10: NKONGMONDO
A11: 9 | B11: =_xlfn.CONCAT("CAM_LV3_",A11) -> CAM_LV3_9 | C11: BESSENGUE | D11: Mayo-Baleo | E11: =+_xlfn.XLOOKUP(C11,Sheet4!F:F,Sheet4!G:G) -> #N/A | H11: DOUALA 1 | I11: BESSENGUE
A12: 10 | B12: =_xlfn.CONCAT("CAM_LV3_",A12) -> CAM_LV3_10 | C12: NEW DEIDO | D12: Mayo-Darle | E12: =+_xlfn.XLOOKUP(C12,Sheet4!F:F,Sheet4!G:G) -> #N/A | H12: DOUALA 1 | I12: NEW DEIDO
A13: 11 | B13: =_xlfn.CONCAT("CAM_LV3_",A13) -> CAM_LV3_11 | C13: GRAND MOULIN | D13: Mbe | E13: =+_xlfn.XLOOKUP(C13,Sheet4!F:F,Sheet4!G:G) -> #N/A | H13: DOUALA 1 | I13: GRAND MOULIN
A14: 12 | B14: =_xlfn.CONCAT("CAM_LV3_",A14) -> CAM_LV3_12 | C14: NKONDO | D14: Meiganga | E14: =+_xlfn.XLOOKUP(C14,Sheet4!F:F,Sheet4!G:G) -> #N/A | H14: DOUALA 1 | I14: NKONDO
... A154: 152 | B154: =_xlfn.CONCAT("CAM_LV3_",A154) -> CAM_LV3_152 | C154: BEPANDA GENTIL | D154: Koza | E154: =+_xlfn.XLOOKUP(C154,Sheet4!F:F,Sheet4!G:G) -> #N/A | H154: DOUALA 5 | I154: BEPANDA GENTIL
A155: 153 | B155: =_xlfn.CONCAT("CAM_LV3_",A155) -> CAM_LV3_153 | D155: Logone-Birni | E155: =+_xlfn.XLOOKUP(C155,Sheet4!F:F,Sheet4!G:G) -> 0
A156: 154 | B156: =_xlfn.CONCAT("CAM_LV3_",A156) -> CAM_LV3_154 | D156: Maga | E156: =+_xlfn.XLOOKUP(C156,Sheet4!F:F,Sheet4!G:G) -> 0
A157: 155 | B157: =_xlfn.CONCAT("CAM_LV3_",A157) -> CAM_LV3_155 | D157: Makary | E157: =+_xlfn.XLOOKUP(C157,Sheet4!F:F,Sheet4!G:G) -> 0
A158: 156 | B158: =_xlfn.CONCAT("CAM_LV3_",A158) -> CAM_LV3_156 | D158: Maroua 1er | E158: =+_xlfn.XLOOKUP(C158,Sheet4!F:F,Sheet4!G:G) -> 0
A159: 157 | B159: =_xlfn.CONCAT("CAM_LV3_",A159) -> CAM_LV3_157 | D159: Maroua 2e | E159: =+_xlfn.XLOOKUP(C159,Sheet4!F:F,Sheet4!G:G) -> 0
A160: 158 | B160: =_xlfn.CONCAT("CAM_LV3_",A160) -> CAM_LV3_158 | D160: Maroua 3e | E160: =+_xlfn.XLOOKUP(C160,Sheet4!F:F,Sheet4!G:G) -> 0
A161: 159 | B161: =_xlfn.CONCAT("CAM_LV3_",A161) -> CAM_LV3_159 | D161: Mozogo | E161: =+_xlfn.XLOOKUP(C161,Sheet4!F:F,Sheet4!G:G) -> 0
A162: 160 | B162: =_xlfn.CONCAT("CAM_LV3_",A162) -> CAM_LV3_160 | C162: Meri | D162: Meri | E162: =+_xlfn.XLOOKUP(C162,Sheet4!F:F,Sheet4!G:G) -> CAM_LV2_22
A163: 161 | B163: =_xlfn.CONCAT("CAM_LV3_",A163) -> CAM_LV3_161 | C163: Mogode | D163: Mogode | E163: =+_xlfn.XLOOKUP(C163,Sheet4!F:F,Sheet4!G:G) -> CAM_LV2_23
A164: 162 | B164: =_xlfn.CONCAT("CAM_LV3_",A164) -> CAM_LV3_162 | C164: Mokolo | D164: Mokolo | E164: =+_xlfn.XLOOKUP(C164,Sheet4!F:F,Sheet4!G:G) -> CAM_LV2_23
A165: 163 | B165: =_xlfn.CONCAT("CAM_LV3_",A165) -> CAM_LV3_163 | C165: Mora | D165: Mora | E165: =+_xlfn.XLOOKUP(C165,Sheet4!F:F,Sheet4!G:G) -> CAM_LV2_25
A166: 164 | B166: =_xlfn.CONCAT("CAM_LV3_",A166) -> CAM_LV3_164 | C166: Moulvoudaye | D166: Moulvoudaye | E166: =+_xlfn.XLOOKUP(C166,Sheet4!F:F,Sheet4!G:G) -> CAM_LV2_20
A167: 165 | B167: =_xlfn.CONCAT("CAM_LV3_",A167) -> CAM_LV3_165 | C167: Ndoukoula | D167: Ndoukoula | E167: =+_xlfn.XLOOKUP(C167,Sheet4!F:F,Sheet4!G:G) -> CAM_LV2_22
A168: 166 | B168: =_xlfn.CONCAT("CAM_LV3_",A168) -> CAM_LV3_166 | C168: Pette | D168: Pette | E168: =+_xlfn.XLOOKUP(C168,Sheet4!F:F,Sheet4!G:G) -> CAM_LV2_22
A169: 167 | B169: =_xlfn.CONCAT("CAM_LV3_",A169) -> CAM_LV3_167 | C169: Soulede-Roua | D169: Soulede-Roua | E169: =+_xlfn.XLOOKUP(C169,Sheet4!F:F,Sheet4!G:G) -> CAM_LV2_23
A170: 168 | B170: =_xlfn.CONCAT("CAM_LV3_",A170) -> CAM_LV3_168 | C170: Tchatibali | D170: Tchatibali | E170: =+_xlfn.XLOOKUP(C170,Sheet4!F:F,Sheet4!G:G) -> CAM_LV2_24
A171: 169 | B171: =_xlfn.CONCAT("CAM_LV3_",A171) -> CAM_LV3_169 | C171: Tokombere | D171: Tokombere | E171: =+_xlfn.XLOOKUP(C171,Sheet4!F:F,Sheet4!G:G) -> CAM_LV2_25
A172: 170 | B172: =_xlfn.CONCAT("CAM_LV3_",A172) -> CAM_LV3_170 | C172: Waza | D172: Waza | E172: =+_xlfn.XLOOKUP(C172,Sheet4!F:F,Sheet4!G:G) -> CAM_LV2_21
A173: 171 | B173: =_xlfn.CONCAT("CAM_LV3_",A173) -> CAM_LV3_171 | C173: Wina | D173: Wina | E173: =+_xlfn.XLOOKUP(C173,Sheet4!F:F,Sheet4!G:G) -> CAM_LV2_24
... A365: 363 | B365: =_xlfn.CONCAT("CAM_LV3_",A365) -> CAM_LV3_363 | C365: West-Coast | D365: West-Coast | E365: =+_xlfn.XLOOKUP(C365,Sheet4!F:F,Sheet4!G:G) -> CAM_LV2_57

Sheet AREA Level 3 
A2: SEQ ID | B2: ID | C2: Name -Reporting | D2: Name - App | E2: Level 2 ID
A3: 1 | B3: =_xlfn.CONCAT("CAM_LV3_",A3) -> CAM_LV3_1 | C3: Bankim | D3: Bankim | E3: =+_xlfn.XLOOKUP(C3,Sheet4!F:F,Sheet4!G:G) -> CAM_LV2_1
A4: 2 | B4: =_xlfn.CONCAT("CAM_LV3_",A4) -> CAM_LV3_2 | C4: Banyo | D4: Banyo | E4: =+_xlfn.XLOOKUP(C4,Sheet4!F:F,Sheet4!G:G) -> CAM_LV2_1
A5: 3 | B5: =_xlfn.CONCAT("CAM_LV3_",A5) -> CAM_LV3_3 | C5: Belel | D5: Belel | E5: =+_xlfn.XLOOKUP(C5,Sheet4!F:F,Sheet4!G:G) -> CAM_LV2_2
A6: 4 | B6: =_xlfn.CONCAT("CAM_LV3_",A6) -> CAM_LV3_4 | C6: Dir | D6: Dir | E6: =+_xlfn.XLOOKUP(C6,Sheet4!F:F,Sheet4!G:G) -> CAM_LV2_3
A7: 5 | B7: =_xlfn.CONCAT("CAM_LV3_",A7) -> CAM_LV3_5 | C7: Djohong | D7: Djohong | E7: =+_xlfn.XLOOKUP(C7,Sheet4!F:F,Sheet4!G:G) -> CAM_LV2_3
A8: 6 | B8: =_xlfn.CONCAT("CAM_LV3_",A8) -> CAM_LV3_6 | C8: Galim-Tignere | D8: Galim-Tignere | E8: =+_xlfn.XLOOKUP(C8,Sheet4!F:F,Sheet4!G:G) -> CAM_LV2_4
A9: 7 | B9: =_xlfn.CONCAT("CAM_LV3_",A9) -> CAM_LV3_7 | C9: Kontcha | D9: Kontcha | E9: =+_xlfn.XLOOKUP(C9,Sheet4!F:F,Sheet4!G:G) -> CAM_LV2_4
A10: 8 | B10: =_xlfn.CONCAT("CAM_LV3_",A10) -> CAM_LV3_8 | C10: Martap | D10: Martap | E10: =+_xlfn.XLOOKUP(C10,Sheet4!F:F,Sheet4!G:G) -> CAM_LV2_2
A11: 9 | B11: =_xlfn.CONCAT("CAM_LV3_",A11) -> CAM_LV3_9 | C11: Mayo-Baleo | D11: Mayo-Baleo | E11: =+_xlfn.XLOOKUP(C11,Sheet4!F:F,Sheet4!G:G) -> CAM_LV2_4
A12: 10 | B12: =_xlfn.CONCAT("CAM_LV3_",A12) -> CAM_LV3_10 | C12: Mayo-Darle | D12: Mayo-Darle | E12: =+_xlfn.XLOOKUP(C12,Sheet4!F:F,Sheet4!G:G) -> CAM_LV2_1
A13: 11 | B13: =_xlfn.CONCAT("CAM_LV3_",A13) -> CAM_LV3_11 | C13: Mbe | D13: Mbe | E13: =+_xlfn.XLOOKUP(C13,Sheet4!F:F,Sheet4!G:G) -> CAM_LV2_2
A14: 12 | B14: =_xlfn.CONCAT("CAM_LV3_",A14) -> CAM_LV3_12 | C14: Meiganga | D14: Meiganga | E14: =+_xlfn.XLOOKUP(C14,Sheet4!F:F,Sheet4!G:G) -> CAM_LV2_3
... A365: 363 | B365: =_xlfn.CONCAT("CAM_LV3_",A365) -> CAM_LV3_363 | C365: West-Coast | D365: West-Coast | E365: =+_xlfn.XLOOKUP(C365,Sheet4!F:F,Sheet4!G:G) -> CAM_LV2_57

Sheet Anomalies
A2: ANOMALY ID | B2: Anomaly Weight | C2: Type | D2: QUESTION ID | E2: CONSTRAINT | F2: VALUE | G2: COMPARED QUESTION | H2: Rule in words | I2: NOTES | J2: Anthony | K2: Philippe | L2: Develop team
A3: ANO-A1..A6 | B3: 1 | C3: AND | D3: I-130 | E3: = | F3: ON TRADE | H3: For On-Trade questionnaire Volume of beer sold per day cannot be more than 150 cases
C4: (OR | D4: V-50-'1' | E4: < | F4: 0 | I4: copy this 6 times
C5: OR) | D5: V-50-'1' | E5: > | F5: 150
A7: ANO-B1..B6 | B7: 1 | C7: AND | D7: I-130 | E7: = | F7: OFF TRADE | H7: For OFF-Trade questionnaire Volume of beer sold per day cannot be more than 300 cases
C8: (OR | D8: V-50-'1' | E8: < | F8: 0 | I8: copy this 6 times
C9: OR) | D9: V-50-'1' | E9: > | F9: 300
A11: ANO-C1..C6 | B11: 1 | C11: AND | D11: I-130 | E11: = | F11: RTM | H11: For RTM questionnaire Volume of beer sold per day cannot be more than 1000 bottles
C12: (OR | D12: V-50-'1' | E12: < | F12: 0 | I12: copy this 6 times
C13: OR) | D13: V-50-'1' | E13: > | F13: 1000
A15: ANO-D | B15: 2 | D15: I-140 | E15: > | F15: 500 | H15: For all surveys volume sold above 500 cases of beers per day should be checked
A17: ANO-E | B17: 1 | C17: AND | D17: I-50 | E17: = | F17: NO | H17: For when end an outlet does not sell alchohol but says yes to selling Beer
C18: AND | D18: I-60 | E18: = | F18: YES
A20: ANO-F | B20: 1 | D20: (E-70) - (P-70) | E20: < | F20: 300 | G20: E-5 | H20: End Time - Start time is less than 5 minutes | I20: (300 is time in seconds)
A22: ANO-G | B22: 1 | D22: SUM V-60--1 | E22: > | G22: I-140 | H22: For when sum of beer sold is higher than the total cases of beer sold | L22: Please explain the wish regarding percentage. Also, selected only sum of cases column.
A24: ANO-H | B24: 1 | D24: M-101 | E24: = | F24: "<10" | G24: "<10". Less than 10 | H24: For when an outlet as a capacity of less than 10 people but sells more than 10 cases of beer per day
C25: AND | D25: I-140 | E25: > | F25: 10
A27: ANO-I | D27: I-130 | E27: = | F27: RTM | L27: Disabled, as discussed on Slack 2017-05-22 #heineken_ameeexport
C28: AND | D28: SUM V-60--2 | E28: > | F28: 0 | L28: Basically states that V-60 may not have bottles input for RTM, but this is not a required restriction anymore.
A31: ANO-J-MAURITIUS | B31: 1 | D31: V-60-'1'-1 | E31: > | F31: 50 | H31: For when one beer SKU sells more than 50 cases per day | L31: Adjusted question specifiers to match the cases column, as mentioned in description.
C32: OR | D32: V-60-'2'-1 | E32: > | F32: 50
C33: OR | D33: V-60-'3'-1 | E33: > | F33: 50
C34: OR | D34: V-60-'4'-1 | E34: > | F34: 50
C35: OR | D35: V-60-'5'-1 | E35: > | F35: 50
C36: OR | D36: V-60-'6'-1 | E36: > | F36: 50
C37: OR | D37: V-60-'7'-1 | E37: > | F37: 50
C38: OR | D38: V-60-'8'-1 | E38: > | F38: 50
C39: OR | D39: V-60-'9'-1 | E39: > | F39: 50

Sheet Back Checking Rules
A1: Rule | C1: Rule In words | D1: CONSTRAINT | E1: ___ | F1: Philippe | G1: Dev Team
A2: Number of enumerators | B2: 20-25 | C2: Estimated of number of enumerator there will be in field (at 1 time)
A3: Number of team leaders (assigned to 1 team max) | B3: 0 | C3: Number of users who will have the role of team leader in the system
A4: Number of Telephone back checkers roles | B4: 0
A5: Number of Comparator roles | B5: 0
A6: Number of Analyst roles | B6: 0
A7: Min. percentage of enum. to backcheck for each enumerator | B7: 0 | C7: Example: If set to 20%, at least 20% of the enumerations of each enumerator will be flagged for priority backchecking
A8: Anomaly threshold to flag for guaranteed backchecking | B8: 0 | C8: Example: If set to 3, an enumeration will be flagged for priority backchecking if it has 3 or more anomalies
A9: Activate Field Back checkers | B9: NO | C9: The survey will the highest anomalies will be allocated to a field backchceker role. Every day in a night batch (at 11pm)
A10: Number of Field back-checkers (assigned to 1 team max) | B10: 0 | C10: How many backcheckers role will their be ?
A11: What is the capacity of outlets per day per field BC | B11: 0 | C11: How many outlets max per day that will be allocated to Field BC
A12: Are all rejections going to team leader | B12: NO
A13: Are all rejections going to original enumerator | B13: NO | G13: New feature to be implemented
A14: Are all rejection going to sales reps | B14: NO | G14: New feature to be implemented
A15: What devices will be used by enumerators & Team leaders | B15: Android Based TBC
A16: What devices will be used by sales reps

Sheet JSON BuilderSKU
B2: JSON | C2: ID | D2: JSON | E2: CHANNEL | H2: COMPANY | J2: litrage/bottle | K2: JSON | L2: litrage/case
A3: " | B3: { "v": | C3: ='Volume & Price List'!A10 -> V60SKU1 | D3: , "n": { "EN": " | E3: ='Volume & Price List'!B10 -> Aspen | F3: ", "SYS":" | G3: "}, "company": " | H3: ='Volume & Price List'!G10 -> JTI | I3: ", "conv": [ | J3: ='Volume & Price List'!I10 -> 10 | K3: , | L3: ='Volume & Price List'!K10 -> 0 | M3: ] }, | N3: =CONCATENATE(B3,A3,C3,A3,D3,E3,F3,E3,G3,H3,I3,J3,K3,L3,M3) -> { "v": "V60SKU1", "n": { "EN": "Aspen", "SYS":"Aspen "}, "company": "JTI", "conv": [10,0] },
A4: " | B4: { "v": | C4: ='Volume & Price List'!A11 -> V60SKU2 | D4: , "n": { "EN": " | E4: ='Volume & Price List'!B11 -> Winston | F4: ", "SYS":" | G4: "}, "company": " | H4: ='Volume & Price List'!G11 -> JTI | I4: ", "conv": [ | J4: ='Volume & Price List'!I11 -> 10 | K4: , | L4: ='Volume & Price List'!K11 -> 0 | M4: ] }, | N4: =CONCATENATE(B4,A4,C4,A4,D4,E4,F4,E4,G4,H4,I4,J4,K4,L4,M4) -> { "v": "V60SKU2", "n": { "EN": "Winston", "SYS":"Winston "}, "company": "JTI", "conv": [10,0] },
A5: " | B5: { "v": | C5: ='Volume & Price List'!A12 -> V60SKU3 | D5: , "n": { "EN": " | E5: ='Volume & Price List'!B12 -> Marlboro | F5: ", "SYS":" | G5: "}, "company": " | H5: ='Volume & Price List'!G12 -> PMI | I5: ", "conv": [ | J5: ='Volume & Price List'!I12 -> 10 | K5: , | L5: ='Volume & Price List'!K12 -> 0 | M5: ] }, | N5: =CONCATENATE(B5,A5,C5,A5,D5,E5,F5,E5,G5,H5,I5,J5,K5,L5,M5) -> { "v": "V60SKU3", "n": { "EN": "Marlboro", "SYS":"Marlboro "}, "company": "PMI", "conv": [10,0] },
A6: " | B6: { "v": | C6: ='Volume & Price List'!#REF! -> #REF! | D6: , "n": { "EN": " | E6: ='Volume & Price List'!#REF! -> #REF! | F6: ", "SYS":" | G6: "}, "company": " | H6: ='Volume & Price List'!#REF! -> #REF! | I6: ", "conv": [ | J6: ='Volume & Price List'!#REF! -> #REF! | K6: , | L6: ='Volume & Price List'!#REF! -> #REF! | M6: ] }, | N6: =CONCATENATE(B6,A6,C6,A6,D6,E6,F6,E6,G6,H6,I6,J6,K6,L6,M6) -> #REF!
A7: " | B7: { "v": | C7: ='Volume & Price List'!A13 -> V60SKU4 | D7: , "n": { "EN": " | E7: ='Volume & Price List'!B13 -> B&H | F7: ", "SYS":" | G7: "}, "company": " | H7: ='Volume & Price List'!G13 -> BAT | I7: ", "conv": [ | J7: ='Volume & Price List'!I13 -> 10 | K7: , | L7: ='Volume & Price List'!K13 -> 0 | M7: ] }, | N7: =CONCATENATE(B7,A7,C7,A7,D7,E7,F7,E7,G7,H7,I7,J7,K7,L7,M7) -> { "v": "V60SKU4", "n": { "EN": "B&H", "SYS":"B&H "}, "company": "BAT", "conv": [10,0] },
A8: " | B8: { "v": | C8: ='Volume & Price List'!A14 -> V60SKU5 | D8: , "n": { "EN": " | E8: ='Volume & Price List'!B14 -> L&B | F8: ", "SYS":" | G8: "}, "company": " | H8: ='Volume & Price List'!G14 -> BAT | I8: ", "conv": [ | J8: ='Volume & Price List'!I14 -> 10 | K8: , | L8: ='Volume & Price List'!K14 -> 0 | M8: ] }, | N8: =CONCATENATE(B8,A8,C8,A8,D8,E8,F8,E8,G8,H8,I8,J8,K8,L8,M8) -> { "v": "V60SKU5", "n": { "EN": "L&B", "SYS":"L&B "}, "company": "BAT", "conv": [10,0] },
A9: " | B9: { "v": | C9: ='Volume & Price List'!A15 -> V60SKU6 | D9: , "n": { "EN": " | E9: ='Volume & Price List'!B15 -> Rothmans | F9: ", "SYS":" | G9: "}, "company": " | H9: ='Volume & Price List'!G15 -> BAT | I9: ", "conv": [ | J9: ='Volume & Price List'!I15 -> 10 | K9: , | L9: ='Volume & Price List'!K15 -> 0 | M9: ] }, | N9: =CONCATENATE(B9,A9,C9,A9,D9,E9,F9,E9,G9,H9,I9,J9,K9,L9,M9) -> { "v": "V60SKU6", "n": { "EN": "Rothmans", "SYS":"Rothmans "}, "company": "BAT", "conv": [10,0] },
A10: " | B10: { "v": | C10: ='Volume & Price List'!A16 -> V60SKU7 | D10: , "n": { "EN": " | E10: ='Volume & Price List'!B16 -> Diplomat | F10: ", "SYS":" | G10: "}, "company": " | H10: ='Volume & Price List'!G16 -> BAT | I10: ", "conv": [ | J10: ='Volume & Price List'!I16 -> 10 | K10: , | L10: ='Volume & Price List'!K16 -> 0 | M10: ] }, | N10: =CONCATENATE(B10,A10,C10,A10,D10,E10,F10,E10,G10,H10,I10,J10,K10,L10,M10) -> { "v": "V60SKU7", "n": { "EN": "Diplomat", "SYS":"Diplomat "}, "company": "BAT", "conv": [10,0] },
A11: " | B11: { "v": | C11: ='Volume & Price List'!A17 -> V60SKU8 | D11: , "n": { "EN": " | E11: ='Volume & Price List'!B17 -> Gold Seal | F11: ", "SYS":" | G11: "}, "company": " | H11: ='Volume & Price List'!G17 -> Oriental | I11: ", "conv": [ | J11: ='Volume & Price List'!I17 -> 10 | K11: , | L11: ='Volume & Price List'!K17 -> 0 | M11: ] }, | N11: =CONCATENATE(B11,A11,C11,A11,D11,E11,F11,E11,G11,H11,I11,J11,K11,L11,M11) -> { "v": "V60SKU8", "n": { "EN": "Gold Seal", "SYS":"Gold Seal "}, "company": "Oriental", "conv": [10,0] },
B12: { "v": | C12: ='Volume & Price List'!A18 -> V60SKU9 | D12: , "n": { "EN": " | E12: ='Volume & Price List'!B18 -> Gold Pin | F12: ", "SYS":" | G12: "}, "company": " | H12: ='Volume & Price List'!G18 -> Oriental | I12: ", "conv": [ | J12: ='Volume & Price List'!I18 -> 10 | K12: , | L12: ='Volume & Price List'!K18 -> 0 | M12: ] }, | N12: =CONCATENATE(B12,A12,C12,A12,D12,E12,F12,E12,G12,H12,I12,J12,K12,L12,M12) -> { "v": V60SKU9, "n": { "EN": "Gold Pin", "SYS":"Gold Pin "}, "company": "Oriental", "conv": [10,0] },
B13: { "v": | C13: ='Volume & Price List'!A19 -> V60SKU10 | D13: , "n": { "EN": " | E13: ='Volume & Price List'!B19 -> Oris | F13: ", "SYS":" | G13: "}, "company": " | H13: ='Volume & Price List'!G19 -> Oriental | I13: ", "conv": [ | J13: ='Volume & Price List'!I19 -> 10 | K13: , | L13: ='Volume & Price List'!K19 -> 0 | M13: ] }, | N13: =CONCATENATE(B13,A13,C13,A13,D13,E13,F13,E13,G13,H13,I13,J13,K13,L13,M13) -> { "v": V60SKU10, "n": { "EN": "Oris", "SYS":"Oris "}, "company": "Oriental", "conv": [10,0] },
B14: { "v": | C14: ='Volume & Price List'!A20 -> V60SKU11 | D14: , "n": { "EN": " | E14: ='Volume & Price List'!B20 -> D&J | F14: ", "SYS":" | G14: "}, "company": " | H14: ='Volume & Price List'!G20 -> Oriental | I14: ", "conv": [ | J14: ='Volume & Price List'!I20 -> 10 | K14: , | L14: ='Volume & Price List'!K20 -> 0 | M14: ] }, | N14: =CONCATENATE(B14,A14,C14,A14,D14,E14,F14,E14,G14,H14,I14,J14,K14,L14,M14) -> { "v": V60SKU11, "n": { "EN": "D&J", "SYS":"D&J "}, "company": "Oriental", "conv": [10,0] },
B15: { "v": | C15: ='Volume & Price List'!A21 -> V60SKU12 | D15: , "n": { "EN": " | E15: ='Volume & Price List'!B21 -> Esse | F15: ", "SYS":" | G15: "}, "company": " | H15: ='Volume & Price List'!G21 -> KT&G | I15: ", "conv": [ | J15: ='Volume & Price List'!I21 -> 10 | K15: , | L15: ='Volume & Price List'!K21 -> 0 | M15: ] }, | N15: =CONCATENATE(B15,A15,C15,A15,D15,E15,F15,E15,G15,H15,I15,J15,K15,L15,M15) -> { "v": V60SKU12, "n": { "EN": "Esse", "SYS":"Esse "}, "company": "KT&G", "conv": [10,0] },
B16: { "v": | C16: ='Volume & Price List'!A22 -> V60SKU13 | D16: , "n": { "EN": " | E16: ='Volume & Price List'!B22 -> Time | F16: ", "SYS":" | G16: "}, "company": " | H16: ='Volume & Price List'!G22 -> KT&G | I16: ", "conv": [ | J16: ='Volume & Price List'!I22 -> 10 | K16: , | L16: ='Volume & Price List'!K22 -> 0 | M16: ] }, | N16: =CONCATENATE(B16,A16,C16,A16,D16,E16,F16,E16,G16,H16,I16,J16,K16,L16,M16) -> { "v": V60SKU13, "n": { "EN": "Time", "SYS":"Time "}, "company": "KT&G", "conv": [10,0] },
B17: { "v": | C17: ='Volume & Price List'!A23 -> V60SKU14 | D17: , "n": { "EN": " | E17: ='Volume & Price List'!B23 -> Vega | F17: ", "SYS":" | G17: "}, "company": " | H17: ='Volume & Price List'!G23 -> Others | I17: ", "conv": [ | J17: ='Volume & Price List'!I23 -> 10 | K17: , | L17: ='Volume & Price List'!K23 -> 0 | M17: ] }, | N17: =CONCATENATE(B17,A17,C17,A17,D17,E17,F17,E17,G17,H17,I17,J17,K17,L17,M17) -> { "v": V60SKU14, "n": { "EN": "Vega", "SYS":"Vega "}, "company": "Others ", "conv": [10,0] },
B18: { "v": | C18: ='Volume & Price List'!A24 -> 0 | D18: , "n": { "EN": " | E18: ='Volume & Price List'!B24 -> 0 | F18: ", "SYS":" | G18: "}, "company": " | H18: ='Volume & Price List'!G24 -> 0 | I18: ", "conv": [ | J18: ='Volume & Price List'!I24 -> 10 | K18: , | L18: ='Volume & Price List'!K24 -> 0 | M18: ] }, | N18: =CONCATENATE(B18,A18,C18,A18,D18,E18,F18,E18,G18,H18,I18,J18,K18,L18,M18) -> { "v": 0, "n": { "EN": "0", "SYS":"0 "}, "company": "0", "conv": [10,0] },
B19: { "v": | C19: ='Volume & Price List'!A25 -> 0 | D19: , "n": { "EN": " | E19: ='Volume & Price List'!B25 -> 0 | F19: ", "SYS":" | G19: "}, "company": " | H19: ='Volume & Price List'!G25 -> 0 | I19: ", "conv": [ | J19: ='Volume & Price List'!I25 -> 0 | K19: , | L19: ='Volume & Price List'!K25 -> 0 | M19: ] }, | N19: =CONCATENATE(B19,A19,C19,A19,D19,E19,F19,E19,G19,H19,I19,J19,K19,L19,M19) -> { "v": 0, "n": { "EN": "0", "SYS":"0 "}, "company": "0", "conv": [0,0] },
B20: { "v": | C20: ='Volume & Price List'!A26 -> 0 | D20: , "n": { "EN": " | E20: ='Volume & Price List'!B26 -> 0 | F20: ", "SYS":" | G20: "}, "company": " | H20: ='Volume & Price List'!G26 -> 0 | I20: ", "conv": [ | J20: ='Volume & Price List'!I26 -> 0 | K20: , | L20: ='Volume & Price List'!K26 -> 0 | M20: ] }, | N20: =CONCATENATE(B20,A20,C20,A20,D20,E20,F20,E20,G20,H20,I20,J20,K20,L20,M20) -> { "v": 0, "n": { "EN": "0", "SYS":"0 "}, "company": "0", "conv": [0,0] },
B21: { "v": | C21: ='Volume & Price List'!A27 -> 0 | D21: , "n": { "EN": " | E21: ='Volume & Price List'!B27 -> 0 | F21: ", "SYS":" | G21: "}, "company": " | H21: ='Volume & Price List'!G27 -> 0 | I21: ", "conv": [ | J21: ='Volume & Price List'!I27 -> 0 | K21: , | L21: ='Volume & Price List'!K27 -> 0 | M21: ] }, | N21: =CONCATENATE(B21,A21,C21,A21,D21,E21,F21,E21,G21,H21,I21,J21,K21,L21,M21) -> { "v": 0, "n": { "EN": "0", "SYS":"0 "}, "company": "0", "conv": [0,0] },
B22: { "v": | C22: ='Volume & Price List'!A28 -> 0 | D22: , "n": { "EN": " | E22: ='Volume & Price List'!B28 -> 0 | F22: ", "SYS":" | G22: "}, "company": " | H22: ='Volume & Price List'!G28 -> 0 | I22: ", "conv": [ | J22: ='Volume & Price List'!I28 -> 0 | K22: , | L22: ='Volume & Price List'!K28 -> 0 | M22: ] }, | N22: =CONCATENATE(B22,A22,C22,A22,D22,E22,F22,E22,G22,H22,I22,J22,K22,L22,M22) -> { "v": 0, "n": { "EN": "0", "SYS":"0 "}, "company": "0", "conv": [0,0] },
B23: { "v": | C23: ='Volume & Price List'!A29 -> 0 | D23: , "n": { "EN": " | E23: ='Volume & Price List'!B29 -> 0 | F23: ", "SYS":" | G23: "}, "company": " | H23: ='Volume & Price List'!G29 -> 0 | I23: ", "conv": [ | J23: ='Volume & Price List'!I29 -> 0 | K23: , | L23: ='Volume & Price List'!K29 -> 0 | M23: ] }, | N23: =CONCATENATE(B23,A23,C23,A23,D23,E23,F23,E23,G23,H23,I23,J23,K23,L23,M23) -> { "v": 0, "n": { "EN": "0", "SYS":"0 "}, "company": "0", "conv": [0,0] },
... B41: { "v": | C41: ='Volume & Price List'!A47 -> 40 | D41: , "n": { "EN": " | E41: ='Volume & Price List'!B47 -> 0 | F41: ", "SYS":" | G41: "}, "company": " | H41: ='Volume & Price List'!G47 -> 0 | I41: ", "conv": [ | J41: ='Volume & Price List'!I47 -> 0 | K41: , | L41: ='Volume & Price List'!K47 -> 0 | M41: ] }, | N41: =CONCATENATE(B41,A41,C41,A41,D41,E41,F41,E41,G41,H41,I41,J41,K41,L41,M41) -> { "v": 40, "n": { "EN": "0", "SYS":"0 "}, "company": "0", "conv": [0,0] },
B42: { "v": | C42: ='Volume & Price List'!A49 -> 42 | D42: , "n": { "EN": " | E42: ='Volume & Price List'!B49 -> 0 | F42: ", "SYS":" | G42: "}, "company": " | H42: ='Volume & Price List'!G49 -> 0 | I42: ", "conv": [ | J42: ='Volume & Price List'!I49 -> 0 | K42: , | L42: ='Volume & Price List'!K49 -> 0 | M42: ] }, | N42: =CONCATENATE(B42,A42,C42,A42,D42,E42,F42,E42,G42,H42,I42,J42,K42,L42,M42) -> { "v": 42, "n": { "EN": "0", "SYS":"0 "}, "company": "0", "conv": [0,0] },
B43: { "v": | C43: ='Volume & Price List'!A50 -> 43 | D43: , "n": { "EN": " | E43: ='Volume & Price List'!B50 -> 0 | F43: ", "SYS":" | G43: "}, "company": " | H43: ='Volume & Price List'!G50 -> 0 | I43: ", "conv": [ | J43: ='Volume & Price List'!I50 -> 0 | K43: , | L43: ='Volume & Price List'!K50 -> 0 | M43: ] }, | N43: =CONCATENATE(B43,A43,C43,A43,D43,E43,F43,E43,G43,H43,I43,J43,K43,L43,M43) -> { "v": 43, "n": { "EN": "0", "SYS":"0 "}, "company": "0", "conv": [0,0] },
B44: { "v": | C44: ='Volume & Price List'!A51 -> 44 | D44: , "n": { "EN": " | E44: ='Volume & Price List'!B51 -> 0 | F44: ", "SYS":" | G44: "}, "company": " | H44: ='Volume & Price List'!G51 -> 0 | I44: ", "conv": [ | J44: ='Volume & Price List'!I51 -> 0 | K44: , | L44: ='Volume & Price List'!K51 -> 0 | M44: ] }, | N44: =CONCATENATE(B44,A44,C44,A44,D44,E44,F44,E44,G44,H44,I44,J44,K44,L44,M44) -> { "v": 44, "n": { "EN": "0", "SYS":"0 "}, "company": "0", "conv": [0,0] },
B45: { "v": | C45: ='Volume & Price List'!A52 -> 45 | D45: , "n": { "EN": " | E45: ='Volume & Price List'!B52 -> 0 | F45: ", "SYS":" | G45: "}, "company": " | H45: ='Volume & Price List'!G52 -> 0 | I45: ", "conv": [ | J45: ='Volume & Price List'!I52 -> 0 | K45: , | L45: ='Volume & Price List'!K52 -> 0 | M45: ] }, | N45: =CONCATENATE(B45,A45,C45,A45,D45,E45,F45,E45,G45,H45,I45,J45,K45,L45,M45) -> { "v": 45, "n": { "EN": "0", "SYS":"0 "}, "company": "0", "conv": [0,0] },
B46: { "v": | C46: ='Volume & Price List'!A53 -> 46 | D46: , "n": { "EN": " | E46: ='Volume & Price List'!B53 -> 0 | F46: ", "SYS":" | G46: "}, "company": " | H46: ='Volume & Price List'!G53 -> 0 | I46: ", "conv": [ | J46: ='Volume & Price List'!I53 -> 0 | K46: , | L46: ='Volume & Price List'!K53 -> 0 | M46: ] }, | N46: =CONCATENATE(B46,A46,C46,A46,D46,E46,F46,E46,G46,H46,I46,J46,K46,L46,M46) -> { "v": 46, "n": { "EN": "0", "SYS":"0 "}, "company": "0", "conv": [0,0] },
B47: { "v": | C47: ='Volume & Price List'!A54 -> 47 | D47: , "n": { "EN": " | E47: ='Volume & Price List'!B54 -> 0 | F47: ", "SYS":" | G47: "}, "company": " | H47: ='Volume & Price List'!G54 -> 0 | I47: ", "conv": [ | J47: ='Volume & Price List'!I54 -> 0 | K47: , | L47: ='Volume & Price List'!K54 -> 0 | M47: ] }, | N47: =CONCATENATE(B47,A47,C47,A47,D47,E47,F47,E47,G47,H47,I47,J47,K47,L47,M47) -> { "v": 47, "n": { "EN": "0", "SYS":"0 "}, "company": "0", "conv": [0,0] },
B48: { "v": | C48: ='Volume & Price List'!A55 -> 48 | D48: , "n": { "EN": " | E48: ='Volume & Price List'!B55 -> 0 | F48: ", "SYS":" | G48: "}, "company": " | H48: ='Volume & Price List'!G55 -> 0 | I48: ", "conv": [ | J48: ='Volume & Price List'!I55 -> 0 | K48: , | L48: ='Volume & Price List'!K55 -> 0 | M48: ] }, | N48: =CONCATENATE(B48,A48,C48,A48,D48,E48,F48,E48,G48,H48,I48,J48,K48,L48,M48) -> { "v": 48, "n": { "EN": "0", "SYS":"0 "}, "company": "0", "conv": [0,0] },
B49: { "v": | C49: ='Volume & Price List'!A56 -> 0 | D49: , "n": { "EN": " | E49: ='Volume & Price List'!B56 -> 0 | F49: ", "SYS":" | G49: "}, "company": " | H49: ='Volume & Price List'!G56 -> 0 | I49: ", "conv": [ | J49: ='Volume & Price List'!I56 -> 0 | K49: , | L49: ='Volume & Price List'!K56 -> 0 | M49: ] }, | N49: =CONCATENATE(B49,A49,C49,A49,D49,E49,F49,E49,G49,H49,I49,J49,K49,L49,M49) -> { "v": 0, "n": { "EN": "0", "SYS":"0 "}, "company": "0", "conv": [0,0] },
B50: { "v": | C50: ='Volume & Price List'!A57 -> V-70 | D50: , "n": { "EN": " | E50: ='Volume & Price List'!B57 -> Shisa | F50: ", "SYS":" | G50: "}, "company": " | H50: ='Volume & Price List'!G57 -> Company | I50: ", "conv": [ | J50: ='Volume & Price List'!I57 -> Conversion Pack | K50: , | L50: ='Volume & Price List'!K57 -> Conversion Carton | M50: ] }, | N50: =CONCATENATE(B50,A50,C50,A50,D50,E50,F50,E50,G50,H50,I50,J50,K50,L50,M50) -> { "v": V-70, "n": { "EN": "Shisa", "SYS":"Shisa "}, "company": "Company", "conv": [Conversion Pack,Conversion Carton] },
B51: { "v": | C51: ='Volume & Price List'!A58 -> 1 | D51: , "n": { "EN": " | E51: ='Volume & Price List'!B58 -> 0 | F51: ", "SYS":" | G51: "}, "company": " | H51: ='Volume & Price List'!G58 -> 0 | I51: ", "conv": [ | J51: ='Volume & Price List'!I58 -> 0 | K51: , | L51: ='Volume & Price List'!K58 -> 0 | M51: ] }, | N51: =CONCATENATE(B51,A51,C51,A51,D51,E51,F51,E51,G51,H51,I51,J51,K51,L51,M51) -> { "v": 1, "n": { "EN": "0", "SYS":"0 "}, "company": "0", "conv": [0,0] },
B52: { "v": | C52: ='Volume & Price List'!A59 -> 2 | D52: , "n": { "EN": " | E52: ='Volume & Price List'!B59 -> 0 | F52: ", "SYS":" | G52: "}, "company": " | H52: ='Volume & Price List'!G59 -> 0 | I52: ", "conv": [ | J52: ='Volume & Price List'!I59 -> 0 | K52: , | L52: ='Volume & Price List'!K59 -> 0 | M52: ] }, | N52: =CONCATENATE(B52,A52,C52,A52,D52,E52,F52,E52,G52,H52,I52,J52,K52,L52,M52) -> { "v": 2, "n": { "EN": "0", "SYS":"0 "}, "company": "0", "conv": [0,0] },
B53: { "v": | C53: ='Volume & Price List'!A60 -> 3 | D53: , "n": { "EN": " | E53: ='Volume & Price List'!B60 -> 0 | F53: ", "SYS":" | G53: "}, "company": " | H53: ='Volume & Price List'!G60 -> 0 | I53: ", "conv": [ | J53: ='Volume & Price List'!I60 -> 0 | K53: , | L53: ='Volume & Price List'!K60 -> 0 | M53: ] }, | N53: =CONCATENATE(B53,A53,C53,A53,D53,E53,F53,E53,G53,H53,I53,J53,K53,L53,M53) -> { "v": 3, "n": { "EN": "0", "SYS":"0 "}, "company": "0", "conv": [0,0] },
... B70: { "v": | C70: ='Volume & Price List'!A77 -> 20 | D70: , "n": { "EN": " | E70: ='Volume & Price List'!B77 -> 0 | F70: ", "SYS":" | G70: "}, "company": " | H70: ='Volume & Price List'!G77 -> 0 | I70: ", "conv": [ | J70: ='Volume & Price List'!I77 -> 0 | K70: , | L70: ='Volume & Price List'!K77 -> 0 | M70: ] }, | N70: =CONCATENATE(B70,A70,C70,A70,D70,E70,F70,E70,G70,H70,I70,J70,K70,L70,M70) -> { "v": 20, "n": { "EN": "0", "SYS":"0 "}, "company": "0", "conv": [0,0] },
B71: { "v": | C71: ='Volume & Price List'!A78 -> 21 | D71: , "n": { "EN": " | E71: ='Volume & Price List'!B78 -> 0 | F71: ", "SYS":" | G71: "}, "company": " | H71: ='Volume & Price List'!G78 -> 0 | I71: ", "conv": [ | J71: ='Volume & Price List'!I78 -> 0 | K71: , | L71: ='Volume & Price List'!K78 -> 0 | N71: =CONCATENATE(B71,A71,C71,A71,D71,E71,F71,E71,G71,H71,I71,J71,K71,L71,M71) -> { "v": 21, "n": { "EN": "0", "SYS":"0 "}, "company": "0", "conv": [0,0
B72: { "v": | C72: ='Volume & Price List'!A79 -> 22 | D72: , "n": { "EN": " | E72: ='Volume & Price List'!B79 -> 0 | F72: ", "SYS":" | G72: "}, "company": " | H72: ='Volume & Price List'!G79 -> 0 | I72: ", "conv": [ | J72: ='Volume & Price List'!I79 -> 0 | K72: , | L72: ='Volume & Price List'!K79 -> 0 | N72: =CONCATENATE(B72,A72,C72,A72,D72,E72,F72,E72,G72,H72,I72,J72,K72,L72,M72) -> { "v": 22, "n": { "EN": "0", "SYS":"0 "}, "company": "0", "conv": [0,0
B73: { "v": | C73: ='Volume & Price List'!A80 -> 23 | D73: , "n": { "EN": " | E73: ='Volume & Price List'!B80 -> 0 | F73: ", "SYS":" | G73: "}, "company": " | H73: ='Volume & Price List'!G80 -> 0 | I73: ", "conv": [ | J73: ='Volume & Price List'!I80 -> 0 | K73: , | L73: ='Volume & Price List'!K80 -> 0 | N73: =CONCATENATE(B73,A73,C73,A73,D73,E73,F73,E73,G73,H73,I73,J73,K73,L73,M73) -> { "v": 23, "n": { "EN": "0", "SYS":"0 "}, "company": "0", "conv": [0,0
B74: { "v": | C74: ='Volume & Price List'!A81 -> 24 | D74: , "n": { "EN": " | E74: ='Volume & Price List'!B81 -> 0 | F74: ", "SYS":" | G74: "}, "company": " | H74: ='Volume & Price List'!G81 -> 0 | I74: ", "conv": [ | J74: ='Volume & Price List'!I81 -> 0 | K74: , | L74: ='Volume & Price List'!K81 -> 0 | N74: =CONCATENATE(B74,A74,C74,A74,D74,E74,F74,E74,G74,H74,I74,J74,K74,L74,M74) -> { "v": 24, "n": { "EN": "0", "SYS":"0 "}, "company": "0", "conv": [0,0
B75: { "v": | C75: ='Volume & Price List'!A82 -> 25 | D75: , "n": { "EN": " | E75: ='Volume & Price List'!B82 -> 0 | F75: ", "SYS":" | G75: "}, "company": " | H75: ='Volume & Price List'!G82 -> 0 | I75: ", "conv": [ | J75: ='Volume & Price List'!I82 -> 0 | K75: , | L75: ='Volume & Price List'!K82 -> 0 | N75: =CONCATENATE(B75,A75,C75,A75,D75,E75,F75,E75,G75,H75,I75,J75,K75,L75,M75) -> { "v": 25, "n": { "EN": "0", "SYS":"0 "}, "company": "0", "conv": [0,0
B76: { "v": | C76: ='Volume & Price List'!A83 -> 26 | D76: , "n": { "EN": " | E76: ='Volume & Price List'!B83 -> 0 | F76: ", "SYS":" | G76: "}, "company": " | H76: ='Volume & Price List'!G83 -> 0 | I76: ", "conv": [ | J76: ='Volume & Price List'!I83 -> 0 | K76: , | L76: ='Volume & Price List'!K83 -> 0 | N76: =CONCATENATE(B76,A76,C76,A76,D76,E76,F76,E76,G76,H76,I76,J76,K76,L76,M76) -> { "v": 26, "n": { "EN": "0", "SYS":"0 "}, "company": "0", "conv": [0,0
B77: { "v": | C77: ='Volume & Price List'!A84 -> 27 | D77: , "n": { "EN": " | E77: ='Volume & Price List'!B84 -> 0 | F77: ", "SYS":" | G77: "}, "company": " | H77: ='Volume & Price List'!G84 -> 0 | I77: ", "conv": [ | J77: ='Volume & Price List'!I84 -> 0 | K77: , | L77: ='Volume & Price List'!K84 -> 0 | N77: =CONCATENATE(B77,A77,C77,A77,D77,E77,F77,E77,G77,H77,I77,J77,K77,L77,M77) -> { "v": 27, "n": { "EN": "0", "SYS":"0 "}, "company": "0", "conv": [0,0
B78: { "v": | C78: ='Volume & Price List'!A85 -> 28 | D78: , "n": { "EN": " | E78: ='Volume & Price List'!B85 -> 0 | F78: ", "SYS":" | G78: "}, "company": " | H78: ='Volume & Price List'!G85 -> 0 | I78: ", "conv": [ | J78: ='Volume & Price List'!I85 -> 0 | K78: , | L78: ='Volume & Price List'!K85 -> 0 | N78: =CONCATENATE(B78,A78,C78,A78,D78,E78,F78,E78,G78,H78,I78,J78,K78,L78,M78) -> { "v": 28, "n": { "EN": "0", "SYS":"0 "}, "company": "0", "conv": [0,0
B79: { "v": | C79: ='Volume & Price List'!A86 -> 29 | D79: , "n": { "EN": " | E79: ='Volume & Price List'!B86 -> 0 | F79: ", "SYS":" | G79: "}, "company": " | H79: ='Volume & Price List'!G86 -> 0 | I79: ", "conv": [ | J79: ='Volume & Price List'!I86 -> 0 | K79: , | L79: ='Volume & Price List'!K86 -> 0 | N79: =CONCATENATE(B79,A79,C79,A79,D79,E79,F79,E79,G79,H79,I79,J79,K79,L79,M79) -> { "v": 29, "n": { "EN": "0", "SYS":"0 "}, "company": "0", "conv": [0,0
B80: { "v": | C80: ='Volume & Price List'!A87 -> 30 | D80: , "n": { "EN": " | E80: ='Volume & Price List'!B87 -> 0 | F80: ", "SYS":" | G80: "}, "company": " | H80: ='Volume & Price List'!G87 -> 0 | I80: ", "conv": [ | J80: ='Volume & Price List'!I87 -> 0 | K80: , | L80: ='Volume & Price List'!K87 -> 0 | N80: =CONCATENATE(B80,A80,C80,A80,D80,E80,F80,E80,G80,H80,I80,J80,K80,L80,M80) -> { "v": 30, "n": { "EN": "0", "SYS":"0 "}, "company": "0", "conv": [0,0
B81: { "v": | C81: ='Volume & Price List'!A88 -> 31 | D81: , "n": { "EN": " | E81: ='Volume & Price List'!B88 -> 0 | F81: ", "SYS":" | G81: "}, "company": " | H81: ='Volume & Price List'!G88 -> 0 | I81: ", "conv": [ | J81: ='Volume & Price List'!I88 -> 0 | K81: , | L81: ='Volume & Price List'!K88 -> 0 | N81: =CONCATENATE(B81,A81,C81,A81,D81,E81,F81,E81,G81,H81,I81,J81,K81,L81,M81) -> { "v": 31, "n": { "EN": "0", "SYS":"0 "}, "company": "0", "conv": [0,0
B82: { "v": | C82: ='Volume & Price List'!A89 -> 32 | D82: , "n": { "EN": " | E82: ='Volume & Price List'!B89 -> 0 | F82: ", "SYS":" | G82: "}, "company": " | H82: ='Volume & Price List'!G89 -> 0 | I82: ", "conv": [ | J82: ='Volume & Price List'!I89 -> 0 | K82: , | L82: ='Volume & Price List'!K89 -> 0 | N82: =CONCATENATE(B82,A82,C82,A82,D82,E82,F82,E82,G82,H82,I82,J82,K82,L82,M82) -> { "v": 32, "n": { "EN": "0", "SYS":"0 "}, "company": "0", "conv": [0,0
... B99: { "v": | C99: ='Volume & Price List'!A106 -> 0 | D99: , "n": { "EN": " | E99: ='Volume & Price List'!B106 -> 0 | F99: ", "SYS":" | G99: "}, "company": " | H99: ='Volume & Price List'!G106 -> 0 | I99: ", "conv": [ | J99: ='Volume & Price List'!I106 -> 0 | K99: , | L99: ='Volume & Price List'!K106 -> 0 | N99: =CONCATENATE(B99,A99,C99,A99,D99,E99,F99,E99,G99,H99,I99,J99,K99,L99,M99) -> { "v": 0, "n": { "EN": "0", "SYS":"0 "}, "company": "0", "conv": [0,0
B105: { "v": | C105: ='Volume & Price List'!A109 -> 0 | D105: , "n": { "EN": " | E105: ='Volume & Price List'!B109 -> 0 | F105: ", "SYS":" | G105: "}, "company": " | H105: ='Volume & Price List'!G109 -> 0 | I105: ", "conv": [ | J105: ='Volume & Price List'!I109 -> 0 | K105: , | L105: ='Volume & Price List'!K109 -> 0 | N105: =CONCATENATE(B105,C105,D105,E105,F105,E105,G105,H105,I105,J105,K105,L105,M105) -> { "v": 0, "n": { "EN": "0", "SYS":"0 "}, "company": "0", "conv": [0,0
B106: { "v": | C106: ='Volume & Price List'!A110 -> 0 | D106: , "n": { "EN": " | E106: ='Volume & Price List'!B110 -> 0 | F106: ", "SYS":" | G106: "}, "company": " | H106: ='Volume & Price List'!G110 -> 0 | I106: ", "conv": [ | J106: ='Volume & Price List'!I110 -> 0 | K106: , | L106: ='Volume & Price List'!K110 -> 0 | N106: =CONCATENATE(B106,C106,D106,E106,F106,E106,G106,H106,I106,J106,K106,L106,M106) -> { "v": 0, "n": { "EN": "0", "SYS":"0 "}, "company": "0", "conv": [0,0
B107: { "v": | C107: ='Volume & Price List'!A111 -> 0 | D107: , "n": { "EN": " | E107: ='Volume & Price List'!B111 -> 0 | F107: ", "SYS":" | G107: "}, "company": " | H107: ='Volume & Price List'!G111 -> 0 | I107: ", "conv": [ | J107: ='Volume & Price List'!I111 -> 0 | K107: , | L107: ='Volume & Price List'!K111 -> 0 | N107: =CONCATENATE(B107,C107,D107,E107,F107,E107,G107,H107,I107,J107,K107,L107,M107) -> { "v": 0, "n": { "EN": "0", "SYS":"0 "}, "company": "0", "conv": [0,0
B108: { "v": | C108: ='Volume & Price List'!A112 -> 0 | D108: , "n": { "EN": " | E108: ='Volume & Price List'!B112 -> 0 | F108: ", "SYS":" | G108: "}, "company": " | H108: ='Volume & Price List'!G112 -> 0 | I108: ", "conv": [ | J108: ='Volume & Price List'!I112 -> 0 | K108: , | L108: ='Volume & Price List'!K112 -> 0 | N108: =CONCATENATE(B108,C108,D108,E108,F108,E108,G108,H108,I108,J108,K108,L108,M108) -> { "v": 0, "n": { "EN": "0", "SYS":"0 "}, "company": "0", "conv": [0,0
B109: { "v": | C109: ='Volume & Price List'!A113 -> 0 | D109: , "n": { "EN": " | E109: ='Volume & Price List'!B113 -> 0 | F109: ", "SYS":" | G109: "}, "company": " | H109: ='Volume & Price List'!G113 -> 0 | I109: ", "conv": [ | J109: ='Volume & Price List'!I113 -> 0 | K109: , | L109: ='Volume & Price List'!K113 -> 0 | N109: =CONCATENATE(B109,C109,D109,E109,F109,E109,G109,H109,I109,J109,K109,L109,M109) -> { "v": 0, "n": { "EN": "0", "SYS":"0 "}, "company": "0", "conv": [0,0
B110: { "v": | C110: ='Volume & Price List'!A114 -> 0 | D110: , "n": { "EN": " | E110: ='Volume & Price List'!B114 -> 0 | F110: ", "SYS":" | G110: "}, "company": " | H110: ='Volume & Price List'!G114 -> 0 | I110: ", "conv": [ | J110: ='Volume & Price List'!I114 -> 0 | K110: , | L110: ='Volume & Price List'!K114 -> 0 | N110: =CONCATENATE(B110,C110,D110,E110,F110,E110,G110,H110,I110,J110,K110,L110,M110) -> { "v": 0, "n": { "EN": "0", "SYS":"0 "}, "company": "0", "conv": [0,0
B111: { "v": | C111: ='Volume & Price List'!A115 -> 0 | D111: , "n": { "EN": " | E111: ='Volume & Price List'!B115 -> 0 | F111: ", "SYS":" | G111: "}, "company": " | H111: ='Volume & Price List'!G115 -> 0 | I111: ", "conv": [ | J111: ='Volume & Price List'!I115 -> 0 | K111: , | L111: ='Volume & Price List'!K115 -> 0 | N111: =CONCATENATE(B111,C111,D111,E111,F111,E111,G111,H111,I111,J111,K111,L111,M111) -> { "v": 0, "n": { "EN": "0", "SYS":"0 "}, "company": "0", "conv": [0,0
B112: { "v": | C112: ='Volume & Price List'!A116 -> 0 | D112: , "n": { "EN": " | E112: ='Volume & Price List'!B116 -> 0 | F112: ", "SYS":" | G112: "}, "company": " | H112: ='Volume & Price List'!G116 -> 0 | I112: ", "conv": [ | J112: ='Volume & Price List'!I116 -> 0 | K112: , | L112: ='Volume & Price List'!K116 -> 0 | N112: =CONCATENATE(B112,C112,D112,E112,F112,E112,G112,H112,I112,J112,K112,L112,M112) -> { "v": 0, "n": { "EN": "0", "SYS":"0 "}, "company": "0", "conv": [0,0
B113: { "v": | C113: ='Volume & Price List'!A117 -> 0 | D113: , "n": { "EN": " | E113: ='Volume & Price List'!B117 -> 0 | F113: ", "SYS":" | G113: "}, "company": " | H113: ='Volume & Price List'!G117 -> 0 | I113: ", "conv": [ | J113: ='Volume & Price List'!I117 -> 0 | K113: , | L113: ='Volume & Price List'!K117 -> 0 | N113: =CONCATENATE(B113,C113,D113,E113,F113,E113,G113,H113,I113,J113,K113,L113,M113) -> { "v": 0, "n": { "EN": "0", "SYS":"0 "}, "company": "0", "conv": [0,0
B114: { "v": | C114: ='Volume & Price List'!A118 -> 0 | D114: , "n": { "EN": " | E114: ='Volume & Price List'!B118 -> 0 | F114: ", "SYS":" | G114: "}, "company": " | H114: ='Volume & Price List'!G118 -> 0 | I114: ", "conv": [ | J114: ='Volume & Price List'!I118 -> 0 | K114: , | L114: ='Volume & Price List'!K118 -> 0 | N114: =CONCATENATE(B114,C114,D114,E114,F114,E114,G114,H114,I114,J114,K114,L114,M114) -> { "v": 0, "n": { "EN": "0", "SYS":"0 "}, "company": "0", "conv": [0,0
B115: { "v": | C115: ='Volume & Price List'!A119 -> 0 | D115: , "n": { "EN": " | E115: ='Volume & Price List'!B119 -> 0 | F115: ", "SYS":" | G115: "}, "company": " | H115: ='Volume & Price List'!G119 -> 0 | I115: ", "conv": [ | J115: ='Volume & Price List'!I119 -> 0 | K115: , | L115: ='Volume & Price List'!K119 -> 0 | N115: =CONCATENATE(B115,C115,D115,E115,F115,E115,G115,H115,I115,J115,K115,L115,M115) -> { "v": 0, "n": { "EN": "0", "SYS":"0 "}, "company": "0", "conv": [0,0
B116: { "v": | C116: ='Volume & Price List'!A120 -> 0 | D116: , "n": { "EN": " | E116: ='Volume & Price List'!B120 -> 0 | F116: ", "SYS":" | G116: "}, "company": " | H116: ='Volume & Price List'!G120 -> 0 | I116: ", "conv": [ | J116: ='Volume & Price List'!I120 -> 0 | K116: , | L116: ='Volume & Price List'!K120 -> 0 | N116: =CONCATENATE(B116,C116,D116,E116,F116,E116,G116,H116,I116,J116,K116,L116,M116) -> { "v": 0, "n": { "EN": "0", "SYS":"0 "}, "company": "0", "conv": [0,0
... B118: { "v": | C118: ='Volume & Price List'!A122 -> 0 | D118: , "n": { "EN": " | E118: ='Volume & Price List'!B122 -> 0 | F118: ", "SYS":" | G118: "}, "company": " | H118: ='Volume & Price List'!G122 -> 0 | I118: ", "conv": [ | J118: ='Volume & Price List'!I122 -> 0 | K118: , | L118: ='Volume & Price List'!K122 -> 0 | N118: =CONCATENATE(B118,C118,D118,E118,F118,E118,G118,H118,I118,J118,K118,L118,M118) -> { "v": 0, "n": { "EN": "0", "SYS":"0 "}, "company": "0", "conv": [0,0
B125: { "v": | C125: ='Volume & Price List'!A128 -> 0 | D125: , "n": { "EN": " | E125: ='Volume & Price List'!B128 -> 0 | F125: ", "SYS":" | G125: "}, "company": " | H125: ='Volume & Price List'!G128 -> 0 | I125: ", "conv": [ | J125: ='Volume & Price List'!I128 -> 0 | K125: , | L125: ='Volume & Price List'!K128 -> 0 | N125: =CONCATENATE(B125,C125,D125,E125,F125,E125,G125,H125,I125,J125,K125,L125,M125) -> { "v": 0, "n": { "EN": "0", "SYS":"0 "}, "company": "0", "conv": [0,0
B126: { "v": | C126: ='Volume & Price List'!A129 -> 0 | D126: , "n": { "EN": " | E126: ='Volume & Price List'!B129 -> 0 | F126: ", "SYS":" | G126: "}, "company": " | H126: ='Volume & Price List'!G129 -> 0 | I126: ", "conv": [ | J126: ='Volume & Price List'!I129 -> 0 | K126: , | L126: ='Volume & Price List'!K129 -> 0 | N126: =CONCATENATE(B126,C126,D126,E126,F126,E126,G126,H126,I126,J126,K126,L126,M126) -> { "v": 0, "n": { "EN": "0", "SYS":"0 "}, "company": "0", "conv": [0,0
B127: { "v": | C127: ='Volume & Price List'!A130 -> 0 | D127: , "n": { "EN": " | E127: ='Volume & Price List'!B130 -> 0 | F127: ", "SYS":" | G127: "}, "company": " | H127: ='Volume & Price List'!G130 -> 0 | I127: ", "conv": [ | J127: ='Volume & Price List'!I130 -> 0 | K127: , | L127: ='Volume & Price List'!K130 -> 0 | N127: =CONCATENATE(B127,C127,D127,E127,F127,E127,G127,H127,I127,J127,K127,L127,M127) -> { "v": 0, "n": { "EN": "0", "SYS":"0 "}, "company": "0", "conv": [0,0
B128: { "v": | C128: ='Volume & Price List'!A131 -> 0 | D128: , "n": { "EN": " | E128: ='Volume & Price List'!B131 -> 0 | F128: ", "SYS":" | G128: "}, "company": " | H128: ='Volume & Price List'!G131 -> 0 | I128: ", "conv": [ | J128: ='Volume & Price List'!I131 -> 0 | K128: , | L128: ='Volume & Price List'!K131 -> 0 | N128: =CONCATENATE(B128,C128,D128,E128,F128,E128,G128,H128,I128,J128,K128,L128,M128) -> { "v": 0, "n": { "EN": "0", "SYS":"0 "}, "company": "0", "conv": [0,0
B129: { "v": | C129: ='Volume & Price List'!A132 -> 0 | D129: , "n": { "EN": " | E129: ='Volume & Price List'!B132 -> 0 | F129: ", "SYS":" | G129: "}, "company": " | H129: ='Volume & Price List'!G132 -> 0 | I129: ", "conv": [ | J129: ='Volume & Price List'!I132 -> 0 | K129: , | L129: ='Volume & Price List'!K132 -> 0 | N129: =CONCATENATE(B129,C129,D129,E129,F129,E129,G129,H129,I129,J129,K129,L129,M129) -> { "v": 0, "n": { "EN": "0", "SYS":"0 "}, "company": "0", "conv": [0,0
B130: { "v": | C130: ='Volume & Price List'!A133 -> 0 | D130: , "n": { "EN": " | E130: ='Volume & Price List'!B133 -> 0 | F130: ", "SYS":" | G130: "}, "company": " | H130: ='Volume & Price List'!G133 -> 0 | I130: ", "conv": [ | J130: ='Volume & Price List'!I133 -> 0 | K130: , | L130: ='Volume & Price List'!K133 -> 0 | N130: =CONCATENATE(B130,C130,D130,E130,F130,E130,G130,H130,I130,J130,K130,L130,M130) -> { "v": 0, "n": { "EN": "0", "SYS":"0 "}, "company": "0", "conv": [0,0
B131: { "v": | C131: ='Volume & Price List'!A134 -> 0 | D131: , "n": { "EN": " | E131: ='Volume & Price List'!B134 -> 0 | F131: ", "SYS":" | G131: "}, "company": " | H131: ='Volume & Price List'!G134 -> 0 | I131: ", "conv": [ | J131: ='Volume & Price List'!I134 -> 0 | K131: , | L131: ='Volume & Price List'!K134 -> 0 | N131: =CONCATENATE(B131,C131,D131,E131,F131,E131,G131,H131,I131,J131,K131,L131,M131) -> { "v": 0, "n": { "EN": "0", "SYS":"0 "}, "company": "0", "conv": [0,0
B132: { "v": | C132: ='Volume & Price List'!A135 -> 0 | D132: , "n": { "EN": " | E132: ='Volume & Price List'!B135 -> 0 | F132: ", "SYS":" | G132: "}, "company": " | H132: ='Volume & Price List'!G135 -> 0 | I132: ", "conv": [ | J132: ='Volume & Price List'!I135 -> 0 | K132: , | L132: ='Volume & Price List'!K135 -> 0 | N132: =CONCATENATE(B132,C132,D132,E132,F132,E132,G132,H132,I132,J132,K132,L132,M132) -> { "v": 0, "n": { "EN": "0", "SYS":"0 "}, "company": "0", "conv": [0,0
B133: { "v": | C133: ='Volume & Price List'!A136 -> 0 | D133: , "n": { "EN": " | E133: ='Volume & Price List'!B136 -> 0 | F133: ", "SYS":" | G133: "}, "company": " | H133: ='Volume & Price List'!G136 -> 0 | I133: ", "conv": [ | J133: ='Volume & Price List'!I136 -> 0 | K133: , | L133: ='Volume & Price List'!K136 -> 0 | N133: =CONCATENATE(B133,C133,D133,E133,F133,E133,G133,H133,I133,J133,K133,L133,M133) -> { "v": 0, "n": { "EN": "0", "SYS":"0 "}, "company": "0", "conv": [0,0
B134: { "v": | C134: ='Volume & Price List'!A137 -> 0 | D134: , "n": { "EN": " | E134: ='Volume & Price List'!B137 -> 0 | F134: ", "SYS":" | G134: "}, "company": " | H134: ='Volume & Price List'!G137 -> 0 | I134: ", "conv": [ | J134: ='Volume & Price List'!I137 -> 0 | K134: , | L134: ='Volume & Price List'!K137 -> 0 | N134: =CONCATENATE(B134,C134,D134,E134,F134,E134,G134,H134,I134,J134,K134,L134,M134) -> { "v": 0, "n": { "EN": "0", "SYS":"0 "}, "company": "0", "conv": [0,0
B135: { "v": | C135: ='Volume & Price List'!A138 -> 0 | D135: , "n": { "EN": " | E135: ='Volume & Price List'!B138 -> 0 | F135: ", "SYS":" | G135: "}, "company": " | H135: ='Volume & Price List'!G138 -> 0 | I135: ", "conv": [ | J135: ='Volume & Price List'!I138 -> 0 | K135: , | L135: ='Volume & Price List'!K138 -> 0 | N135: =CONCATENATE(B135,C135,D135,E135,F135,E135,G135,H135,I135,J135,K135,L135,M135) -> { "v": 0, "n": { "EN": "0", "SYS":"0 "}, "company": "0", "conv": [0,0
B136: { "v": | C136: ='Volume & Price List'!A139 -> 0 | D136: , "n": { "EN": " | E136: ='Volume & Price List'!B139 -> 0 | F136: ", "SYS":" | G136: "}, "company": " | H136: ='Volume & Price List'!G139 -> 0 | I136: ", "conv": [ | J136: ='Volume & Price List'!I139 -> 0 | K136: , | L136: ='Volume & Price List'!K139 -> 0 | N136: =CONCATENATE(B136,C136,D136,E136,F136,E136,G136,H136,I136,J136,K136,L136,M136) -> { "v": 0, "n": { "EN": "0", "SYS":"0 "}, "company": "0", "conv": [0,0
... B223: { "v": | C223: ='Volume & Price List'!A226 -> 0 | D223: , "n": { "EN": " | E223: ='Volume & Price List'!B226 -> 0 | F223: ", "SYS":" | G223: "}, "company": " | H223: ='Volume & Price List'!G226 -> 0 | I223: ", "conv": [ | J223: ='Volume & Price List'!I226 -> 0 | K223: , | L223: ='Volume & Price List'!K226 -> 0 | N223: =CONCATENATE(B223,C223,D223,E223,F223,E223,G223,H223,I223,J223,K223,L223,M223) -> { "v": 0, "n": { "EN": "0", "SYS":"0 "}, "company": "0", "conv": [0,0

Sheet Constraint
A1: Answer Options | E1: JSON Builders
A2: TEXT | E2: Name | F2: Code
A3: SYSTEM | E3: list-start | F3: { "v": "
A4: NOTE | E4: list-en | F4: ", "n" : { "SYS": "
A5: DATE & TIME | E5: list-la | F5: ", "EN": "
A6: PHOTOGRAPH | E6: list-end | F6: "} },
A7: SINGLE SELECTION | E7: single-quote | F7: "
A8: MULTIPLE SELECTION | E8: question-start | F8: :{ "n": { "SYS": "
A9: MULTIPLE SELECTION (min 1, max 2) | E9: qestion-la | F9: ", "EN": "
A10: MULTIPLE SELECTION (min 1, max 3) | E10: question-label | F10: }, "label": "
A11: MULTIPLE SELECTION (min 2, max 2) | E11: question-vis-enum | F11: , "o": [ "e" ],
A12: MULTIPLE SELECTION (max 3) | E12: question-ans-options
A13: MULITPLE SELECTION (allow to insert numbers) | E13: sku-company | F13: "}, "Company": "
A14: NUMERICAL | E14: sku-category | F14: ", "Category": "
A15: MULTIPLE NUMERICAL FIELDS | E15: sku-Packtype | F15: ", "Packtype": "
A16: GPS | E16: sku-Brand | F16: ", "Brand": "
A17: NUMERICAL (0 to 7) | E17: sku-conv | F17: ", "conv" : [
A18: NUMERICAL (0 to 52) | E18: sku-end | F18: ] },
A19: NUMERICAL (0 to 20) | E19: area-vis | F19: " }, "vi" : [ { "r": "A-10", "o": "=", "t": "v", "v": "
E20: area-vis-end | F20: " } ] },
E21: area-vis-lv2 | F21: " }, "vi" : [ { "r": "A-20", "o": "=", "t": "v", "v": "
E22: area-vis-lv3 | F22: " }, "vi" : [ { "r": "A-30", "o": "=", "t": "v", "v": "
F23: " }

Sheet JSON BuilderDistributor
B2: JSON | C2: ID | D2: JSON | E2: CHANNEL
B3: { "v": | C3: =+'I&M Lists'!#REF! -> #REF! | D3: , "n" : { "EN": " | E3: ='I&M Lists'!#REF! -> #REF! | F3: ", "SYS":" | G3: "} }, | H3: =CONCATENATE(B3,C3,D3,E3,F3,E3,G3) -> #REF!
B4: { "v": | C4: =+'I&M Lists'!#REF! -> #REF! | D4: , "n" : { "EN": " | E4: ='I&M Lists'!#REF! -> #REF! | F4: ", "SYS":" | G4: "} }, | H4: =CONCATENATE(B4,C4,D4,E4,F4,E4,G4) -> #REF!
B5: { "v": | C5: =+'I&M Lists'!#REF! -> #REF! | D5: , "n" : { "EN": " | E5: ='I&M Lists'!#REF! -> #REF! | F5: ", "SYS":" | G5: "} }, | H5: =CONCATENATE(B5,C5,D5,E5,F5,E5,G5) -> #REF!
B6: { "v": | C6: =+'I&M Lists'!#REF! -> #REF! | D6: , "n" : { "EN": " | E6: ='I&M Lists'!#REF! -> #REF! | F6: ", "SYS":" | G6: "} }, | H6: =CONCATENATE(B6,C6,D6,E6,F6,E6,G6) -> #REF!
B7: { "v": | C7: =+'I&M Lists'!#REF! -> #REF! | D7: , "n" : { "EN": " | E7: ='I&M Lists'!#REF! -> #REF! | F7: ", "SYS":" | G7: "} }, | H7: =CONCATENATE(B7,C7,D7,E7,F7,E7,G7) -> #REF!
B8: { "v": | C8: =+'I&M Lists'!#REF! -> #REF! | D8: , "n" : { "EN": " | E8: ='I&M Lists'!#REF! -> #REF! | F8: ", "SYS":" | G8: "} }, | H8: =CONCATENATE(B8,C8,D8,E8,F8,E8,G8) -> #REF!
B9: { "v": | C9: =+'I&M Lists'!#REF! -> #REF! | D9: , "n" : { "EN": " | E9: ='I&M Lists'!#REF! -> #REF! | F9: ", "SYS":" | G9: "} }, | H9: =CONCATENATE(B9,C9,D9,E9,F9,E9,G9) -> #REF!
B10: { "v": | C10: =+'I&M Lists'!#REF! -> #REF! | D10: , "n" : { "EN": " | E10: ='I&M Lists'!#REF! -> #REF! | F10: ", "SYS":" | G10: "} }, | H10: =CONCATENATE(B10,C10,D10,E10,F10,E10,G10) -> #REF!
B11: { "v": | C11: =+'I&M Lists'!#REF! -> #REF! | D11: , "n" : { "EN": " | E11: ='I&M Lists'!#REF! -> #REF! | F11: ", "SYS":" | G11: "} }, | H11: =CONCATENATE(B11,C11,D11,E11,F11,E11,G11) -> #REF!
B12: { "v": | C12: =+'I&M Lists'!#REF! -> #REF! | D12: , "n" : { "EN": " | E12: ='I&M Lists'!#REF! -> #REF! | F12: ", "SYS":" | G12: "} }, | H12: =CONCATENATE(B12,C12,D12,E12,F12,E12,G12) -> #REF!
B13: { "v": | C13: =+'I&M Lists'!#REF! -> #REF! | D13: , "n" : { "EN": " | E13: ='I&M Lists'!#REF! -> #REF! | F13: ", "SYS":" | G13: "} }, | H13: =CONCATENATE(B13,C13,D13,E13,F13,E13,G13) -> #REF!
B14: { "v": | C14: =+'I&M Lists'!#REF! -> #REF! | D14: , "n" : { "EN": " | E14: ='I&M Lists'!#REF! -> #REF! | F14: ", "SYS":" | G14: "} }, | H14: =CONCATENATE(B14,C14,D14,E14,F14,E14,G14) -> #REF!
... B16: { "v": | C16: =+'I&M Lists'!#REF! -> #REF! | D16: , "n" : { "EN": " | E16: ='I&M Lists'!#REF! -> #REF! | F16: ", "SYS":" | G16: "} }, | H16: =CONCATENATE(B16,C16,D16,E16,F16,E16,G16) -> #REF!
B19: { "v": | C19: ='I&M Lists'!B78 -> 1 | D19: , "n" : { "EN": " | E19: ='I&M Lists'!E78 -> Alotau Enterprises | F19: ", "SYS":" | G19: "} }, | H19: =CONCATENATE(B19,C19,D19,E19,F19,E19,G19) -> { "v": 1, "n" : { "EN": "Alotau Enterprises", "SYS":"Alotau Enterprises"} },
B20: { "v": | C20: ='I&M Lists'!B79 -> 2 | D20: , "n" : { "EN": " | E20: ='I&M Lists'!E79 -> Andersons Foodland - Kpo | F20: ", "SYS":" | G20: "} }, | H20: =CONCATENATE(B20,C20,D20,E20,F20,E20,G20) -> { "v": 2, "n" : { "EN": "Andersons Foodland - Kpo", "SYS":"Andersons Foodland - Kpo"} },
B21: { "v": | C21: ='I&M Lists'!B80 -> 3 | D21: , "n" : { "EN": " | E21: ='I&M Lists'!E80 -> Andersons Foodland Lae | F21: ", "SYS":" | G21: "} }, | H21: =CONCATENATE(B21,C21,D21,E21,F21,E21,G21) -> { "v": 3, "n" : { "EN": "Andersons Foodland Lae", "SYS":"Andersons Foodland Lae"} },
B22: { "v": | C22: ='I&M Lists'!B81 -> 4 | D22: , "n" : { "EN": " | E22: ='I&M Lists'!E81 -> Auskoa Limited | F22: ", "SYS":" | G22: "} }, | H22: =CONCATENATE(B22,C22,D22,E22,F22,E22,G22) -> { "v": 4, "n" : { "EN": "Auskoa Limited", "SYS":"Auskoa Limited"} },
B23: { "v": | C23: ='I&M Lists'!#REF! -> #REF! | D23: , "n" : { "EN": " | E23: ='I&M Lists'!#REF! -> #REF! | F23: ", "SYS":" | G23: "} }, | H23: =CONCATENATE(B23,C23,D23,E23,F23,E23,G23) -> #REF!
B24: { "v": | C24: ='I&M Lists'!#REF! -> #REF! | D24: , "n" : { "EN": " | E24: ='I&M Lists'!#REF! -> #REF! | F24: ", "SYS":" | G24: "} }, | H24: =CONCATENATE(B24,C24,D24,E24,F24,E24,G24) -> #REF!
B25: { "v": | C25: ='I&M Lists'!#REF! -> #REF! | D25: , "n" : { "EN": " | E25: ='I&M Lists'!#REF! -> #REF! | F25: ", "SYS":" | G25: "} }, | H25: =CONCATENATE(B25,C25,D25,E25,F25,E25,G25) -> #REF!
B26: { "v": | C26: ='I&M Lists'!#REF! -> #REF! | D26: , "n" : { "EN": " | E26: ='I&M Lists'!#REF! -> #REF! | F26: ", "SYS":" | G26: "} }, | H26: =CONCATENATE(B26,C26,D26,E26,F26,E26,G26) -> #REF!
B27: { "v": | C27: ='I&M Lists'!#REF! -> #REF! | D27: , "n" : { "EN": " | E27: ='I&M Lists'!#REF! -> #REF! | F27: ", "SYS":" | G27: "} }, | H27: =CONCATENATE(B27,C27,D27,E27,F27,E27,G27) -> #REF!
B28: { "v": | C28: ='I&M Lists'!#REF! -> #REF! | D28: , "n" : { "EN": " | E28: ='I&M Lists'!#REF! -> #REF! | F28: ", "SYS":" | G28: "} }, | H28: =CONCATENATE(B28,C28,D28,E28,F28,E28,G28) -> #REF!
B29: { "v": | C29: ='I&M Lists'!#REF! -> #REF! | D29: , "n" : { "EN": " | E29: ='I&M Lists'!#REF! -> #REF! | F29: ", "SYS":" | G29: "} }, | H29: =CONCATENATE(B29,C29,D29,E29,F29,E29,G29) -> #REF!
B30: { "v": | C30: ='I&M Lists'!#REF! -> #REF! | D30: , "n" : { "EN": " | E30: ='I&M Lists'!#REF! -> #REF! | F30: ", "SYS":" | G30: "} }, | H30: =CONCATENATE(B30,C30,D30,E30,F30,E30,G30) -> #REF!
B31: { "v": | C31: ='I&M Lists'!#REF! -> #REF! | D31: , "n" : { "EN": " | E31: ='I&M Lists'!#REF! -> #REF! | F31: ", "SYS":" | G31: "} }, | H31: =CONCATENATE(B31,C31,D31,E31,F31,E31,G31) -> #REF!
B32: { "v": | C32: ='I&M Lists'!#REF! -> #REF! | D32: , "n" : { "EN": " | E32: ='I&M Lists'!#REF! -> #REF! | F32: ", "SYS":" | G32: "} }, | H32: =CONCATENATE(B32,C32,D32,E32,F32,E32,G32) -> #REF!
B33: { "v": | C33: ='I&M Lists'!#REF! -> #REF! | D33: , "n" : { "EN": " | E33: ='I&M Lists'!#REF! -> #REF! | F33: ", "SYS":" | G33: "} }, | H33: =CONCATENATE(B33,C33,D33,E33,F33,E33,G33) -> #REF!
B34: { "v": | C34: ='I&M Lists'!#REF! -> #REF! | D34: , "n" : { "EN": " | E34: ='I&M Lists'!#REF! -> #REF! | F34: ", "SYS":" | G34: "} }, | H34: =CONCATENATE(B34,C34,D34,E34,F34,E34,G34) -> #REF!
... B82: { "v": | C82: ='I&M Lists'!#REF! -> #REF! | D82: , "n" : { "EN": " | E82: ='I&M Lists'!#REF! -> #REF! | F82: ", "SYS":" | G82: "} }, | H82: =CONCATENATE(B82,C82,D82,E82,F82,E82,G82) -> #REF!

Sheet JSON BuilderChannels
B1: ON-TRADE
B2: JSON | C2: ID | D2: JSON | E2: CHANNEL
B3: { "v": " | C3: ='I&M Lists'!#REF! -> #REF! | D3: ", "n" : { "EN": " | E3: ='I&M Lists'!#REF! -> #REF! | F3: "} }, | G3: =CONCATENATE(B3,C3,D3,E3,F3) -> #REF!
B4: { "v": " | C4: ='I&M Lists'!#REF! -> #REF! | D4: ", "n" : { "EN": " | E4: ='I&M Lists'!#REF! -> #REF! | F4: "} }, | G4: =CONCATENATE(B4,C4,D4,E4,F4) -> #REF!
B5: { "v": " | C5: ='I&M Lists'!#REF! -> #REF! | D5: ", "n" : { "EN": " | E5: ='I&M Lists'!#REF! -> #REF! | F5: "} }, | G5: =CONCATENATE(B5,C5,D5,E5,F5) -> #REF!
B6: { "v": " | C6: ='I&M Lists'!#REF! -> #REF! | D6: ", "n" : { "EN": " | E6: ='I&M Lists'!#REF! -> #REF! | F6: "} }, | G6: =CONCATENATE(B6,C6,D6,E6,F6) -> #REF!
B7: { "v": " | C7: ='I&M Lists'!#REF! -> #REF! | D7: ", "n" : { "EN": " | E7: ='I&M Lists'!#REF! -> #REF! | F7: "} }, | G7: =CONCATENATE(B7,C7,D7,E7,F7) -> #REF!
B8: { "v": " | C8: ='I&M Lists'!#REF! -> #REF! | D8: ", "n" : { "EN": " | E8: ='I&M Lists'!#REF! -> #REF! | F8: "} }, | G8: =CONCATENATE(B8,C8,D8,E8,F8) -> #REF!
B9: { "v": " | C9: ='I&M Lists'!#REF! -> #REF! | D9: ", "n" : { "EN": " | E9: ='I&M Lists'!#REF! -> #REF! | F9: "} }, | G9: =CONCATENATE(B9,C9,D9,E9,F9) -> #REF!
B10: { "v": " | C10: ='I&M Lists'!#REF! -> #REF! | D10: ", "n" : { "EN": " | E10: ='I&M Lists'!#REF! -> #REF! | F10: "} }, | G10: =CONCATENATE(B10,C10,D10,E10,F10) -> #REF!
B11: { "v": " | C11: ='I&M Lists'!#REF! -> #REF! | D11: ", "n" : { "EN": " | E11: ='I&M Lists'!#REF! -> #REF! | F11: "} }, | G11: =CONCATENATE(B11,C11,D11,E11,F11) -> #REF!
B12: { "v": " | C12: ='I&M Lists'!#REF! -> #REF! | D12: ", "n" : { "EN": " | E12: ='I&M Lists'!#REF! -> #REF! | F12: "} }, | G12: =CONCATENATE(B12,C12,D12,E12,F12) -> #REF!
B13: { "v": " | C13: ='I&M Lists'!#REF! -> #REF! | D13: ", "n" : { "EN": " | E13: ='I&M Lists'!#REF! -> #REF! | F13: "} }, | G13: =CONCATENATE(B13,C13,D13,E13,F13) -> #REF!
B16: OFF-TRADE
B17: JSON | C17: ID | D17: JSON | E17: CHANNEL
B18: { "v": " | C18: ='I&M Lists'!#REF! -> #REF! | D18: ", "n" : { "EN": " | E18: ='I&M Lists'!#REF! -> #REF! | F18: "} }, | G18: =CONCATENATE(B18,C18,D18,E18,F18) -> #REF!
B19: { "v": " | C19: ='I&M Lists'!#REF! -> #REF! | D19: ", "n" : { "EN": " | E19: ='I&M Lists'!#REF! -> #REF! | F19: "} }, | G19: =CONCATENATE(B19,C19,D19,E19,F19) -> #REF!
B20: { "v": " | C20: ='I&M Lists'!#REF! -> #REF! | D20: ", "n" : { "EN": " | E20: ='I&M Lists'!#REF! -> #REF! | F20: "} }, | G20: =CONCATENATE(B20,C20,D20,E20,F20) -> #REF!
B21: { "v": " | C21: ='I&M Lists'!#REF! -> #REF! | D21: ", "n" : { "EN": " | E21: ='I&M Lists'!#REF! -> #REF! | F21: "} }, | G21: =CONCATENATE(B21,C21,D21,E21,F21) -> #REF!
B22: { "v": " | C22: ='I&M Lists'!#REF! -> #REF! | D22: ", "n" : { "EN": " | E22: ='I&M Lists'!#REF! -> #REF! | F22: "} }, | G22: =CONCATENATE(B22,C22,D22,E22,F22) -> #REF!
B23: { "v": " | C23: ='I&M Lists'!#REF! -> #REF! | D23: ", "n" : { "EN": " | E23: ='I&M Lists'!#REF! -> #REF! | F23: "} }, | G23: =CONCATENATE(B23,C23,D23,E23,F23) -> #REF!
B24: { "v": " | C24: ='I&M Lists'!#REF! -> #REF! | D24: ", "n" : { "EN": " | E24: ='I&M Lists'!#REF! -> #REF! | F24: "} }, | G24: =CONCATENATE(B24,C24,D24,E24,F24) -> #REF!
B27: RTM
B28: JSON | C28: ID | D28: JSON | E28: CHANNEL
B29: { "v": " | C29: ='I&M Lists'!#REF! -> #REF! | D29: ", "n" : { "EN": " | E29: ='I&M Lists'!#REF! -> #REF! | F29: "} }, | G29: =CONCATENATE(B29,C29,D29,E29,F29) -> #REF!
B30: { "v": " | C30: ='I&M Lists'!#REF! -> #REF! | D30: ", "n" : { "EN": " | E30: ='I&M Lists'!#REF! -> #REF! | F30: "} }, | G30: =CONCATENATE(B30,C30,D30,E30,F30) -> #REF!
B31: { "v": " | C31: ='I&M Lists'!#REF! -> #REF! | D31: ", "n" : { "EN": " | E31: ='I&M Lists'!#REF! -> #REF! | F31: "} }, | G31: =CONCATENATE(B31,C31,D31,E31,F31) -> #REF!
B32: { "v": " | C32: ='I&M Lists'!#REF! -> #REF! | D32: ", "n" : { "EN": " | E32: ='I&M Lists'!#REF! -> #REF! | F32: "} }, | G32: =CONCATENATE(B32,C32,D32,E32,F32) -> #REF!
B33: { "v": " | C33: ='I&M Lists'!#REF! -> #REF! | D33: ", "n" : { "EN": " | E33: ='I&M Lists'!#REF! -> #REF! | F33: "} }, | G33: =CONCATENATE(B33,C33,D33,E33,F33) -> #REF!
